Workbook

Sheet Sum
A1: Item Code | B1: Product Name | C1: 46125 | D1: Purchased | E1: Arrived | F1: Sales Order | G1: Cons. | H1: OH Stock | I1: In-Transit | J1: On Hold | K1: Alloc. | L1: Avail. | M1: Total Stock | N1: ABC | O1: Wkly Fcst. | P1: OH TO | Q1: Inv. TO | R1: LT | S1: SS | T1: Extra | U1: MOQ | V1: Plan | W1: LA Plan | X1: HOU Plan | Y1: Case Pack | Z1: Channel | AA1: Case Type | AB1: Case Qty | AC1: CBM
A2: BOBO22-GN | B2: =_xlfn.XLOOKUP(A2,'Product List'!B:B,'Product List'!I:I) -> MINI/MOE SILENT CRSTL RUN WHEEL LG 8.5-Green | C2: 0 | D2: =SUMIFS(Purchase!F:F,Purchase!C:C,A2,Purchase!I:I,">"&$C$1,Purchase!V:V,"<>暂缓发货") -> 744 | E2: =SUMIFS(Purchase!F:F,Purchase!C:C,A2,Purchase!J:J,">0",Purchase!I:I,">"&$C$1) -> 744 | F2: =SUMIFS(Sales!E:E,Sales!C:C,A2,Sales!K:K,">"&$C$1) -> 376 | G2: =SUMIFS(Sales!E:E,Sales!C:C,A2,Sales!K:K,">"&$C$1,Sales!L:L,">0") -> 368 | H2: =C2+E2-G2-SUMIFS(Transfer!V:V,Transfer!O:O,A2)+SUMIFS(Transfer!W:W,Transfer!O:O,A2) -> 376 | I2: =D2-E2+SUMIFS(Transfer!V:V,Transfer!O:O,A2)-SUMIFS(Transfer!W:W,Transfer!O:O,A2) -> 0 | J2: =SUMIFS(Purchase!F:F,Purchase!C:C,A2,Purchase!V:V,"暂缓发货") -> 0 | K2: =F2-G2 -> 8 | L2: =H2-K2 -> 368 | M2: =H2+I2-K2 -> 368 | N2: =_xlfn.XLOOKUP(A2,'Product List'!B:B,'Product List'!F:F) -> C | O2: =SUMIF('Weekly Sales'!B:B,A2,'Weekly Sales'!R:R) -> 12.666667 | P2: =IF(O2=0,999,ROUNDDOWN((L2)/O2,0)) -> 29 | Q2: =IF(O2=0,999,ROUNDDOWN((M2)/O2,0)) -> 29 | R2: =_xlfn.XLOOKUP(A2,'Product List'!B:B,'Product List'!P:P) -> 10 | S2: =IF(N2="A",6,IF(N2="B",5,2)) -> 2 | T2: =SUMIF('Weekly Sales'!B:B,A2,'Weekly Sales'!T:T) -> 0 | U2: =_xlfn.XLOOKUP(A2,'Product List'!B:B,'Product List'!O:O) -> 1000 | V2: =ROUNDUP(MAX(0,O2*(R2+S2+2)+T2-M2)/Y2,0)*Y2 -> 0 | W2: =_xlfn.XLOOKUP(A2,Sum_LA!A:A,Sum_LA!V:V) -> 0 | X2: =_xlfn.XLOOKUP(A2,Sum_HOU!A:A,Sum_HOU!V:V) -> 192 | Y2: {=_xlfn.XLOOKUP(1,('Case Pack'!A:A=A2)*('Case Pack'!F:F<=TODAY()),'Case Pack'!D:D,"未找到箱规")} -> 16 | Z2: =_xlfn.XLOOKUP(A2,'Product List'!B:B,'Product List'!M:M) -> PSP | AA2: {=_xlfn.XLOOKUP(1,('Case Pack'!A:A=A2)*('Case Pack'!F:F<=TODAY()),'Case Pack'!G:G,"未找到箱规")} -> C | AB2: =V2/Y2 -> 0 | AC2: =_xlfn.XLOOKUP(AA2,'Case Type'!A:A,'Case Type'!H:H)*AB2 -> 0
A3: BOBO22-WH | B3: =_xlfn.XLOOKUP(A3,'Product List'!B:B,'Product List'!I:I) -> MINI/MOE SILENT CRSTL RUN WHEEL LG 8.5-White | C3: 412 | D3: =SUMIFS(Purchase!F:F,Purchase!C:C,A3,Purchase!I:I,">"&$C$1,Purchase!V:V,"<>暂缓发货") -> 7336 | E3: =SUMIFS(Purchase!F:F,Purchase!C:C,A3,Purchase!J:J,">0",Purchase!I:I,">"&$C$1) -> 7336 | F3: =SUMIFS(Sales!E:E,Sales!C:C,A3,Sales!K:K,">"&$C$1) -> 4748 | G3: =SUMIFS(Sales!E:E,Sales!C:C,A3,Sales!K:K,">"&$C$1,Sales!L:L,">0") -> 3876 | H3: =C3+E3-G3-SUMIFS(Transfer!V:V,Transfer!O:O,A3)+SUMIFS(Transfer!W:W,Transfer!O:O,A3) -> 3872 | I3: =D3-E3+SUMIFS(Transfer!V:V,Transfer!O:O,A3)-SUMIFS(Transfer!W:W,Transfer!O:O,A3) -> 0 | J3: =SUMIFS(Purchase!F:F,Purchase!C:C,A3,Purchase!V:V,"暂缓发货") -> 1352 | K3: =F3-G3 -> 872 | L3: =H3-K3 -> 3000 | M3: =H3+I3-K3 -> 3000 | N3: =_xlfn.XLOOKUP(A3,'Product List'!B:B,'Product List'!F:F) -> A | O3: =SUMIF('Weekly Sales'!B:B,A3,'Weekly Sales'!R:R) -> 95.5 | P3: =IF(O3=0,999,ROUNDDOWN((L3)/O3,0)) -> 31 | Q3: =IF(O3=0,999,ROUNDDOWN((M3)/O3,0)) -> 31 | R3: =_xlfn.XLOOKUP(A3,'Product List'!B:B,'Product List'!P:P) -> 10 | S3: =IF(N3="A",6,IF(N3="B",5,2)) -> 6 | T3: =SUMIF('Weekly Sales'!B:B,A3,'Weekly Sales'!T:T) -> 620.75 | U3: =_xlfn.XLOOKUP(A3,'Product List'!B:B,'Product List'!O:O) -> 1000 | V3: =ROUNDUP(MAX(0,O3*(R3+S3+2)+T3-M3)/Y3,0)*Y3 -> 0 | W3: =_xlfn.XLOOKUP(A3,Sum_LA!A:A,Sum_LA!V:V) -> 0 | X3: =_xlfn.XLOOKUP(A3,Sum_HOU!A:A,Sum_HOU!V:V) -> 0 | Y3: {=_xlfn.XLOOKUP(1,('Case Pack'!A:A=A3)*('Case Pack'!F:F<=TODAY()),'Case Pack'!D:D,"未找到箱规")} -> 16 | Z3: =_xlfn.XLOOKUP(A3,'Product List'!B:B,'Product List'!M:M) -> PetcoUS, PetcoMX, Pet Supermarket，PSP | AA3: {=_xlfn.XLOOKUP(1,('Case Pack'!A:A=A3)*('Case Pack'!F:F<=TODAY()),'Case Pack'!G:G,"未找到箱规")} -> C | AB3: =V3/Y3 -> 0 | AC3: =_xlfn.XLOOKUP(AA3,'Case Type'!A:A,'Case Type'!H:H)*AB3 -> 0
A4: CFDL1090-BR | B4: =_xlfn.XLOOKUP(A4,'Product List'!B:B,'Product List'!I:I) -> MINI/MOE SMALL ANIMAL BEDDING CRINKLE PAPER BROWN 1EA | C4: 0 | D4: =SUMIFS(Purchase!F:F,Purchase!C:C,A4,Purchase!I:I,">"&$C$1,Purchase!V:V,"<>暂缓发货") -> 1260 | E4: =SUMIFS(Purchase!F:F,Purchase!C:C,A4,Purchase!J:J,">0",Purchase!I:I,">"&$C$1) -> 1260 | F4: =SUMIFS(Sales!E:E,Sales!C:C,A4,Sales!K:K,">"&$C$1) -> 630 | G4: =SUMIFS(Sales!E:E,Sales!C:C,A4,Sales!K:K,">"&$C$1,Sales!L:L,">0") -> 630 | H4: =C4+E4-G4-SUMIFS(Transfer!V:V,Transfer!O:O,A4)+SUMIFS(Transfer!W:W,Transfer!O:O,A4) -> 630 | I4: =D4-E4+SUMIFS(Transfer!V:V,Transfer!O:O,A4)-SUMIFS(Transfer!W:W,Transfer!O:O,A4) -> 0 | J4: =SUMIFS(Purchase!F:F,Purchase!C:C,A4,Purchase!V:V,"暂缓发货") -> 0 | K4: =F4-G4 -> 0 | L4: =H4-K4 -> 630 | M4: =H4+I4-K4 -> 630 | N4: =_xlfn.XLOOKUP(A4,'Product List'!B:B,'Product List'!F:F) -> C | O4: =SUMIF('Weekly Sales'!B:B,A4,'Weekly Sales'!R:R) -> 6 | P4: =IF(O4=0,999,ROUNDDOWN((L4)/O4,0)) -> 105 | Q4: =IF(O4=0,999,ROUNDDOWN((M4)/O4,0)) -> 105 | R4: =_xlfn.XLOOKUP(A4,'Product List'!B:B,'Product List'!P:P) -> 10 | S4: =IF(N4="A",6,IF(N4="B",5,2)) -> 2 | T4: =SUMIF('Weekly Sales'!B:B,A4,'Weekly Sales'!T:T) -> 0 | U4: =_xlfn.XLOOKUP(A4,'Product List'!B:B,'Product List'!O:O) -> 1000 | V4: =ROUNDUP(MAX(0,O4*(R4+S4+2)+T4-M4)/Y4,0)*Y4 -> 0 | W4: =_xlfn.XLOOKUP(A4,Sum_LA!A:A,Sum_LA!V:V) -> 0 | X4: =_xlfn.XLOOKUP(A4,Sum_HOU!A:A,Sum_HOU!V:V) -> 90 | Y4: {=_xlfn.XLOOKUP(1,('Case Pack'!A:A=A4)*('Case Pack'!F:F<=TODAY()),'Case Pack'!D:D,"未找到箱规")} -> 30 | Z4: =_xlfn.XLOOKUP(A4,'Product List'!B:B,'Product List'!M:M) -> PSP | AA4: {=_xlfn.XLOOKUP(1,('Case Pack'!A:A=A4)*('Case Pack'!F:F<=TODAY()),'Case Pack'!G:G,"未找到箱规")} -> A | AB4: =V4/Y4 -> 0 | AC4: =_xlfn.XLOOKUP(AA4,'Case Type'!A:A,'Case Type'!H:H)*AB4 -> 0
A5: CFDL1090-PK | B5: =_xlfn.XLOOKUP(A5,'Product List'!B:B,'Product List'!I:I) -> MINI/MOE SMALL ANIMAL BEDDING PAPER PEBBLES PSTCH/CREAM 1EA | C5: 0 | D5: =SUMIFS(Purchase!F:F,Purchase!C:C,A5,Purchase!I:I,">"&$C$1,Purchase!V:V,"<>暂缓发货") -> 1260 | E5: =SUMIFS(Purchase!F:F,Purchase!C:C,A5,Purchase!J:J,">0",Purchase!I:I,">"&$C$1) -> 1260 | F5: =SUMIFS(Sales!E:E,Sales!C:C,A5,Sales!K:K,">"&$C$1) -> 630 | G5: =SUMIFS(Sales!E:E,Sales!C:C,A5,Sales!K:K,">"&$C$1,Sales!L:L,">0") -> 630 | H5: =C5+E5-G5-SUMIFS(Transfer!V:V,Transfer!O:O,A5)+SUMIFS(Transfer!W:W,Transfer!O:O,A5) -> 630 | I5: =D5-E5+SUMIFS(Transfer!V:V,Transfer!O:O,A5)-SUMIFS(Transfer!W:W,Transfer!O:O,A5) -> 0 | J5: =SUMIFS(Purchase!F:F,Purchase!C:C,A5,Purchase!V:V,"暂缓发货") -> 0 | K5: =F5-G5 -> 0 | L5: =H5-K5 -> 630 | M5: =H5+I5-K5 -> 630 | N5: =_xlfn.XLOOKUP(A5,'Product List'!B:B,'Product List'!F:F) -> C | O5: =SUMIF('Weekly Sales'!B:B,A5,'Weekly Sales'!R:R) -> 1.3333333 | P5: =IF(O5=0,999,ROUNDDOWN((L5)/O5,0)) -> 472 | Q5: =IF(O5=0,999,ROUNDDOWN((M5)/O5,0)) -> 472 | R5: =_xlfn.XLOOKUP(A5,'Product List'!B:B,'Product List'!P:P) -> 10 | S5: =IF(N5="A",6,IF(N5="B",5,2)) -> 2 | T5: =SUMIF('Weekly Sales'!B:B,A5,'Weekly Sales'!T:T) -> 0 | U5: =_xlfn.XLOOKUP(A5,'Product List'!B:B,'Product List'!O:O) -> 1000 | V5: =ROUNDUP(MAX(0,O5*(R5+S5+2)+T5-M5)/Y5,0)*Y5 -> 0 | W5: =_xlfn.XLOOKUP(A5,Sum_LA!A:A,Sum_LA!V:V) -> 0 | X5: =_xlfn.XLOOKUP(A5,Sum_HOU!A:A,Sum_HOU!V:V) -> 30 | Y5: {=_xlfn.XLOOKUP(1,('Case Pack'!A:A=A5)*('Case Pack'!F:F<=TODAY()),'Case Pack'!D:D,"未找到箱规")} -> 30 | Z5: =_xlfn.XLOOKUP(A5,'Product List'!B:B,'Product List'!M:M) -> PSP | AA5: {=_xlfn.XLOOKUP(1,('Case Pack'!A:A=A5)*('Case Pack'!F:F<=TODAY()),'Case Pack'!G:G,"未找到箱规")} -> A | AB5: =V5/Y5 -> 0 | AC5: =_xlfn.XLOOKUP(AA5,'Case Type'!A:A,'Case Type'!H:H)*AB5 -> 0
A6: CFDL9000-GN-YL | B6: =_xlfn.XLOOKUP(A6,'Product List'!B:B,'Product List'!I:I) -> MINI/MOE SMALL ANIMAL BEDDING ROLLED PAPER FOREST MIX 1EA | C6: 0 | D6: =SUMIFS(Purchase!F:F,Purchase!C:C,A6,Purchase!I:I,">"&$C$1,Purchase!V:V,"<>暂缓发货") -> 3420 | E6: =SUMIFS(Purchase!F:F,Purchase!C:C,A6,Purchase!J:J,">0",Purchase!I:I,">"&$C$1) -> 3420 | F6: =SUMIFS(Sales!E:E,Sales!C:C,A6,Sales!K:K,">"&$C$1) -> 2040 | G6: =SUMIFS(Sales!E:E,Sales!C:C,A6,Sales!K:K,">"&$C$1,Sales!L:L,">0") -> 2040 | H6: =C6+E6-G6-SUMIFS(Transfer!V:V,Transfer!O:O,A6)+SUMIFS(Transfer!W:W,Transfer!O:O,A6) -> 1380 | I6: =D6-E6+SUMIFS(Transfer!V:V,Transfer!O:O,A6)-SUMIFS(Transfer!W:W,Transfer!O:O,A6) -> 0 | J6: =SUMIFS(Purchase!F:F,Purchase!C:C,A6,Purchase!V:V,"暂缓发货") -> 0 | K6: =F6-G6 -> 0 | L6: =H6-K6 -> 1380 | M6: =H6+I6-K6 -> 1380 | N6: =_xlfn.XLOOKUP(A6,'Product List'!B:B,'Product List'!F:F) -> B | O6: =SUMIF('Weekly Sales'!B:B,A6,'Weekly Sales'!R:R) -> 4 | P6: =IF(O6=0,999,ROUNDDOWN((L6)/O6,0)) -> 345 | Q6: =IF(O6=0,999,ROUNDDOWN((M6)/O6,0)) -> 345 | R6: =_xlfn.XLOOKUP(A6,'Product List'!B:B,'Product List'!P:P) -> 10 | S6: =IF(N6="A",6,IF(N6="B",5,2)) -> 5 | T6: =SUMIF('Weekly Sales'!B:B,A6,'Weekly Sales'!T:T) -> 21 | U6: =_xlfn.XLOOKUP(A6,'Product List'!B:B,'Product List'!O:O) -> 1000 | V6: =ROUNDUP(MAX(0,O6*(R6+S6+2)+T6-M6)/Y6,0)*Y6 -> 0 | W6: =_xlfn.XLOOKUP(A6,Sum_LA!A:A,Sum_LA!V:V) -> 0 | X6: =_xlfn.XLOOKUP(A6,Sum_HOU!A:A,Sum_HOU!V:V) -> 90 | Y6: {=_xlfn.XLOOKUP(1,('Case Pack'!A:A=A6)*('Case Pack'!F:F<=TODAY()),'Case Pack'!D:D,"未找到箱规")} -> 30 | Z6: =_xlfn.XLOOKUP(A6,'Product List'!B:B,'Product List'!M:M) -> PSP | AA6: {=_xlfn.XLOOKUP(1,('Case Pack'!A:A=A6)*('Case Pack'!F:F<=TODAY()),'Case Pack'!G:G,"未找到箱规")} -> A | AB6: =V6/Y6 -> 0 | AC6: =_xlfn.XLOOKUP(AA6,'Case Type'!A:A,'Case Type'!H:H)*AB6 -> 0
A7: CFLS18000 | B7: =_xlfn.XLOOKUP(A7,'Product List'!B:B,'Product List'!I:I) -> MMO-GREEN APPLE CHEW | C7: 0 | D7: =SUMIFS(Purchase!F:F,Purchase!C:C,A7,Purchase!I:I,">"&$C$1,Purchase!V:V,"<>暂缓发货") -> 9936 | E7: =SUMIFS(Purchase!F:F,Purchase!C:C,A7,Purchase!J:J,">0",Purchase!I:I,">"&$C$1) -> 9936 | F7: =SUMIFS(Sales!E:E,Sales!C:C,A7,Sales!K:K,">"&$C$1) -> 5568 | G7: =SUMIFS(Sales!E:E,Sales!C:C,A7,Sales!K:K,">"&$C$1,Sales!L:L,">0") -> 4560 | H7: =C7+E7-G7-SUMIFS(Transfer!V:V,Transfer!O:O,A7)+SUMIFS(Transfer!W:W,Transfer!O:O,A7) -> 5376 | I7: =D7-E7+SUMIFS(Transfer!V:V,Transfer!O:O,A7)-SUMIFS(Transfer!W:W,Transfer!O:O,A7) -> 0 | J7: =SUMIFS(Purchase!F:F,Purchase!C:C,A7,Purchase!V:V,"暂缓发货") -> 2112 | K7: =F7-G7 -> 1008 | L7: =H7-K7 -> 4368 | M7: =H7+I7-K7 -> 4368 | N7: =_xlfn.XLOOKUP(A7,'Product List'!B:B,'Product List'!F:F) -> B | O7: =SUMIF('Weekly Sales'!B:B,A7,'Weekly Sales'!R:R) -> 150.16667 | P7: =IF(O7=0,999,ROUNDDOWN((L7)/O7,0)) -> 29 | Q7: =IF(O7=0,999,ROUNDDOWN((M7)/O7,0)) -> 29 | R7: =_xlfn.XLOOKUP(A7,'Product List'!B:B,'Product List'!P:P) -> 10 | S7: =IF(N7="A",6,IF(N7="B",5,2)) -> 5 | T7: =SUMIF('Weekly Sales'!B:B,A7,'Weekly Sales'!T:T) -> 498.70833 | U7: =_xlfn.XLOOKUP(A7,'Product List'!B:B,'Product List'!O:O) -> 1000 | V7: =ROUNDUP(MAX(0,O7*(R7+S7+2)+T7-M7)/Y7,0)*Y7 -> 0 | W7: =_xlfn.XLOOKUP(A7,Sum_LA!A:A,Sum_LA!V:V) -> 0 | X7: =_xlfn.XLOOKUP(A7,Sum_HOU!A:A,Sum_HOU!V:V) -> 144 | Y7: {=_xlfn.XLOOKUP(1,('Case Pack'!A:A=A7)*('Case Pack'!F:F<=TODAY()),'Case Pack'!D:D,"未找到箱规")} -> 48 | Z7: =_xlfn.XLOOKUP(A7,'Product List'!B:B,'Product List'!M:M) -> PetcoUS，PSP | AA7: {=_xlfn.XLOOKUP(1,('Case Pack'!A:A=A7)*('Case Pack'!F:F<=TODAY()),'Case Pack'!G:G,"未找到箱规")} -> B | AB7: =V7/Y7 -> 0 | AC7: =_xlfn.XLOOKUP(AA7,'Case Type'!A:A,'Case Type'!H:H)*AB7 -> 0
A8: CFLS64000YE | B8: =_xlfn.XLOOKUP(A8,'Product List'!B:B,'Product List'!I:I) -> MMO-CAMP LUNCH BOX CHEW | C8: 0 | D8: =SUMIFS(Purchase!F:F,Purchase!C:C,A8,Purchase!I:I,">"&$C$1,Purchase!V:V,"<>暂缓发货") -> 10800 | E8: =SUMIFS(Purchase!F:F,Purchase!C:C,A8,Purchase!J:J,">0",Purchase!I:I,">"&$C$1) -> 10800 | F8: =SUMIFS(Sales!E:E,Sales!C:C,A8,Sales!K:K,">"&$C$1) -> 6768 | G8: =SUMIFS(Sales!E:E,Sales!C:C,A8,Sales!K:K,">"&$C$1,Sales!L:L,">0") -> 5616 | H8: =C8+E8-G8-SUMIFS(Transfer!V:V,Transfer!O:O,A8)+SUMIFS(Transfer!W:W,Transfer!O:O,A8) -> 5184 | I8: =D8-E8+SUMIFS(Transfer!V:V,Transfer!O:O,A8)-SUMIFS(Transfer!W:W,Transfer!O:O,A8) -> 0 | J8: =SUMIFS(Purchase!F:F,Purchase!C:C,A8,Purchase!V:V,"暂缓发货") -> 2160 | K8: =F8-G8 -> 1152 | L8: =H8-K8 -> 4032 | M8: =H8+I8-K8 -> 4032 | N8: =_xlfn.XLOOKUP(A8,'Product List'!B:B,'Product List'!F:F) -> B | O8: =SUMIF('Weekly Sales'!B:B,A8,'Weekly Sales'!R:R) -> 167.83333 | P8: =IF(O8=0,999,ROUNDDOWN((L8)/O8,0)) -> 24 | Q8: =IF(O8=0,999,ROUNDDOWN((M8)/O8,0)) -> 24 | R8: =_xlfn.XLOOKUP(A8,'Product List'!B:B,'Product List'!P:P) -> 10 | S8: =IF(N8="A",6,IF(N8="B",5,2)) -> 5 | T8: =SUMIF('Weekly Sales'!B:B,A8,'Weekly Sales'!T:T) -> 560.45833 | U8: =_xlfn.XLOOKUP(A8,'Product List'!B:B,'Product List'!O:O) -> 1000 | V8: =ROUNDUP(MAX(0,O8*(R8+S8+2)+T8-M8)/Y8,0)*Y8 -> 0 | W8: =_xlfn.XLOOKUP(A8,Sum_LA!A:A,Sum_LA!V:V) -> 0 | X8: =_xlfn.XLOOKUP(A8,Sum_HOU!A:A,Sum_HOU!V:V) -> 216 | Y8: {=_xlfn.XLOOKUP(1,('Case Pack'!A:A=A8)*('Case Pack'!F:F<=TODAY()),'Case Pack'!D:D,"未找到箱规")} -> 72 | Z8: =_xlfn.XLOOKUP(A8,'Product List'!B:B,'Product List'!M:M) -> PetcoUS, Pet Supermarket，PSP | AA8: {=_xlfn.XLOOKUP(1,('Case Pack'!A:A=A8)*('Case Pack'!F:F<=TODAY()),'Case Pack'!G:G,"未找到箱规")} -> B | AB8: =V8/Y8 -> 0 | AC8: =_xlfn.XLOOKUP(AA8,'Case Type'!A:A,'Case Type'!H:H)*AB8 -> 0
A9: CFLS71000WH | B9: =_xlfn.XLOOKUP(A9,'Product List'!B:B,'Product List'!I:I) -> MMO-SHELL PEARL HAMSTER CHEW | C9: 0 | D9: =SUMIFS(Purchase!F:F,Purchase!C:C,A9,Purchase!I:I,">"&$C$1,Purchase!V:V,"<>暂缓发货") -> 5248 | E9: =SUMIFS(Purchase!F:F,Purchase!C:C,A9,Purchase!J:J,">0",Purchase!I:I,">"&$C$1) -> 5248 | F9: =SUMIFS(Sales!E:E,Sales!C:C,A9,Sales!K:K,">"&$C$1) -> 2112 | G9: =SUMIFS(Sales!E:E,Sales!C:C,A9,Sales!K:K,">"&$C$1,Sales!L:L,">0") -> 2112 | H9: =C9+E9-G9-SUMIFS(Transfer!V:V,Transfer!O:O,A9)+SUMIFS(Transfer!W:W,Transfer!O:O,A9) -> 3136 | I9: =D9-E9+SUMIFS(Transfer!V:V,Transfer!O:O,A9)-SUMIFS(Transfer!W:W,Transfer!O:O,A9) -> 0 | J9: =SUMIFS(Purchase!F:F,Purchase!C:C,A9,Purchase!V:V,"暂缓发货") -> 640 | K9: =F9-G9 -> 0 | L9: =H9-K9 -> 3136 | M9: =H9+I9-K9 -> 3136 | N9: =_xlfn.XLOOKUP(A9,'Product List'!B:B,'Product List'!F:F) -> C | O9: =SUMIF('Weekly Sales'!B:B,A9,'Weekly Sales'!R:R) -> 31.166667 | P9: =IF(O9=0,999,ROUNDDOWN((L9)/O9,0)) -> 100 | Q9: =IF(O9=0,999,ROUNDDOWN((M9)/O9,0)) -> 100 | R9: =_xlfn.XLOOKUP(A9,'Product List'!B:B,'Product List'!P:P) -> 10 | S9: =IF(N9="A",6,IF(N9="B",5,2)) -> 2 | T9: =SUMIF('Weekly Sales'!B:B,A9,'Weekly Sales'!T:T) -> 0 | U9: =_xlfn.XLOOKUP(A9,'Product List'!B:B,'Product List'!O:O) -> 1000 | V9: =ROUNDUP(MAX(0,O9*(R9+S9+2)+T9-M9)/Y9,0)*Y9 -> 0 | W9: =_xlfn.XLOOKUP(A9,Sum_LA!A:A,Sum_LA!V:V) -> 0 | X9: =_xlfn.XLOOKUP(A9,Sum_HOU!A:A,Sum_HOU!V:V) -> 0 | Y9: {=_xlfn.XLOOKUP(1,('Case Pack'!A:A=A9)*('Case Pack'!F:F<=TODAY()),'Case Pack'!D:D,"未找到箱规")} -> 64 | Z9: =_xlfn.XLOOKUP(A9,'Product List'!B:B,'Product List'!M:M) -> PetcoUS | AA9: {=_xlfn.XLOOKUP(1,('Case Pack'!A:A=A9)*('Case Pack'!F:F<=TODAY()),'Case Pack'!G:G,"未找到箱规")} -> B | AB9: =V9/Y9 -> 0 | AC9: =_xlfn.XLOOKUP(AA9,'Case Type'!A:A,'Case Type'!H:H)*AB9 -> 0
A10: CPSH54000WH | B10: =_xlfn.XLOOKUP(A10,'Product List'!B:B,'Product List'!I:I) -> NONO Magnetic Water Bottle (220 ML) | C10: 0 | D10: =SUMIFS(Purchase!F:F,Purchase!C:C,A10,Purchase!I:I,">"&$C$1,Purchase!V:V,"<>暂缓发货") -> 1260 | E10: =SUMIFS(Purchase!F:F,Purchase!C:C,A10,Purchase!J:J,">0",Purchase!I:I,">"&$C$1) -> 1260 | F10: =SUMIFS(Sales!E:E,Sales!C:C,A10,Sales!K:K,">"&$C$1) -> 660 | G10: =SUMIFS(Sales!E:E,Sales!C:C,A10,Sales!K:K,">"&$C$1,Sales!L:L,">0") -> 660 | H10: =C10+E10-G10-SUMIFS(Transfer!V:V,Transfer!O:O,A10)+SUMIFS(Transfer!W:W,Transfer!O:O,A10) -> 600 | I10: =D10-E10+SUMIFS(Transfer!V:V,Transfer!O:O,A10)-SUMIFS(Transfer!W:W,Transfer!O:O,A10) -> 0 | J10: =SUMIFS(Purchase!F:F,Purchase!C:C,A10,Purchase!V:V,"暂缓发货") -> 0 | K10: =F10-G10 -> 0 | L10: =H10-K10 -> 600 | M10: =H10+I10-K10 -> 600 | N10: =_xlfn.XLOOKUP(A10,'Product List'!B:B,'Product List'!F:F) -> C | O10: =SUMIF('Weekly Sales'!B:B,A10,'Weekly Sales'!R:R) -> 7.6666667 | P10: =IF(O10=0,999,ROUNDDOWN((L10)/O10,0)) -> 78 | Q10: =IF(O10=0,999,ROUNDDOWN((M10)/O10,0)) -> 78 | R10: =_xlfn.XLOOKUP(A10,'Product List'!B:B,'Product List'!P:P) -> 10 | S10: =IF(N10="A",6,IF(N10="B",5,2)) -> 2 | T10: =SUMIF('Weekly Sales'!B:B,A10,'Weekly Sales'!T:T) -> 0 | U10: =_xlfn.XLOOKUP(A10,'Product List'!B:B,'Product List'!O:O) -> 500 | V10: =ROUNDUP(MAX(0,O10*(R10+S10+2)+T10-M10)/Y10,0)*Y10 -> 0 | W10: =_xlfn.XLOOKUP(A10,Sum_LA!A:A,Sum_LA!V:V) -> 0 | X10: =_xlfn.XLOOKUP(A10,Sum_HOU!A:A,Sum_HOU!V:V) -> 120 | Y10: {=_xlfn.XLOOKUP(1,('Case Pack'!A:A=A10)*('Case Pack'!F:F<=TODAY()),'Case Pack'!D:D,"未找到箱规")} -> 60 | Z10: =_xlfn.XLOOKUP(A10,'Product List'!B:B,'Product List'!M:M) -> PetcoMX,PSP | AA10: {=_xlfn.XLOOKUP(1,('Case Pack'!A:A=A10)*('Case Pack'!F:F<=TODAY()),'Case Pack'!G:G,"未找到箱规")} -> A | AB10: =V10/Y10 -> 0 | AC10: =_xlfn.XLOOKUP(AA10,'Case Type'!A:A,'Case Type'!H:H)*AB10 -> 0
A11: CPSH60007BK | B11: =_xlfn.XLOOKUP(A11,'Product List'!B:B,'Product List'!I:I) -> MINI & MOE MAG CONECT WTR BTL 4 OZ | C11: 0 | D11: =SUMIFS(Purchase!F:F,Purchase!C:C,A11,Purchase!I:I,">"&$C$1,Purchase!V:V,"<>暂缓发货") -> 15606 | E11: =SUMIFS(Purchase!F:F,Purchase!C:C,A11,Purchase!J:J,">0",Purchase!I:I,">"&$C$1) -> 15606 | F11: =SUMIFS(Sales!E:E,Sales!C:C,A11,Sales!K:K,">"&$C$1) -> 6912 | G11: =SUMIFS(Sales!E:E,Sales!C:C,A11,Sales!K:K,">"&$C$1,Sales!L:L,">0") -> 6912 | H11: =C11+E11-G11-SUMIFS(Transfer!V:V,Transfer!O:O,A11)+SUMIFS(Transfer!W:W,Transfer!O:O,A11) -> 8694 | I11: =D11-E11+SUMIFS(Transfer!V:V,Transfer!O:O,A11)-SUMIFS(Transfer!W:W,Transfer!O:O,A11) -> 0 | J11: =SUMIFS(Purchase!F:F,Purchase!C:C,A11,Purchase!V:V,"暂缓发货") -> 432 | K11: =F11-G11 -> 0 | L11: =H11-K11 -> 8694 | M11: =H11+I11-K11 -> 8694 | N11: =_xlfn.XLOOKUP(A11,'Product List'!B:B,'Product List'!F:F) -> A | O11: =SUMIF('Weekly Sales'!B:B,A11,'Weekly Sales'!R:R) -> 315 | P11: =IF(O11=0,999,ROUNDDOWN((L11)/O11,0)) -> 27 | Q11: =IF(O11=0,999,ROUNDDOWN((M11)/O11,0)) -> 27 | R11: =_xlfn.XLOOKUP(A11,'Product List'!B:B,'Product List'!P:P) -> 10 | S11: =IF(N11="A",6,IF(N11="B",5,2)) -> 6 | T11: =SUMIF('Weekly Sales'!B:B,A11,'Weekly Sales'!T:T) -> 2047.5 | U11: =_xlfn.XLOOKUP(A11,'Product List'!B:B,'Product List'!O:O) -> 500 | V11: =ROUNDUP(MAX(0,O11*(R11+S11+2)+T11-M11)/Y11,0)*Y11 -> 0 | W11: =_xlfn.XLOOKUP(A11,Sum_LA!A:A,Sum_LA!V:V) -> 0 | X11: =_xlfn.XLOOKUP(A11,Sum_HOU!A:A,Sum_HOU!V:V) -> 0 | Y11: {=_xlfn.XLOOKUP(1,('Case Pack'!A:A=A11)*('Case Pack'!F:F<=TODAY()),'Case Pack'!D:D,"未找到箱规")} -> 54 | Z11: =_xlfn.XLOOKUP(A11,'Product List'!B:B,'Product List'!M:M) -> Petsmart | AA11: {=_xlfn.XLOOKUP(1,('Case Pack'!A:A=A11)*('Case Pack'!F:F<=TODAY()),'Case Pack'!G:G,"未找到箱规")} -> A | AB11: =V11/Y11 -> 0 | AC11: =_xlfn.XLOOKUP(AA11,'Case Type'!A:A,'Case Type'!H:H)*AB11 -> 0
A12: CPSL22004GN | B12: =_xlfn.XLOOKUP(A12,'Product List'!B:B,'Product List'!I:I) -> Ceramic Candy Bowl | C12: 0 | D12: =SUMIFS(Purchase!F:F,Purchase!C:C,A12,Purchase!I:I,">"&$C$1,Purchase!V:V,"<>暂缓发货") -> 1248 | E12: =SUMIFS(Purchase!F:F,Purchase!C:C,A12,Purchase!J:J,">0",Purchase!I:I,">"&$C$1) -> 1248 | F12: =SUMIFS(Sales!E:E,Sales!C:C,A12,Sales!K:K,">"&$C$1) -> 672 | G12: =SUMIFS(Sales!E:E,Sales!C:C,A12,Sales!K:K,">"&$C$1,Sales!L:L,">0") -> 672 | H12: =C12+E12-G12-SUMIFS(Transfer!V:V,Transfer!O:O,A12)+SUMIFS(Transfer!W:W,Transfer!O:O,A12) -> 576 | I12: =D12-E12+SUMIFS(Transfer!V:V,Transfer!O:O,A12)-SUMIFS(Transfer!W:W,Transfer!O:O,A12) -> 0 | J12: =SUMIFS(Purchase!F:F,Purchase!C:C,A12,Purchase!V:V,"暂缓发货") -> 0 | K12: =F12-G12 -> 0 | L12: =H12-K12 -> 576 | M12: =H12+I12-K12 -> 576 | N12: =_xlfn.XLOOKUP(A12,'Product List'!B:B,'Product List'!F:F) -> C | O12: =SUMIF('Weekly Sales'!B:B,A12,'Weekly Sales'!R:R) -> 2.1666667 | P12: =IF(O12=0,999,ROUNDDOWN((L12)/O12,0)) -> 265 | Q12: =IF(O12=0,999,ROUNDDOWN((M12)/O12,0)) -> 265 | R12: =_xlfn.XLOOKUP(A12,'Product List'!B:B,'Product List'!P:P) -> 15 | S12: =IF(N12="A",6,IF(N12="B",5,2)) -> 2 | T12: =SUMIF('Weekly Sales'!B:B,A12,'Weekly Sales'!T:T) -> 0 | U12: =_xlfn.XLOOKUP(A12,'Product List'!B:B,'Product List'!O:O) -> 2000 | V12: =ROUNDUP(MAX(0,O12*(R12+S12+2)+T12-M12)/Y12,0)*Y12 -> 0 | W12: =_xlfn.XLOOKUP(A12,Sum_LA!A:A,Sum_LA!V:V) -> 0 | X12: =_xlfn.XLOOKUP(A12,Sum_HOU!A:A,Sum_HOU!V:V) -> 48 | Y12: {=_xlfn.XLOOKUP(1,('Case Pack'!A:A=A12)*('Case Pack'!F:F<=TODAY()),'Case Pack'!D:D,"未找到箱规")} -> 48 | Z12: =_xlfn.XLOOKUP(A12,'Product List'!B:B,'Product List'!M:M) -> PetcoMX,PSP | AA12: {=_xlfn.XLOOKUP(1,('Case Pack'!A:A=A12)*('Case Pack'!F:F<=TODAY()),'Case Pack'!G:G,"未找到箱规")} -> B | AB12: =V12/Y12 -> 0 | AC12: =_xlfn.XLOOKUP(AA12,'Case Type'!A:A,'Case Type'!H:H)*AB12 -> 0
A13: CPWJ0011 | B13: =_xlfn.XLOOKUP(A13,'Product List'!B:B,'Product List'!I:I) -> MINI/MOE MUSHROOM CABIN | C13: 0 | D13: =SUMIFS(Purchase!F:F,Purchase!C:C,A13,Purchase!I:I,">"&$C$1,Purchase!V:V,"<>暂缓发货") -> 2368 | E13: =SUMIFS(Purchase!F:F,Purchase!C:C,A13,Purchase!J:J,">0",Purchase!I:I,">"&$C$1) -> 1856 | F13: =SUMIFS(Sales!E:E,Sales!C:C,A13,Sales!K:K,">"&$C$1) -> 1360 | G13: =SUMIFS(Sales!E:E,Sales!C:C,A13,Sales!K:K,">"&$C$1,Sales!L:L,">0") -> 1296 | H13: =C13+E13-G13-SUMIFS(Transfer!V:V,Transfer!O:O,A13)+SUMIFS(Transfer!W:W,Transfer!O:O,A13) -> 560 | I13: =D13-E13+SUMIFS(Transfer!V:V,Transfer!O:O,A13)-SUMIFS(Transfer!W:W,Transfer!O:O,A13) -> 512 | J13: =SUMIFS(Purchase!F:F,Purchase!C:C,A13,Purchase!V:V,"暂缓发货") -> 0 | K13: =F13-G13 -> 64 | L13: =H13-K13 -> 496 | M13: =H13+I13-K13 -> 1008 | N13: =_xlfn.XLOOKUP(A13,'Product List'!B:B,'Product List'!F:F) -> B | O13: =SUMIF('Weekly Sales'!B:B,A13,'Weekly Sales'!R:R) -> 28.333333 | P13: =IF(O13=0,999,ROUNDDOWN((L13)/O13,0)) -> 17 | Q13: =IF(O13=0,999,ROUNDDOWN((M13)/O13,0)) -> 35 | R13: =_xlfn.XLOOKUP(A13,'Product List'!B:B,'Product List'!P:P) -> 15 | S13: =IF(N13="A",6,IF(N13="B",5,2)) -> 5 | T13: =SUMIF('Weekly Sales'!B:B,A13,'Weekly Sales'!T:T) -> 148.75 | U13: =_xlfn.XLOOKUP(A13,'Product List'!B:B,'Product List'!O:O) -> 500 | V13: =ROUNDUP(MAX(0,O13*(R13+S13+2)+T13-M13)/Y13,0)*Y13 -> 0 | W13: =_xlfn.XLOOKUP(A13,Sum_LA!A:A,Sum_LA!V:V) -> 0 | X13: =_xlfn.XLOOKUP(A13,Sum_HOU!A:A,Sum_HOU!V:V) -> 784 | Y13: {=_xlfn.XLOOKUP(1,('Case Pack'!A:A=A13)*('Case Pack'!F:F<=TODAY()),'Case Pack'!D:D,"未找到箱规")} -> 16 | Z13: =_xlfn.XLOOKUP(A13,'Product List'!B:B,'Product List'!M:M) -> PSP | AA13: {=_xlfn.XLOOKUP(1,('Case Pack'!A:A=A13)*('Case Pack'!F:F<=TODAY()),'Case Pack'!G:G,"未找到箱规")} -> C | AB13: =V13/Y13 -> 0 | AC13: =_xlfn.XLOOKUP(AA13,'Case Type'!A:A,'Case Type'!H:H)*AB13 -> 0
... A35: R-72 | B35: =_xlfn.XLOOKUP(A35,'Product List'!B:B,'Product List'!I:I) -> MMO-WAVE BRIDGE | C35: 352 | D35: =SUMIFS(Purchase!F:F,Purchase!C:C,A35,Purchase!I:I,">"&$C$1,Purchase!V:V,"<>暂缓发货") -> 2508 | E35: =SUMIFS(Purchase!F:F,Purchase!C:C,A35,Purchase!J:J,">0",Purchase!I:I,">"&$C$1) -> 2508 | F35: =SUMIFS(Sales!E:E,Sales!C:C,A35,Sales!K:K,">"&$C$1) -> 2853 | G35: =SUMIFS(Sales!E:E,Sales!C:C,A35,Sales!K:K,">"&$C$1,Sales!L:L,">0") -> 2853 | H35: =C35+E35-G35-SUMIFS(Transfer!V:V,Transfer!O:O,A35)+SUMIFS(Transfer!W:W,Transfer!O:O,A35) -> 7 | I35: =D35-E35+SUMIFS(Transfer!V:V,Transfer!O:O,A35)-SUMIFS(Transfer!W:W,Transfer!O:O,A35) -> 0 | J35: =SUMIFS(Purchase!F:F,Purchase!C:C,A35,Purchase!V:V,"暂缓发货") -> 0 | K35: =F35-G35 -> 0 | L35: =H35-K35 -> 7 | M35: =H35+I35-K35 -> 7 | N35: =_xlfn.XLOOKUP(A35,'Product List'!B:B,'Product List'!F:F) -> B | O35: =SUMIF('Weekly Sales'!B:B,A35,'Weekly Sales'!R:R) -> 0 | P35: =IF(O35=0,999,ROUNDDOWN((L35)/O35,0)) -> 999 | Q35: =IF(O35=0,999,ROUNDDOWN((M35)/O35,0)) -> 999 | R35: =_xlfn.XLOOKUP(A35,'Product List'!B:B,'Product List'!P:P) -> 15 | S35: =IF(N35="A",6,IF(N35="B",5,2)) -> 5 | T35: =SUMIF('Weekly Sales'!B:B,A35,'Weekly Sales'!T:T) -> 0 | U35: =_xlfn.XLOOKUP(A35,'Product List'!B:B,'Product List'!O:O) -> 500 | V35: =ROUNDUP(MAX(0,O35*(R35+S35+2)+T35-M35)/Y35,0)*Y35 -> 0 | W35: =_xlfn.XLOOKUP(A35,Sum_LA!A:A,Sum_LA!V:V) -> 0 | X35: =_xlfn.XLOOKUP(A35,Sum_HOU!A:A,Sum_HOU!V:V) -> 0 | Y35: {=_xlfn.XLOOKUP(1,('Case Pack'!A:A=A35)*('Case Pack'!F:F<=TODAY()),'Case Pack'!D:D,"未找到箱规")} -> 33 | Z35: =_xlfn.XLOOKUP(A35,'Product List'!B:B,'Product List'!M:M) -> PetcoUS，Canada | AA35: {=_xlfn.XLOOKUP(1,('Case Pack'!A:A=A35)*('Case Pack'!F:F<=TODAY()),'Case Pack'!G:G,"未找到箱规")} -> C | AB35: =V35/Y35 -> 0 | AC35: =_xlfn.XLOOKUP(AA35,'Case Type'!A:A,'Case Type'!H:H)*AB35 -> 0
A36: R-8 | B36: =_xlfn.XLOOKUP(A36,'Product List'!B:B,'Product List'!I:I) -> MINI/MOE BENDABLE BIRCHWOOD FENCE | C36: =746 -> 746 | D36: =SUMIFS(Purchase!F:F,Purchase!C:C,A36,Purchase!I:I,">"&$C$1,Purchase!V:V,"<>暂缓发货") -> 2592 | E36: =SUMIFS(Purchase!F:F,Purchase!C:C,A36,Purchase!J:J,">0",Purchase!I:I,">"&$C$1) -> 2592 | F36: =SUMIFS(Sales!E:E,Sales!C:C,A36,Sales!K:K,">"&$C$1) -> 2634 | G36: =SUMIFS(Sales!E:E,Sales!C:C,A36,Sales!K:K,">"&$C$1,Sales!L:L,">0") -> 2634 | H36: =C36+E36-G36-SUMIFS(Transfer!V:V,Transfer!O:O,A36)+SUMIFS(Transfer!W:W,Transfer!O:O,A36) -> 704 | I36: =D36-E36+SUMIFS(Transfer!V:V,Transfer!O:O,A36)-SUMIFS(Transfer!W:W,Transfer!O:O,A36) -> 0 | J36: =SUMIFS(Purchase!F:F,Purchase!C:C,A36,Purchase!V:V,"暂缓发货") -> 0 | K36: =F36-G36 -> 0 | L36: =H36-K36 -> 704 | M36: =H36+I36-K36 -> 704 | N36: =_xlfn.XLOOKUP(A36,'Product List'!B:B,'Product List'!F:F) -> B | O36: =SUMIF('Weekly Sales'!B:B,A36,'Weekly Sales'!R:R) -> 16 | P36: =IF(O36=0,999,ROUNDDOWN((L36)/O36,0)) -> 44 | Q36: =IF(O36=0,999,ROUNDDOWN((M36)/O36,0)) -> 44 | R36: =_xlfn.XLOOKUP(A36,'Product List'!B:B,'Product List'!P:P) -> 15 | S36: =IF(N36="A",6,IF(N36="B",5,2)) -> 5 | T36: =SUMIF('Weekly Sales'!B:B,A36,'Weekly Sales'!T:T) -> 84 | U36: =_xlfn.XLOOKUP(A36,'Product List'!B:B,'Product List'!O:O) -> 500 | V36: =ROUNDUP(MAX(0,O36*(R36+S36+2)+T36-M36)/Y36,0)*Y36 -> 0 | W36: =_xlfn.XLOOKUP(A36,Sum_LA!A:A,Sum_LA!V:V) -> 0 | X36: =_xlfn.XLOOKUP(A36,Sum_HOU!A:A,Sum_HOU!V:V) -> 448 | Y36: {=_xlfn.XLOOKUP(1,('Case Pack'!A:A=A36)*('Case Pack'!F:F<=TODAY()),'Case Pack'!D:D,"未找到箱规")} -> 32 | Z36: =_xlfn.XLOOKUP(A36,'Product List'!B:B,'Product List'!M:M) -> PSP, PetcoUS | AA36: {=_xlfn.XLOOKUP(1,('Case Pack'!A:A=A36)*('Case Pack'!F:F<=TODAY()),'Case Pack'!G:G,"未找到箱规")} -> F | AB36: =V36/Y36 -> 0 | AC36: =_xlfn.XLOOKUP(AA36,'Case Type'!A:A,'Case Type'!H:H)*AB36 -> 0
A37: RJ510-BL | B37: =_xlfn.XLOOKUP(A37,'Product List'!B:B,'Product List'!I:I) -> Crystal Outdoor Cage | C37: 0 | D37: =SUMIFS(Purchase!F:F,Purchase!C:C,A37,Purchase!I:I,">"&$C$1,Purchase!V:V,"<>暂缓发货") -> 1250 | E37: =SUMIFS(Purchase!F:F,Purchase!C:C,A37,Purchase!J:J,">0",Purchase!I:I,">"&$C$1) -> 1250 | F37: =SUMIFS(Sales!E:E,Sales!C:C,A37,Sales!K:K,">"&$C$1) -> 305 | G37: =SUMIFS(Sales!E:E,Sales!C:C,A37,Sales!K:K,">"&$C$1,Sales!L:L,">0") -> 305 | H37: =C37+E37-G37-SUMIFS(Transfer!V:V,Transfer!O:O,A37)+SUMIFS(Transfer!W:W,Transfer!O:O,A37) -> 945 | I37: =D37-E37+SUMIFS(Transfer!V:V,Transfer!O:O,A37)-SUMIFS(Transfer!W:W,Transfer!O:O,A37) -> 0 | J37: =SUMIFS(Purchase!F:F,Purchase!C:C,A37,Purchase!V:V,"暂缓发货") -> 0 | K37: =F37-G37 -> 0 | L37: =H37-K37 -> 945 | M37: =H37+I37-K37 -> 945 | N37: =_xlfn.XLOOKUP(A37,'Product List'!B:B,'Product List'!F:F) -> C | O37: =SUMIF('Weekly Sales'!B:B,A37,'Weekly Sales'!R:R) -> 0.66666667 | P37: =IF(O37=0,999,ROUNDDOWN((L37)/O37,0)) -> 1417 | Q37: =IF(O37=0,999,ROUNDDOWN((M37)/O37,0)) -> 1417 | R37: =_xlfn.XLOOKUP(A37,'Product List'!B:B,'Product List'!P:P) -> 10 | S37: =IF(N37="A",6,IF(N37="B",5,2)) -> 2 | T37: =SUMIF('Weekly Sales'!B:B,A37,'Weekly Sales'!T:T) -> 0 | U37: =_xlfn.XLOOKUP(A37,'Product List'!B:B,'Product List'!O:O) -> 1000 | V37: =ROUNDUP(MAX(0,O37*(R37+S37+2)+T37-M37)/Y37,0)*Y37 -> 0 | W37: =_xlfn.XLOOKUP(A37,Sum_LA!A:A,Sum_LA!V:V) -> 0 | X37: =_xlfn.XLOOKUP(A37,Sum_HOU!A:A,Sum_HOU!V:V) -> 10 | Y37: {=_xlfn.XLOOKUP(1,('Case Pack'!A:A=A37)*('Case Pack'!F:F<=TODAY()),'Case Pack'!D:D,"未找到箱规")} -> 5 | Z37: =_xlfn.XLOOKUP(A37,'Product List'!B:B,'Product List'!M:M) -> PetcoMX,PSP，Canada | AA37: {=_xlfn.XLOOKUP(1,('Case Pack'!A:A=A37)*('Case Pack'!F:F<=TODAY()),'Case Pack'!G:G,"未找到箱规")} -> A | AB37: =V37/Y37 -> 0 | AC37: =_xlfn.XLOOKUP(AA37,'Case Type'!A:A,'Case Type'!H:H)*AB37 -> 0
A38: SP-4 | B38: =_xlfn.XLOOKUP(A38,'Product List'!B:B,'Product List'!I:I) -> D. MMO-COTTAGE VIEW CAGE | C38: 0 | D38: =SUMIFS(Purchase!F:F,Purchase!C:C,A38,Purchase!I:I,">"&$C$1,Purchase!V:V,"<>暂缓发货") -> 741 | E38: =SUMIFS(Purchase!F:F,Purchase!C:C,A38,Purchase!J:J,">0",Purchase!I:I,">"&$C$1) -> 741 | F38: =SUMIFS(Sales!E:E,Sales!C:C,A38,Sales!K:K,">"&$C$1) -> 306 | G38: =SUMIFS(Sales!E:E,Sales!C:C,A38,Sales!K:K,">"&$C$1,Sales!L:L,">0") -> 137 | H38: =C38+E38-G38-SUMIFS(Transfer!V:V,Transfer!O:O,A38)+SUMIFS(Transfer!W:W,Transfer!O:O,A38) -> 604 | I38: =D38-E38+SUMIFS(Transfer!V:V,Transfer!O:O,A38)-SUMIFS(Transfer!W:W,Transfer!O:O,A38) -> 0 | J38: =SUMIFS(Purchase!F:F,Purchase!C:C,A38,Purchase!V:V,"暂缓发货") -> 0 | K38: =F38-G38 -> 169 | L38: =H38-K38 -> 435 | M38: =H38+I38-K38 -> 435 | N38: =_xlfn.XLOOKUP(A38,'Product List'!B:B,'Product List'!F:F) -> A | O38: =SUMIF('Weekly Sales'!B:B,A38,'Weekly Sales'!R:R) -> 0 | P38: =IF(O38=0,999,ROUNDDOWN((L38)/O38,0)) -> 999 | Q38: =IF(O38=0,999,ROUNDDOWN((M38)/O38,0)) -> 999 | R38: =_xlfn.XLOOKUP(A38,'Product List'!B:B,'Product List'!P:P) -> 10 | S38: =IF(N38="A",6,IF(N38="B",5,2)) -> 6 | T38: =SUMIF('Weekly Sales'!B:B,A38,'Weekly Sales'!T:T) -> 0 | U38: =_xlfn.XLOOKUP(A38,'Product List'!B:B,'Product List'!O:O) -> 1000 | V38: =ROUNDUP(MAX(0,O38*(R38+S38+2)+T38-M38)/Y38,0)*Y38 -> 0 | W38: =_xlfn.XLOOKUP(A38,Sum_LA!A:A,Sum_LA!V:V) -> 0 | X38: =_xlfn.XLOOKUP(A38,Sum_HOU!A:A,Sum_HOU!V:V) -> 0 | Y38: {=_xlfn.XLOOKUP(1,('Case Pack'!A:A=A38)*('Case Pack'!F:F<=TODAY()),'Case Pack'!D:D,"未找到箱规")} -> 1 | Z38: =_xlfn.XLOOKUP(A38,'Product List'!B:B,'Product List'!M:M) -> PSP, PetcoUS, PetcoMX | AA38: {=_xlfn.XLOOKUP(1,('Case Pack'!A:A=A38)*('Case Pack'!F:F<=TODAY()),'Case Pack'!G:G,"未找到箱规")} -> S3 | AB38: =V38/Y38 -> 0 | AC38: =_xlfn.XLOOKUP(AA38,'Case Type'!A:A,'Case Type'!H:H)*AB38 -> 0
A39: SP-7 | B39: =_xlfn.XLOOKUP(A39,'Product List'!B:B,'Product List'!I:I) -> MINI/MOE ROCKING BIRDHOUSE HIDE 1EA | C39: 0 | D39: =SUMIFS(Purchase!F:F,Purchase!C:C,A39,Purchase!I:I,">"&$C$1,Purchase!V:V,"<>暂缓发货") -> 0 | E39: =SUMIFS(Purchase!F:F,Purchase!C:C,A39,Purchase!J:J,">0",Purchase!I:I,">"&$C$1) -> 0 | F39: =SUMIFS(Sales!E:E,Sales!C:C,A39,Sales!K:K,">"&$C$1) -> 0 | G39: =SUMIFS(Sales!E:E,Sales!C:C,A39,Sales!K:K,">"&$C$1,Sales!L:L,">0") -> 0 | H39: =C39+E39-G39-SUMIFS(Transfer!V:V,Transfer!O:O,A39)+SUMIFS(Transfer!W:W,Transfer!O:O,A39) -> 0 | I39: =D39-E39+SUMIFS(Transfer!V:V,Transfer!O:O,A39)-SUMIFS(Transfer!W:W,Transfer!O:O,A39) -> 0 | J39: =SUMIFS(Purchase!F:F,Purchase!C:C,A39,Purchase!V:V,"暂缓发货") -> 0 | K39: =F39-G39 -> 0 | L39: =H39-K39 -> 0 | M39: =H39+I39-K39 -> 0 | N39: =_xlfn.XLOOKUP(A39,'Product List'!B:B,'Product List'!F:F) -> C | O39: =SUMIF('Weekly Sales'!B:B,A39,'Weekly Sales'!R:R) -> 0 | P39: =IF(O39=0,999,ROUNDDOWN((L39)/O39,0)) -> 999 | Q39: =IF(O39=0,999,ROUNDDOWN((M39)/O39,0)) -> 999 | R39: =_xlfn.XLOOKUP(A39,'Product List'!B:B,'Product List'!P:P) -> 10 | S39: =IF(N39="A",6,IF(N39="B",5,2)) -> 2 | T39: =SUMIF('Weekly Sales'!B:B,A39,'Weekly Sales'!T:T) -> 0 | U39: =_xlfn.XLOOKUP(A39,'Product List'!B:B,'Product List'!O:O) -> 500 | V39: =ROUNDUP(MAX(0,O39*(R39+S39+2)+T39-M39)/Y39,0)*Y39 -> 0 | W39: =_xlfn.XLOOKUP(A39,Sum_LA!A:A,Sum_LA!V:V) -> 0 | X39: =_xlfn.XLOOKUP(A39,Sum_HOU!A:A,Sum_HOU!V:V) -> 0 | Y39: {=_xlfn.XLOOKUP(1,('Case Pack'!A:A=A39)*('Case Pack'!F:F<=TODAY()),'Case Pack'!D:D,"未找到箱规")} -> 18 | Z39: =_xlfn.XLOOKUP(A39,'Product List'!B:B,'Product List'!M:M) -> PSP | AA39: {=_xlfn.XLOOKUP(1,('Case Pack'!A:A=A39)*('Case Pack'!F:F<=TODAY()),'Case Pack'!G:G,"未找到箱规")} -> C | AB39: =V39/Y39 -> 0 | AC39: =_xlfn.XLOOKUP(AA39,'Case Type'!A:A,'Case Type'!H:H)*AB39 -> 0
A40: SZP542-GN | B40: =_xlfn.XLOOKUP(A40,'Product List'!B:B,'Product List'!I:I) -> Bubble water bottle (color:green) | C40: 144 | D40: =SUMIFS(Purchase!F:F,Purchase!C:C,A40,Purchase!I:I,">"&$C$1,Purchase!V:V,"<>暂缓发货") -> 288 | E40: =SUMIFS(Purchase!F:F,Purchase!C:C,A40,Purchase!J:J,">0",Purchase!I:I,">"&$C$1) -> 288 | F40: =SUMIFS(Sales!E:E,Sales!C:C,A40,Sales!K:K,">"&$C$1) -> 198 | G40: =SUMIFS(Sales!E:E,Sales!C:C,A40,Sales!K:K,">"&$C$1,Sales!L:L,">0") -> 198 | H40: =C40+E40-G40-SUMIFS(Transfer!V:V,Transfer!O:O,A40)+SUMIFS(Transfer!W:W,Transfer!O:O,A40) -> 234 | I40: =D40-E40+SUMIFS(Transfer!V:V,Transfer!O:O,A40)-SUMIFS(Transfer!W:W,Transfer!O:O,A40) -> 0 | J40: =SUMIFS(Purchase!F:F,Purchase!C:C,A40,Purchase!V:V,"暂缓发货") -> 0 | K40: =F40-G40 -> 0 | L40: =H40-K40 -> 234 | M40: =H40+I40-K40 -> 234 | N40: =_xlfn.XLOOKUP(A40,'Product List'!B:B,'Product List'!F:F) -> C | O40: =SUMIF('Weekly Sales'!B:B,A40,'Weekly Sales'!R:R) -> 0 | P40: =IF(O40=0,999,ROUNDDOWN((L40)/O40,0)) -> 999 | Q40: =IF(O40=0,999,ROUNDDOWN((M40)/O40,0)) -> 999 | R40: =_xlfn.XLOOKUP(A40,'Product List'!B:B,'Product List'!P:P) -> 10 | S40: =IF(N40="A",6,IF(N40="B",5,2)) -> 2 | T40: =SUMIF('Weekly Sales'!B:B,A40,'Weekly Sales'!T:T) -> 0 | U40: =_xlfn.XLOOKUP(A40,'Product List'!B:B,'Product List'!O:O) -> 1000 | V40: =ROUNDUP(MAX(0,O40*(R40+S40+2)+T40-M40)/Y40,0)*Y40 -> 0 | W40: =_xlfn.XLOOKUP(A40,Sum_LA!A:A,Sum_LA!V:V) -> 0 | X40: =_xlfn.XLOOKUP(A40,Sum_HOU!A:A,Sum_HOU!V:V) -> 0 | Y40: {=_xlfn.XLOOKUP(1,('Case Pack'!A:A=A40)*('Case Pack'!F:F<=TODAY()),'Case Pack'!D:D,"未找到箱规")} -> 18 | Z40: =_xlfn.XLOOKUP(A40,'Product List'!B:B,'Product List'!M:M) -> Pet Supermarket,PetcoMX | AA40: {=_xlfn.XLOOKUP(1,('Case Pack'!A:A=A40)*('Case Pack'!F:F<=TODAY()),'Case Pack'!G:G,"未找到箱规")} -> B | AB40: =V40/Y40 -> 0 | AC40: =_xlfn.XLOOKUP(AA40,'Case Type'!A:A,'Case Type'!H:H)*AB40 -> 0
A41: SZP542-WH | B41: =_xlfn.XLOOKUP(A41,'Product List'!B:B,'Product List'!I:I) -> MMO-BUBBLE WATER BOTTLE | C41: 360 | D41: =SUMIFS(Purchase!F:F,Purchase!C:C,A41,Purchase!I:I,">"&$C$1,Purchase!V:V,"<>暂缓发货") -> 18648 | E41: =SUMIFS(Purchase!F:F,Purchase!C:C,A41,Purchase!J:J,">0",Purchase!I:I,">"&$C$1) -> 18648 | F41: =SUMIFS(Sales!E:E,Sales!C:C,A41,Sales!K:K,">"&$C$1) -> 13590 | G41: =SUMIFS(Sales!E:E,Sales!C:C,A41,Sales!K:K,">"&$C$1,Sales!L:L,">0") -> 10566 | H41: =C41+E41-G41-SUMIFS(Transfer!V:V,Transfer!O:O,A41)+SUMIFS(Transfer!W:W,Transfer!O:O,A41) -> 8442 | I41: =D41-E41+SUMIFS(Transfer!V:V,Transfer!O:O,A41)-SUMIFS(Transfer!W:W,Transfer!O:O,A41) -> 0 | J41: =SUMIFS(Purchase!F:F,Purchase!C:C,A41,Purchase!V:V,"暂缓发货") -> 5124 | K41: =F41-G41 -> 3024 | L41: =H41-K41 -> 5418 | M41: =H41+I41-K41 -> 5418 | N41: =_xlfn.XLOOKUP(A41,'Product List'!B:B,'Product List'!F:F) -> A | O41: =SUMIF('Weekly Sales'!B:B,A41,'Weekly Sales'!R:R) -> 321.16667 | P41: =IF(O41=0,999,ROUNDDOWN((L41)/O41,0)) -> 16 | Q41: =IF(O41=0,999,ROUNDDOWN((M41)/O41,0)) -> 16 | R41: =_xlfn.XLOOKUP(A41,'Product List'!B:B,'Product List'!P:P) -> 10 | S41: =IF(N41="A",6,IF(N41="B",5,2)) -> 6 | T41: =SUMIF('Weekly Sales'!B:B,A41,'Weekly Sales'!T:T) -> 2101.5833 | U41: =_xlfn.XLOOKUP(A41,'Product List'!B:B,'Product List'!O:O) -> 1000 | V41: =ROUNDUP(MAX(0,O41*(R41+S41+2)+T41-M41)/Y41,0)*Y41 -> 2478 | W41: =_xlfn.XLOOKUP(A41,Sum_LA!A:A,Sum_LA!V:V) -> 2394 | X41: =_xlfn.XLOOKUP(A41,Sum_HOU!A:A,Sum_HOU!V:V) -> 126 | Y41: {=_xlfn.XLOOKUP(1,('Case Pack'!A:A=A41)*('Case Pack'!F:F<=TODAY()),'Case Pack'!D:D,"未找到箱规")} -> 42 | Z41: =_xlfn.XLOOKUP(A41,'Product List'!B:B,'Product List'!M:M) -> PetcoUS,PSP | AA41: {=_xlfn.XLOOKUP(1,('Case Pack'!A:A=A41)*('Case Pack'!F:F<=TODAY()),'Case Pack'!G:G,"未找到箱规")} -> C | AB41: =V41/Y41 -> 59 | AC41: =_xlfn.XLOOKUP(AA41,'Case Type'!A:A,'Case Type'!H:H)*AB41 -> 9.281633
A42: T-1-BL | B42: =_xlfn.XLOOKUP(A42,'Product List'!B:B,'Product List'!I:I) -> MMO-PAPER TWIST BLU/WHT | C42: 936 | D42: =SUMIFS(Purchase!F:F,Purchase!C:C,A42,Purchase!I:I,">"&$C$1,Purchase!V:V,"<>暂缓发货") -> 4740 | E42: =SUMIFS(Purchase!F:F,Purchase!C:C,A42,Purchase!J:J,">0",Purchase!I:I,">"&$C$1) -> 4740 | F42: =SUMIFS(Sales!E:E,Sales!C:C,A42,Sales!K:K,">"&$C$1) -> 2136 | G42: =SUMIFS(Sales!E:E,Sales!C:C,A42,Sales!K:K,">"&$C$1,Sales!L:L,">0") -> 2136 | H42: =C42+E42-G42-SUMIFS(Transfer!V:V,Transfer!O:O,A42)+SUMIFS(Transfer!W:W,Transfer!O:O,A42) -> 3540 | I42: =D42-E42+SUMIFS(Transfer!V:V,Transfer!O:O,A42)-SUMIFS(Transfer!W:W,Transfer!O:O,A42) -> 0 | J42: =SUMIFS(Purchase!F:F,Purchase!C:C,A42,Purchase!V:V,"暂缓发货") -> 0 | K42: =F42-G42 -> 0 | L42: =H42-K42 -> 3540 | M42: =H42+I42-K42 -> 3540 | N42: =_xlfn.XLOOKUP(A42,'Product List'!B:B,'Product List'!F:F) -> B | O42: =SUMIF('Weekly Sales'!B:B,A42,'Weekly Sales'!R:R) -> 48.5 | P42: =IF(O42=0,999,ROUNDDOWN((L42)/O42,0)) -> 72 | Q42: =IF(O42=0,999,ROUNDDOWN((M42)/O42,0)) -> 72 | R42: =_xlfn.XLOOKUP(A42,'Product List'!B:B,'Product List'!P:P) -> 10 | S42: =IF(N42="A",6,IF(N42="B",5,2)) -> 5 | T42: =SUMIF('Weekly Sales'!B:B,A42,'Weekly Sales'!T:T) -> 157.625 | U42: =_xlfn.XLOOKUP(A42,'Product List'!B:B,'Product List'!O:O) -> 500 | V42: =ROUNDUP(MAX(0,O42*(R42+S42+2)+T42-M42)/Y42,0)*Y42 -> 0 | W42: =_xlfn.XLOOKUP(A42,Sum_LA!A:A,Sum_LA!V:V) -> 0 | X42: =_xlfn.XLOOKUP(A42,Sum_HOU!A:A,Sum_HOU!V:V) -> 0 | Y42: {=_xlfn.XLOOKUP(1,('Case Pack'!A:A=A42)*('Case Pack'!F:F<=TODAY()),'Case Pack'!D:D,"未找到箱规")} -> 30 | Z42: =_xlfn.XLOOKUP(A42,'Product List'!B:B,'Product List'!M:M) -> PetcoUS，PSP | AA42: {=_xlfn.XLOOKUP(1,('Case Pack'!A:A=A42)*('Case Pack'!F:F<=TODAY()),'Case Pack'!G:G,"未找到箱规")} -> A | AB42: =V42/Y42 -> 0 | AC42: =_xlfn.XLOOKUP(AA42,'Case Type'!A:A,'Case Type'!H:H)*AB42 -> 0
A43: T-1-BL-WH | B43: =_xlfn.XLOOKUP(A43,'Product List'!B:B,'Product List'!I:I) -> MINI/MOE SMALL ANIMAL BEDDING PAPER TWISTS | C43: 0 | D43: =SUMIFS(Purchase!F:F,Purchase!C:C,A43,Purchase!I:I,">"&$C$1,Purchase!V:V,"<>暂缓发货") -> 3420 | E43: =SUMIFS(Purchase!F:F,Purchase!C:C,A43,Purchase!J:J,">0",Purchase!I:I,">"&$C$1) -> 3390 | F43: =SUMIFS(Sales!E:E,Sales!C:C,A43,Sales!K:K,">"&$C$1) -> 2010 | G43: =SUMIFS(Sales!E:E,Sales!C:C,A43,Sales!K:K,">"&$C$1,Sales!L:L,">0") -> 2010 | H43: =C43+E43-G43-SUMIFS(Transfer!V:V,Transfer!O:O,A43)+SUMIFS(Transfer!W:W,Transfer!O:O,A43) -> 1380 | I43: =D43-E43+SUMIFS(Transfer!V:V,Transfer!O:O,A43)-SUMIFS(Transfer!W:W,Transfer!O:O,A43) -> 30 | J43: =SUMIFS(Purchase!F:F,Purchase!C:C,A43,Purchase!V:V,"暂缓发货") -> 0 | K43: =F43-G43 -> 0 | L43: =H43-K43 -> 1380 | M43: =H43+I43-K43 -> 1410 | N43: =_xlfn.XLOOKUP(A43,'Product List'!B:B,'Product List'!F:F) -> C | O43: =SUMIF('Weekly Sales'!B:B,A43,'Weekly Sales'!R:R) -> 9.1666667 | P43: =IF(O43=0,999,ROUNDDOWN((L43)/O43,0)) -> 150 | Q43: =IF(O43=0,999,ROUNDDOWN((M43)/O43,0)) -> 153 | R43: =_xlfn.XLOOKUP(A43,'Product List'!B:B,'Product List'!P:P) -> 10 | S43: =IF(N43="A",6,IF(N43="B",5,2)) -> 2 | T43: =SUMIF('Weekly Sales'!B:B,A43,'Weekly Sales'!T:T) -> 0 | U43: =_xlfn.XLOOKUP(A43,'Product List'!B:B,'Product List'!O:O) -> 1000 | V43: =ROUNDUP(MAX(0,O43*(R43+S43+2)+T43-M43)/Y43,0)*Y43 -> 0 | W43: =_xlfn.XLOOKUP(A43,Sum_LA!A:A,Sum_LA!V:V) -> 0 | X43: =_xlfn.XLOOKUP(A43,Sum_HOU!A:A,Sum_HOU!V:V) -> 150 | Y43: {=_xlfn.XLOOKUP(1,('Case Pack'!A:A=A43)*('Case Pack'!F:F<=TODAY()),'Case Pack'!D:D,"未找到箱规")} -> 30 | Z43: =_xlfn.XLOOKUP(A43,'Product List'!B:B,'Product List'!M:M) -> PSP | AA43: {=_xlfn.XLOOKUP(1,('Case Pack'!A:A=A43)*('Case Pack'!F:F<=TODAY()),'Case Pack'!G:G,"未找到箱规")} -> A | AB43: =V43/Y43 -> 0 | AC43: =_xlfn.XLOOKUP(AA43,'Case Type'!A:A,'Case Type'!H:H)*AB43 -> 0
A44: T-1-BR-WH | B44: =_xlfn.XLOOKUP(A44,'Product List'!B:B,'Product List'!I:I) -> Paper twist brown / white bedding | C44: 0 | D44: =SUMIFS(Purchase!F:F,Purchase!C:C,A44,Purchase!I:I,">"&$C$1,Purchase!V:V,"<>暂缓发货") -> 1860 | E44: =SUMIFS(Purchase!F:F,Purchase!C:C,A44,Purchase!J:J,">0",Purchase!I:I,">"&$C$1) -> 1860 | F44: =SUMIFS(Sales!E:E,Sales!C:C,A44,Sales!K:K,">"&$C$1) -> 930 | G44: =SUMIFS(Sales!E:E,Sales!C:C,A44,Sales!K:K,">"&$C$1,Sales!L:L,">0") -> 930 | H44: =C44+E44-G44-SUMIFS(Transfer!V:V,Transfer!O:O,A44)+SUMIFS(Transfer!W:W,Transfer!O:O,A44) -> 930 | I44: =D44-E44+SUMIFS(Transfer!V:V,Transfer!O:O,A44)-SUMIFS(Transfer!W:W,Transfer!O:O,A44) -> 0 | J44: =SUMIFS(Purchase!F:F,Purchase!C:C,A44,Purchase!V:V,"暂缓发货") -> 0 | K44: =F44-G44 -> 0 | L44: =H44-K44 -> 930 | M44: =H44+I44-K44 -> 930 | N44: =_xlfn.XLOOKUP(A44,'Product List'!B:B,'Product List'!F:F) -> C | O44: =SUMIF('Weekly Sales'!B:B,A44,'Weekly Sales'!R:R) -> 0.5 | P44: =IF(O44=0,999,ROUNDDOWN((L44)/O44,0)) -> 1860 | Q44: =IF(O44=0,999,ROUNDDOWN((M44)/O44,0)) -> 1860 | R44: =_xlfn.XLOOKUP(A44,'Product List'!B:B,'Product List'!P:P) -> 10 | S44: =IF(N44="A",6,IF(N44="B",5,2)) -> 2 | T44: =SUMIF('Weekly Sales'!B:B,A44,'Weekly Sales'!T:T) -> 0 | U44: =_xlfn.XLOOKUP(A44,'Product List'!B:B,'Product List'!O:O) -> 1000 | V44: =ROUNDUP(MAX(0,O44*(R44+S44+2)+T44-M44)/Y44,0)*Y44 -> 0 | W44: =_xlfn.XLOOKUP(A44,Sum_LA!A:A,Sum_LA!V:V) -> 0 | X44: =_xlfn.XLOOKUP(A44,Sum_HOU!A:A,Sum_HOU!V:V) -> 30 | Y44: {=_xlfn.XLOOKUP(1,('Case Pack'!A:A=A44)*('Case Pack'!F:F<=TODAY()),'Case Pack'!D:D,"未找到箱规")} -> 30 | Z44: =_xlfn.XLOOKUP(A44,'Product List'!B:B,'Product List'!M:M) -> Pet Supermarket，PSP | AA44: {=_xlfn.XLOOKUP(1,('Case Pack'!A:A=A44)*('Case Pack'!F:F<=TODAY()),'Case Pack'!G:G,"未找到箱规")} -> A | AB44: =V44/Y44 -> 0 | AC44: =_xlfn.XLOOKUP(AA44,'Case Type'!A:A,'Case Type'!H:H)*AB44 -> 0
A45: T-1-PK | B45: =_xlfn.XLOOKUP(A45,'Product List'!B:B,'Product List'!I:I) -> MINI/MOE SMALL ANIMAL BEDDING PAPER TWISTS BUBBLEGUM 1EA | C45: 0 | D45: =SUMIFS(Purchase!F:F,Purchase!C:C,A45,Purchase!I:I,">"&$C$1,Purchase!V:V,"<>暂缓发货") -> 1260 | E45: =SUMIFS(Purchase!F:F,Purchase!C:C,A45,Purchase!J:J,">0",Purchase!I:I,">"&$C$1) -> 1260 | F45: =SUMIFS(Sales!E:E,Sales!C:C,A45,Sales!K:K,">"&$C$1) -> 660 | G45: =SUMIFS(Sales!E:E,Sales!C:C,A45,Sales!K:K,">"&$C$1,Sales!L:L,">0") -> 660 | H45: =C45+E45-G45-SUMIFS(Transfer!V:V,Transfer!O:O,A45)+SUMIFS(Transfer!W:W,Transfer!O:O,A45) -> 600 | I45: =D45-E45+SUMIFS(Transfer!V:V,Transfer!O:O,A45)-SUMIFS(Transfer!W:W,Transfer!O:O,A45) -> 0 | J45: =SUMIFS(Purchase!F:F,Purchase!C:C,A45,Purchase!V:V,"暂缓发货") -> 0 | K45: =F45-G45 -> 0 | L45: =H45-K45 -> 600 | M45: =H45+I45-K45 -> 600 | N45: =_xlfn.XLOOKUP(A45,'Product List'!B:B,'Product List'!F:F) -> C | O45: =SUMIF('Weekly Sales'!B:B,A45,'Weekly Sales'!R:R) -> 1.6666667 | P45: =IF(O45=0,999,ROUNDDOWN((L45)/O45,0)) -> 359 | Q45: =IF(O45=0,999,ROUNDDOWN((M45)/O45,0)) -> 359 | R45: =_xlfn.XLOOKUP(A45,'Product List'!B:B,'Product List'!P:P) -> 10 | S45: =IF(N45="A",6,IF(N45="B",5,2)) -> 2 | T45: =SUMIF('Weekly Sales'!B:B,A45,'Weekly Sales'!T:T) -> 0 | U45: =_xlfn.XLOOKUP(A45,'Product List'!B:B,'Product List'!O:O) -> 1000 | V45: =ROUNDUP(MAX(0,O45*(R45+S45+2)+T45-M45)/Y45,0)*Y45 -> 0 | W45: =_xlfn.XLOOKUP(A45,Sum_LA!A:A,Sum_LA!V:V) -> 0 | X45: =_xlfn.XLOOKUP(A45,Sum_HOU!A:A,Sum_HOU!V:V) -> 30 | Y45: {=_xlfn.XLOOKUP(1,('Case Pack'!A:A=A45)*('Case Pack'!F:F<=TODAY()),'Case Pack'!D:D,"未找到箱规")} -> 30 | Z45: =_xlfn.XLOOKUP(A45,'Product List'!B:B,'Product List'!M:M) -> PSP | AA45: {=_xlfn.XLOOKUP(1,('Case Pack'!A:A=A45)*('Case Pack'!F:F<=TODAY()),'Case Pack'!G:G,"未找到箱规")} -> A | AB45: =V45/Y45 -> 0 | AC45: =_xlfn.XLOOKUP(AA45,'Case Type'!A:A,'Case Type'!H:H)*AB45 -> 0
A46: T-41 | B46: =_xlfn.XLOOKUP(A46,'Product List'!B:B,'Product List'!I:I) -> Forest Series Hamster Chew Toy & Treat | C46: 0 | D46: =SUMIFS(Purchase!F:F,Purchase!C:C,A46,Purchase!I:I,">"&$C$1,Purchase!V:V,"<>暂缓发货") -> 1560 | E46: =SUMIFS(Purchase!F:F,Purchase!C:C,A46,Purchase!J:J,">0",Purchase!I:I,">"&$C$1) -> 1560 | F46: =SUMIFS(Sales!E:E,Sales!C:C,A46,Sales!K:K,">"&$C$1) -> 1020 | G46: =SUMIFS(Sales!E:E,Sales!C:C,A46,Sales!K:K,">"&$C$1,Sales!L:L,">0") -> 1020 | H46: =C46+E46-G46-SUMIFS(Transfer!V:V,Transfer!O:O,A46)+SUMIFS(Transfer!W:W,Transfer!O:O,A46) -> 540 | I46: =D46-E46+SUMIFS(Transfer!V:V,Transfer!O:O,A46)-SUMIFS(Transfer!W:W,Transfer!O:O,A46) -> 0 | J46: =SUMIFS(Purchase!F:F,Purchase!C:C,A46,Purchase!V:V,"暂缓发货") -> 0 | K46: =F46-G46 -> 0 | L46: =H46-K46 -> 540 | M46: =H46+I46-K46 -> 540 | N46: =_xlfn.XLOOKUP(A46,'Product List'!B:B,'Product List'!F:F) -> C | O46: =SUMIF('Weekly Sales'!B:B,A46,'Weekly Sales'!R:R) -> 3 | P46: =IF(O46=0,999,ROUNDDOWN((L46)/O46,0)) -> 180 | Q46: =IF(O46=0,999,ROUNDDOWN((M46)/O46,0)) -> 180 | R46: =_xlfn.XLOOKUP(A46,'Product List'!B:B,'Product List'!P:P) -> 10 | S46: =IF(N46="A",6,IF(N46="B",5,2)) -> 2 | T46: =SUMIF('Weekly Sales'!B:B,A46,'Weekly Sales'!T:T) -> 0 | U46: =_xlfn.XLOOKUP(A46,'Product List'!B:B,'Product List'!O:O) -> 1000 | V46: =ROUNDUP(MAX(0,O46*(R46+S46+2)+T46-M46)/Y46,0)*Y46 -> 0 | W46: =_xlfn.XLOOKUP(A46,Sum_LA!A:A,Sum_LA!V:V) -> 0 | X46: =_xlfn.XLOOKUP(A46,Sum_HOU!A:A,Sum_HOU!V:V) -> 60 | Y46: {=_xlfn.XLOOKUP(1,('Case Pack'!A:A=A46)*('Case Pack'!F:F<=TODAY()),'Case Pack'!D:D,"未找到箱规")} -> 60 | Z46: =_xlfn.XLOOKUP(A46,'Product List'!B:B,'Product List'!M:M) -> Pet Supermarket,PSP | AA46: {=_xlfn.XLOOKUP(1,('Case Pack'!A:A=A46)*('Case Pack'!F:F<=TODAY()),'Case Pack'!G:G,"未找到箱规")} -> B | AB46: =V46/Y46 -> 0 | AC46: =_xlfn.XLOOKUP(AA46,'Case Type'!A:A,'Case Type'!H:H)*AB46 -> 0
A47: WJ-13 | B47: =_xlfn.XLOOKUP(A47,'Product List'!B:B,'Product List'!I:I) -> MINI/MOE CAMPING TENT HIDE | C47: 132 | D47: =SUMIFS(Purchase!F:F,Purchase!C:C,A47,Purchase!I:I,">"&$C$1,Purchase!V:V,"<>暂缓发货") -> 16584 | E47: =SUMIFS(Purchase!F:F,Purchase!C:C,A47,Purchase!J:J,">0",Purchase!I:I,">"&$C$1) -> 10068 | F47: =SUMIFS(Sales!E:E,Sales!C:C,A47,Sales!K:K,">"&$C$1) -> 9348 | G47: =SUMIFS(Sales!E:E,Sales!C:C,A47,Sales!K:K,">"&$C$1,Sales!L:L,">0") -> 9276 | H47: =C47+E47-G47-SUMIFS(Transfer!V:V,Transfer!O:O,A47)+SUMIFS(Transfer!W:W,Transfer!O:O,A47) -> 924 | I47: =D47-E47+SUMIFS(Transfer!V:V,Transfer!O:O,A47)-SUMIFS(Transfer!W:W,Transfer!O:O,A47) -> 6516 | J47: =SUMIFS(Purchase!F:F,Purchase!C:C,A47,Purchase!V:V,"暂缓发货") -> 0 | K47: =F47-G47 -> 72 | L47: =H47-K47 -> 852 | M47: =H47+I47-K47 -> 7368 | N47: =_xlfn.XLOOKUP(A47,'Product List'!B:B,'Product List'!F:F) -> A | O47: =SUMIF('Weekly Sales'!B:B,A47,'Weekly Sales'!R:R) -> 231 | P47: =IF(O47=0,999,ROUNDDOWN((L47)/O47,0)) -> 3 | Q47: =IF(O47=0,999,ROUNDDOWN((M47)/O47,0)) -> 31 | R47: =_xlfn.XLOOKUP(A47,'Product List'!B:B,'Product List'!P:P) -> 15 | S47: =IF(N47="A",6,IF(N47="B",5,2)) -> 6 | T47: =SUMIF('Weekly Sales'!B:B,A47,'Weekly Sales'!T:T) -> 1669.5 | U47: =_xlfn.XLOOKUP(A47,'Product List'!B:B,'Product List'!O:O) -> 500 | V47: =ROUNDUP(MAX(0,O47*(R47+S47+2)+T47-M47)/Y47,0)*Y47 -> 0 | W47: =_xlfn.XLOOKUP(A47,Sum_LA!A:A,Sum_LA!V:V) -> 0 | X47: =_xlfn.XLOOKUP(A47,Sum_HOU!A:A,Sum_HOU!V:V) -> 1422 | Y47: {=_xlfn.XLOOKUP(1,('Case Pack'!A:A=A47)*('Case Pack'!F:F<=TODAY()),'Case Pack'!D:D,"未找到箱规")} -> 18 | Z47: =_xlfn.XLOOKUP(A47,'Product List'!B:B,'Product List'!M:M) -> PSP, Petsmart, Pet Supermarket,Canada | AA47: {=_xlfn.XLOOKUP(1,('Case Pack'!A:A=A47)*('Case Pack'!F:F<=TODAY()),'Case Pack'!G:G,"未找到箱规")} -> B | AB47: =V47/Y47 -> 0 | AC47: =_xlfn.XLOOKUP(AA47,'Case Type'!A:A,'Case Type'!H:H)*AB47 -> 0
A48: WJ-14-B | B48: =_xlfn.XLOOKUP(A48,'Product List'!B:B,'Product List'!I:I) -> Little Devil Travel Cage | C48: 0 | D48: =SUMIFS(Purchase!F:F,Purchase!C:C,A48,Purchase!I:I,">"&$C$1,Purchase!V:V,"<>暂缓发货") -> 1260 | E48: =SUMIFS(Purchase!F:F,Purchase!C:C,A48,Purchase!J:J,">0",Purchase!I:I,">"&$C$1) -> 1260 | F48: =SUMIFS(Sales!E:E,Sales!C:C,A48,Sales!K:K,">"&$C$1) -> 612 | G48: =SUMIFS(Sales!E:E,Sales!C:C,A48,Sales!K:K,">"&$C$1,Sales!L:L,">0") -> 612 | H48: =C48+E48-G48-SUMIFS(Transfer!V:V,Transfer!O:O,A48)+SUMIFS(Transfer!W:W,Transfer!O:O,A48) -> 648 | I48: =D48-E48+SUMIFS(Transfer!V:V,Transfer!O:O,A48)-SUMIFS(Transfer!W:W,Transfer!O:O,A48) -> 0 | J48: =SUMIFS(Purchase!F:F,Purchase!C:C,A48,Purchase!V:V,"暂缓发货") -> 0 | K48: =F48-G48 -> 0 | L48: =H48-K48 -> 648 | M48: =H48+I48-K48 -> 648 | N48: =_xlfn.XLOOKUP(A48,'Product List'!B:B,'Product List'!F:F) -> C | O48: =SUMIF('Weekly Sales'!B:B,A48,'Weekly Sales'!R:R) -> 4 | P48: =IF(O48=0,999,ROUNDDOWN((L48)/O48,0)) -> 162 | Q48: =IF(O48=0,999,ROUNDDOWN((M48)/O48,0)) -> 162 | R48: =_xlfn.XLOOKUP(A48,'Product List'!B:B,'Product List'!P:P) -> 10 | S48: =IF(N48="A",6,IF(N48="B",5,2)) -> 2 | T48: =SUMIF('Weekly Sales'!B:B,A48,'Weekly Sales'!T:T) -> 0 | U48: =_xlfn.XLOOKUP(A48,'Product List'!B:B,'Product List'!O:O) -> 1000 | V48: =ROUNDUP(MAX(0,O48*(R48+S48+2)+T48-M48)/Y48,0)*Y48 -> 0 | W48: =_xlfn.XLOOKUP(A48,Sum_LA!A:A,Sum_LA!V:V) -> 0 | X48: =_xlfn.XLOOKUP(A48,Sum_HOU!A:A,Sum_HOU!V:V) -> 72 | Y48: {=_xlfn.XLOOKUP(1,('Case Pack'!A:A=A48)*('Case Pack'!F:F<=TODAY()),'Case Pack'!D:D,"未找到箱规")} -> 18 | Z48: =_xlfn.XLOOKUP(A48,'Product List'!B:B,'Product List'!M:M) -> PetcoMX,PSP，Canada | AA48: {=_xlfn.XLOOKUP(1,('Case Pack'!A:A=A48)*('Case Pack'!F:F<=TODAY()),'Case Pack'!G:G,"未找到箱规")} -> C | AB48: =V48/Y48 -> 0 | AC48: =_xlfn.XLOOKUP(AA48,'Case Type'!A:A,'Case Type'!H:H)*AB48 -> 0
... A62: ZM1.2-RD-GN | B62: =_xlfn.XLOOKUP(A62,'Product List'!B:B,'Product List'!I:I) -> MINI/MOE SMALL ANIMAL BEDDING PAPER FLK XMAS CRAN/MATCHA 1EA | C62: 0 | D62: =SUMIFS(Purchase!F:F,Purchase!C:C,A62,Purchase!I:I,">"&$C$1,Purchase!V:V,"<>暂缓发货") -> 1260 | E62: =SUMIFS(Purchase!F:F,Purchase!C:C,A62,Purchase!J:J,">0",Purchase!I:I,">"&$C$1) -> 1260 | F62: =SUMIFS(Sales!E:E,Sales!C:C,A62,Sales!K:K,">"&$C$1) -> 630 | G62: =SUMIFS(Sales!E:E,Sales!C:C,A62,Sales!K:K,">"&$C$1,Sales!L:L,">0") -> 630 | H62: =C62+E62-G62-SUMIFS(Transfer!V:V,Transfer!O:O,A62)+SUMIFS(Transfer!W:W,Transfer!O:O,A62) -> 630 | I62: =D62-E62+SUMIFS(Transfer!V:V,Transfer!O:O,A62)-SUMIFS(Transfer!W:W,Transfer!O:O,A62) -> 0 | J62: =SUMIFS(Purchase!F:F,Purchase!C:C,A62,Purchase!V:V,"暂缓发货") -> 0 | K62: =F62-G62 -> 0 | L62: =H62-K62 -> 630 | M62: =H62+I62-K62 -> 630 | N62: =_xlfn.XLOOKUP(A62,'Product List'!B:B,'Product List'!F:F) -> C | O62: =SUMIF('Weekly Sales'!B:B,A62,'Weekly Sales'!R:R) -> 0.33333333 | P62: =IF(O62=0,999,ROUNDDOWN((L62)/O62,0)) -> 1890 | Q62: =IF(O62=0,999,ROUNDDOWN((M62)/O62,0)) -> 1890 | R62: =_xlfn.XLOOKUP(A62,'Product List'!B:B,'Product List'!P:P) -> 10 | S62: =IF(N62="A",6,IF(N62="B",5,2)) -> 2 | T62: =SUMIF('Weekly Sales'!B:B,A62,'Weekly Sales'!T:T) -> 0 | U62: =_xlfn.XLOOKUP(A62,'Product List'!B:B,'Product List'!O:O) -> 1000 | V62: =ROUNDUP(MAX(0,O62*(R62+S62+2)+T62-M62)/Y62,0)*Y62 -> 0 | W62: =_xlfn.XLOOKUP(A62,Sum_LA!A:A,Sum_LA!V:V) -> 0 | X62: =_xlfn.XLOOKUP(A62,Sum_HOU!A:A,Sum_HOU!V:V) -> 14 | Y62: {=_xlfn.XLOOKUP(1,('Case Pack'!A:A=A62)*('Case Pack'!F:F<=TODAY()),'Case Pack'!D:D,"未找到箱规")} -> 14 | Z62: =_xlfn.XLOOKUP(A62,'Product List'!B:B,'Product List'!M:M) -> PSP | AA62: {=_xlfn.XLOOKUP(1,('Case Pack'!A:A=A62)*('Case Pack'!F:F<=TODAY()),'Case Pack'!G:G,"未找到箱规")} -> C | AB62: =V62/Y62 -> 0 | AC62: =_xlfn.XLOOKUP(AA62,'Case Type'!A:A,'Case Type'!H:H)*AB62 -> 0

Sheet Sum_LA
A1: Item Code | B1: Product Name | C1: 46125 | D1: Purchased | E1: Arrived | F1: Sales Order | G1: Cons. | H1: OH Stock | I1: In-Transit | J1: On Hold | K1: Alloc. | L1: Avail. | M1: Total Stock | N1: ABC | O1: Wkly Fcst. | P1: OH TO | Q1: Inv. TO | R1: LT | S1: SS | T1: Extra | U1: MOQ | V1: Plan | W1: Case Pack | X1: Channel | Y1: Case Type | Z1: Case Qty | AA1: CBM
A2: BOBO22-GN | B2: =_xlfn.XLOOKUP(A2,'Product List'!B:B,'Product List'!I:I) -> MINI/MOE SILENT CRSTL RUN WHEEL LG 8.5-Green | C2: 0 | D2: =SUMIFS(Purchase!F:F,Purchase!C:C,A2,Purchase!I:I,">"&$C$1,Purchase!V:V,"<>暂缓发货",Purchase!U:U,"LA") -> 744 | E2: =SUMIFS(Purchase!F:F,Purchase!C:C,A2,Purchase!J:J,">0",Purchase!I:I,">"&$C$1,Purchase!U:U,"LA") -> 744 | F2: =SUMIFS(Sales!E:E,Sales!C:C,A2,Sales!K:K,">"&$C$1,Sales!I:I,"LA") -> 376 | G2: =SUMIFS(Sales!E:E,Sales!C:C,A2,Sales!K:K,">"&$C$1,Sales!L:L,">0",Sales!I:I,"LA") -> 368 | H2: =C2+E2-G2+SUMIFS(Transfer!W:W,Transfer!O:O,A2,Transfer!Q:Q,"LA",Transfer!U:U,">"&$C$1)-SUMIFS(Transfer!V:V,Transfer!O:O,A2,Transfer!P:P,"LA",Transfer!T:T,">"&$C$1) -> 376 | I2: =D2-E2+SUMIFS(Transfer!V:V,Transfer!O:O,A2,Transfer!Q:Q,"LA")-SUMIFS(Transfer!W:W,Transfer!O:O,A2,Transfer!Q:Q,"LA") -> 0 | J2: =SUMIFS(Purchase!F:F,Purchase!C:C,A2,Purchase!V:V,"暂缓发货",Purchase!U:U,"LA") -> 0 | K2: =F2-G2 -> 8 | L2: =H2-K2 -> 368 | M2: =H2+I2-K2 -> 368 | N2: =_xlfn.XLOOKUP(A2,'Product List'!B:B,'Product List'!F:F) -> C | O2: =SUMIFS('Weekly Sales'!R:R,'Weekly Sales'!B:B,A2,'Weekly Sales'!U:U,"LA") -> 0 | P2: =IF(O2=0,999,ROUNDDOWN((L2)/O2,0)) -> 999 | Q2: =IF(O2=0,999,ROUNDDOWN((M2)/O2,0)) -> 999 | R2: =_xlfn.XLOOKUP(A2,'Product List'!B:B,'Product List'!P:P) -> 10 | S2: =IF(N2="A",6,IF(N2="B",5,2)) -> 2 | T2: =SUMIFS('Weekly Sales'!T:T,'Weekly Sales'!B:B,A2,'Weekly Sales'!U:U,"LA") -> 0 | U2: =_xlfn.XLOOKUP(A2,'Product List'!B:B,'Product List'!O:O) -> 1000 | V2: =ROUNDUP(MAX(0,O2*(R2+S2+2)+T2-M2)/W2,0)*W2 -> 0 | W2: {=_xlfn.XLOOKUP(1,('Case Pack'!A:A=A2)*('Case Pack'!F:F<=TODAY()),'Case Pack'!D:D,"未找到箱规")} -> 16 | X2: =_xlfn.XLOOKUP(A2,'Product List'!B:B,'Product List'!M:M) -> PSP | Y2: {=_xlfn.XLOOKUP(1,('Case Pack'!A:A=A2)*('Case Pack'!F:F<=TODAY()),'Case Pack'!G:G,"未找到箱规")} -> C | Z2: =V2/W2 -> 0 | AA2: =_xlfn.XLOOKUP(Y2,'Case Type'!A:A,'Case Type'!H:H)*Z2 -> 0
A3: BOBO22-WH | B3: =_xlfn.XLOOKUP(A3,'Product List'!B:B,'Product List'!I:I) -> MINI/MOE SILENT CRSTL RUN WHEEL LG 8.5-White | C3: 412 | D3: =SUMIFS(Purchase!F:F,Purchase!C:C,A3,Purchase!I:I,">"&$C$1,Purchase!V:V,"<>暂缓发货",Purchase!U:U,"LA") -> 7336 | E3: =SUMIFS(Purchase!F:F,Purchase!C:C,A3,Purchase!J:J,">0",Purchase!I:I,">"&$C$1,Purchase!U:U,"LA") -> 7336 | F3: =SUMIFS(Sales!E:E,Sales!C:C,A3,Sales!K:K,">"&$C$1,Sales!I:I,"LA") -> 4748 | G3: =SUMIFS(Sales!E:E,Sales!C:C,A3,Sales!K:K,">"&$C$1,Sales!L:L,">0",Sales!I:I,"LA") -> 3876 | H3: =C3+E3-G3+SUMIFS(Transfer!W:W,Transfer!O:O,A3,Transfer!Q:Q,"LA",Transfer!U:U,">"&$C$1)-SUMIFS(Transfer!V:V,Transfer!O:O,A3,Transfer!P:P,"LA",Transfer!T:T,">"&$C$1) -> 3872 | I3: =D3-E3+SUMIFS(Transfer!V:V,Transfer!O:O,A3,Transfer!Q:Q,"LA")-SUMIFS(Transfer!W:W,Transfer!O:O,A3,Transfer!Q:Q,"LA") -> 0 | J3: =SUMIFS(Purchase!F:F,Purchase!C:C,A3,Purchase!V:V,"暂缓发货",Purchase!U:U,"LA") -> 1352 | K3: =F3-G3 -> 872 | L3: =H3-K3 -> 3000 | M3: =H3+I3-K3 -> 3000 | N3: =_xlfn.XLOOKUP(A3,'Product List'!B:B,'Product List'!F:F) -> A | O3: =SUMIFS('Weekly Sales'!R:R,'Weekly Sales'!B:B,A3,'Weekly Sales'!U:U,"LA") -> 95.5 | P3: =IF(O3=0,999,ROUNDDOWN((L3)/O3,0)) -> 31 | Q3: =IF(O3=0,999,ROUNDDOWN((M3)/O3,0)) -> 31 | R3: =_xlfn.XLOOKUP(A3,'Product List'!B:B,'Product List'!P:P) -> 10 | S3: =IF(N3="A",6,IF(N3="B",5,2)) -> 6 | T3: =SUMIFS('Weekly Sales'!T:T,'Weekly Sales'!B:B,A3,'Weekly Sales'!U:U,"LA") -> 620.75 | U3: =_xlfn.XLOOKUP(A3,'Product List'!B:B,'Product List'!O:O) -> 1000 | V3: =ROUNDUP(MAX(0,O3*(R3+S3+2)+T3-M3)/W3,0)*W3 -> 0 | W3: {=_xlfn.XLOOKUP(1,('Case Pack'!A:A=A3)*('Case Pack'!F:F<=TODAY()),'Case Pack'!D:D,"未找到箱规")} -> 16 | X3: =_xlfn.XLOOKUP(A3,'Product List'!B:B,'Product List'!M:M) -> PetcoUS, PetcoMX, Pet Supermarket，PSP | Y3: {=_xlfn.XLOOKUP(1,('Case Pack'!A:A=A3)*('Case Pack'!F:F<=TODAY()),'Case Pack'!G:G,"未找到箱规")} -> C | Z3: =V3/W3 -> 0 | AA3: =_xlfn.XLOOKUP(Y3,'Case Type'!A:A,'Case Type'!H:H)*Z3 -> 0
A4: CFDL1090-BR | B4: =_xlfn.XLOOKUP(A4,'Product List'!B:B,'Product List'!I:I) -> MINI/MOE SMALL ANIMAL BEDDING CRINKLE PAPER BROWN 1EA | C4: 0 | D4: =SUMIFS(Purchase!F:F,Purchase!C:C,A4,Purchase!I:I,">"&$C$1,Purchase!V:V,"<>暂缓发货",Purchase!U:U,"LA") -> 1260 | E4: =SUMIFS(Purchase!F:F,Purchase!C:C,A4,Purchase!J:J,">0",Purchase!I:I,">"&$C$1,Purchase!U:U,"LA") -> 1260 | F4: =SUMIFS(Sales!E:E,Sales!C:C,A4,Sales!K:K,">"&$C$1,Sales!I:I,"LA") -> 630 | G4: =SUMIFS(Sales!E:E,Sales!C:C,A4,Sales!K:K,">"&$C$1,Sales!L:L,">0",Sales!I:I,"LA") -> 630 | H4: =C4+E4-G4+SUMIFS(Transfer!W:W,Transfer!O:O,A4,Transfer!Q:Q,"LA",Transfer!U:U,">"&$C$1)-SUMIFS(Transfer!V:V,Transfer!O:O,A4,Transfer!P:P,"LA",Transfer!T:T,">"&$C$1) -> 630 | I4: =D4-E4+SUMIFS(Transfer!V:V,Transfer!O:O,A4,Transfer!Q:Q,"LA")-SUMIFS(Transfer!W:W,Transfer!O:O,A4,Transfer!Q:Q,"LA") -> 0 | J4: =SUMIFS(Purchase!F:F,Purchase!C:C,A4,Purchase!V:V,"暂缓发货",Purchase!U:U,"LA") -> 0 | K4: =F4-G4 -> 0 | L4: =H4-K4 -> 630 | M4: =H4+I4-K4 -> 630 | N4: =_xlfn.XLOOKUP(A4,'Product List'!B:B,'Product List'!F:F) -> C | O4: =SUMIFS('Weekly Sales'!R:R,'Weekly Sales'!B:B,A4,'Weekly Sales'!U:U,"LA") -> 0 | P4: =IF(O4=0,999,ROUNDDOWN((L4)/O4,0)) -> 999 | Q4: =IF(O4=0,999,ROUNDDOWN((M4)/O4,0)) -> 999 | R4: =_xlfn.XLOOKUP(A4,'Product List'!B:B,'Product List'!P:P) -> 10 | S4: =IF(N4="A",6,IF(N4="B",5,2)) -> 2 | T4: =SUMIFS('Weekly Sales'!T:T,'Weekly Sales'!B:B,A4,'Weekly Sales'!U:U,"LA") -> 0 | U4: =_xlfn.XLOOKUP(A4,'Product List'!B:B,'Product List'!O:O) -> 1000 | V4: =ROUNDUP(MAX(0,O4*(R4+S4+2)+T4-M4)/W4,0)*W4 -> 0 | W4: {=_xlfn.XLOOKUP(1,('Case Pack'!A:A=A4)*('Case Pack'!F:F<=TODAY()),'Case Pack'!D:D,"未找到箱规")} -> 30 | X4: =_xlfn.XLOOKUP(A4,'Product List'!B:B,'Product List'!M:M) -> PSP | Y4: {=_xlfn.XLOOKUP(1,('Case Pack'!A:A=A4)*('Case Pack'!F:F<=TODAY()),'Case Pack'!G:G,"未找到箱规")} -> A | Z4: =V4/W4 -> 0 | AA4: =_xlfn.XLOOKUP(Y4,'Case Type'!A:A,'Case Type'!H:H)*Z4 -> 0
A5: CFDL1090-PK | B5: =_xlfn.XLOOKUP(A5,'Product List'!B:B,'Product List'!I:I) -> MINI/MOE SMALL ANIMAL BEDDING PAPER PEBBLES PSTCH/CREAM 1EA | C5: 0 | D5: =SUMIFS(Purchase!F:F,Purchase!C:C,A5,Purchase!I:I,">"&$C$1,Purchase!V:V,"<>暂缓发货",Purchase!U:U,"LA") -> 1260 | E5: =SUMIFS(Purchase!F:F,Purchase!C:C,A5,Purchase!J:J,">0",Purchase!I:I,">"&$C$1,Purchase!U:U,"LA") -> 1260 | F5: =SUMIFS(Sales!E:E,Sales!C:C,A5,Sales!K:K,">"&$C$1,Sales!I:I,"LA") -> 630 | G5: =SUMIFS(Sales!E:E,Sales!C:C,A5,Sales!K:K,">"&$C$1,Sales!L:L,">0",Sales!I:I,"LA") -> 630 | H5: =C5+E5-G5+SUMIFS(Transfer!W:W,Transfer!O:O,A5,Transfer!Q:Q,"LA",Transfer!U:U,">"&$C$1)-SUMIFS(Transfer!V:V,Transfer!O:O,A5,Transfer!P:P,"LA",Transfer!T:T,">"&$C$1) -> 630 | I5: =D5-E5+SUMIFS(Transfer!V:V,Transfer!O:O,A5,Transfer!Q:Q,"LA")-SUMIFS(Transfer!W:W,Transfer!O:O,A5,Transfer!Q:Q,"LA") -> 0 | J5: =SUMIFS(Purchase!F:F,Purchase!C:C,A5,Purchase!V:V,"暂缓发货",Purchase!U:U,"LA") -> 0 | K5: =F5-G5 -> 0 | L5: =H5-K5 -> 630 | M5: =H5+I5-K5 -> 630 | N5: =_xlfn.XLOOKUP(A5,'Product List'!B:B,'Product List'!F:F) -> C | O5: =SUMIFS('Weekly Sales'!R:R,'Weekly Sales'!B:B,A5,'Weekly Sales'!U:U,"LA") -> 0 | P5: =IF(O5=0,999,ROUNDDOWN((L5)/O5,0)) -> 999 | Q5: =IF(O5=0,999,ROUNDDOWN((M5)/O5,0)) -> 999 | R5: =_xlfn.XLOOKUP(A5,'Product List'!B:B,'Product List'!P:P) -> 10 | S5: =IF(N5="A",6,IF(N5="B",5,2)) -> 2 | T5: =SUMIFS('Weekly Sales'!T:T,'Weekly Sales'!B:B,A5,'Weekly Sales'!U:U,"LA") -> 0 | U5: =_xlfn.XLOOKUP(A5,'Product List'!B:B,'Product List'!O:O) -> 1000 | V5: =ROUNDUP(MAX(0,O5*(R5+S5+2)+T5-M5)/W5,0)*W5 -> 0 | W5: {=_xlfn.XLOOKUP(1,('Case Pack'!A:A=A5)*('Case Pack'!F:F<=TODAY()),'Case Pack'!D:D,"未找到箱规")} -> 30 | X5: =_xlfn.XLOOKUP(A5,'Product List'!B:B,'Product List'!M:M) -> PSP | Y5: {=_xlfn.XLOOKUP(1,('Case Pack'!A:A=A5)*('Case Pack'!F:F<=TODAY()),'Case Pack'!G:G,"未找到箱规")} -> A | Z5: =V5/W5 -> 0 | AA5: =_xlfn.XLOOKUP(Y5,'Case Type'!A:A,'Case Type'!H:H)*Z5 -> 0
A6: CFDL9000-GN-YL | B6: =_xlfn.XLOOKUP(A6,'Product List'!B:B,'Product List'!I:I) -> MINI/MOE SMALL ANIMAL BEDDING ROLLED PAPER FOREST MIX 1EA | C6: 0 | D6: =SUMIFS(Purchase!F:F,Purchase!C:C,A6,Purchase!I:I,">"&$C$1,Purchase!V:V,"<>暂缓发货",Purchase!U:U,"LA") -> 3420 | E6: =SUMIFS(Purchase!F:F,Purchase!C:C,A6,Purchase!J:J,">0",Purchase!I:I,">"&$C$1,Purchase!U:U,"LA") -> 3420 | F6: =SUMIFS(Sales!E:E,Sales!C:C,A6,Sales!K:K,">"&$C$1,Sales!I:I,"LA") -> 2040 | G6: =SUMIFS(Sales!E:E,Sales!C:C,A6,Sales!K:K,">"&$C$1,Sales!L:L,">0",Sales!I:I,"LA") -> 2040 | H6: =C6+E6-G6+SUMIFS(Transfer!W:W,Transfer!O:O,A6,Transfer!Q:Q,"LA",Transfer!U:U,">"&$C$1)-SUMIFS(Transfer!V:V,Transfer!O:O,A6,Transfer!P:P,"LA",Transfer!T:T,">"&$C$1) -> 1380 | I6: =D6-E6+SUMIFS(Transfer!V:V,Transfer!O:O,A6,Transfer!Q:Q,"LA")-SUMIFS(Transfer!W:W,Transfer!O:O,A6,Transfer!Q:Q,"LA") -> 0 | J6: =SUMIFS(Purchase!F:F,Purchase!C:C,A6,Purchase!V:V,"暂缓发货",Purchase!U:U,"LA") -> 0 | K6: =F6-G6 -> 0 | L6: =H6-K6 -> 1380 | M6: =H6+I6-K6 -> 1380 | N6: =_xlfn.XLOOKUP(A6,'Product List'!B:B,'Product List'!F:F) -> B | O6: =SUMIFS('Weekly Sales'!R:R,'Weekly Sales'!B:B,A6,'Weekly Sales'!U:U,"LA") -> 0 | P6: =IF(O6=0,999,ROUNDDOWN((L6)/O6,0)) -> 999 | Q6: =IF(O6=0,999,ROUNDDOWN((M6)/O6,0)) -> 999 | R6: =_xlfn.XLOOKUP(A6,'Product List'!B:B,'Product List'!P:P) -> 10 | S6: =IF(N6="A",6,IF(N6="B",5,2)) -> 5 | T6: =SUMIFS('Weekly Sales'!T:T,'Weekly Sales'!B:B,A6,'Weekly Sales'!U:U,"LA") -> 0 | U6: =_xlfn.XLOOKUP(A6,'Product List'!B:B,'Product List'!O:O) -> 1000 | V6: =ROUNDUP(MAX(0,O6*(R6+S6+2)+T6-M6)/W6,0)*W6 -> 0 | W6: {=_xlfn.XLOOKUP(1,('Case Pack'!A:A=A6)*('Case Pack'!F:F<=TODAY()),'Case Pack'!D:D,"未找到箱规")} -> 30 | X6: =_xlfn.XLOOKUP(A6,'Product List'!B:B,'Product List'!M:M) -> PSP | Y6: {=_xlfn.XLOOKUP(1,('Case Pack'!A:A=A6)*('Case Pack'!F:F<=TODAY()),'Case Pack'!G:G,"未找到箱规")} -> A | Z6: =V6/W6 -> 0 | AA6: =_xlfn.XLOOKUP(Y6,'Case Type'!A:A,'Case Type'!H:H)*Z6 -> 0
A7: CFLS18000 | B7: =_xlfn.XLOOKUP(A7,'Product List'!B:B,'Product List'!I:I) -> MMO-GREEN APPLE CHEW | C7: 0 | D7: =SUMIFS(Purchase!F:F,Purchase!C:C,A7,Purchase!I:I,">"&$C$1,Purchase!V:V,"<>暂缓发货",Purchase!U:U,"LA") -> 9936 | E7: =SUMIFS(Purchase!F:F,Purchase!C:C,A7,Purchase!J:J,">0",Purchase!I:I,">"&$C$1,Purchase!U:U,"LA") -> 9936 | F7: =SUMIFS(Sales!E:E,Sales!C:C,A7,Sales!K:K,">"&$C$1,Sales!I:I,"LA") -> 5568 | G7: =SUMIFS(Sales!E:E,Sales!C:C,A7,Sales!K:K,">"&$C$1,Sales!L:L,">0",Sales!I:I,"LA") -> 4560 | H7: =C7+E7-G7+SUMIFS(Transfer!W:W,Transfer!O:O,A7,Transfer!Q:Q,"LA",Transfer!U:U,">"&$C$1)-SUMIFS(Transfer!V:V,Transfer!O:O,A7,Transfer!P:P,"LA",Transfer!T:T,">"&$C$1) -> 5376 | I7: =D7-E7+SUMIFS(Transfer!V:V,Transfer!O:O,A7,Transfer!Q:Q,"LA")-SUMIFS(Transfer!W:W,Transfer!O:O,A7,Transfer!Q:Q,"LA") -> 0 | J7: =SUMIFS(Purchase!F:F,Purchase!C:C,A7,Purchase!V:V,"暂缓发货",Purchase!U:U,"LA") -> 2112 | K7: =F7-G7 -> 1008 | L7: =H7-K7 -> 4368 | M7: =H7+I7-K7 -> 4368 | N7: =_xlfn.XLOOKUP(A7,'Product List'!B:B,'Product List'!F:F) -> B | O7: =SUMIFS('Weekly Sales'!R:R,'Weekly Sales'!B:B,A7,'Weekly Sales'!U:U,"LA") -> 144.83333 | P7: =IF(O7=0,999,ROUNDDOWN((L7)/O7,0)) -> 30 | Q7: =IF(O7=0,999,ROUNDDOWN((M7)/O7,0)) -> 30 | R7: =_xlfn.XLOOKUP(A7,'Product List'!B:B,'Product List'!P:P) -> 10 | S7: =IF(N7="A",6,IF(N7="B",5,2)) -> 5 | T7: =SUMIFS('Weekly Sales'!T:T,'Weekly Sales'!B:B,A7,'Weekly Sales'!U:U,"LA") -> 470.70833 | U7: =_xlfn.XLOOKUP(A7,'Product List'!B:B,'Product List'!O:O) -> 1000 | V7: =ROUNDUP(MAX(0,O7*(R7+S7+2)+T7-M7)/W7,0)*W7 -> 0 | W7: {=_xlfn.XLOOKUP(1,('Case Pack'!A:A=A7)*('Case Pack'!F:F<=TODAY()),'Case Pack'!D:D,"未找到箱规")} -> 48 | X7: =_xlfn.XLOOKUP(A7,'Product List'!B:B,'Product List'!M:M) -> PetcoUS，PSP | Y7: {=_xlfn.XLOOKUP(1,('Case Pack'!A:A=A7)*('Case Pack'!F:F<=TODAY()),'Case Pack'!G:G,"未找到箱规")} -> B | Z7: =V7/W7 -> 0 | AA7: =_xlfn.XLOOKUP(Y7,'Case Type'!A:A,'Case Type'!H:H)*Z7 -> 0
A8: CFLS64000YE | B8: =_xlfn.XLOOKUP(A8,'Product List'!B:B,'Product List'!I:I) -> MMO-CAMP LUNCH BOX CHEW | C8: 0 | D8: =SUMIFS(Purchase!F:F,Purchase!C:C,A8,Purchase!I:I,">"&$C$1,Purchase!V:V,"<>暂缓发货",Purchase!U:U,"LA") -> 10800 | E8: =SUMIFS(Purchase!F:F,Purchase!C:C,A8,Purchase!J:J,">0",Purchase!I:I,">"&$C$1,Purchase!U:U,"LA") -> 10800 | F8: =SUMIFS(Sales!E:E,Sales!C:C,A8,Sales!K:K,">"&$C$1,Sales!I:I,"LA") -> 6768 | G8: =SUMIFS(Sales!E:E,Sales!C:C,A8,Sales!K:K,">"&$C$1,Sales!L:L,">0",Sales!I:I,"LA") -> 5616 | H8: =C8+E8-G8+SUMIFS(Transfer!W:W,Transfer!O:O,A8,Transfer!Q:Q,"LA",Transfer!U:U,">"&$C$1)-SUMIFS(Transfer!V:V,Transfer!O:O,A8,Transfer!P:P,"LA",Transfer!T:T,">"&$C$1) -> 5184 | I8: =D8-E8+SUMIFS(Transfer!V:V,Transfer!O:O,A8,Transfer!Q:Q,"LA")-SUMIFS(Transfer!W:W,Transfer!O:O,A8,Transfer!Q:Q,"LA") -> 0 | J8: =SUMIFS(Purchase!F:F,Purchase!C:C,A8,Purchase!V:V,"暂缓发货",Purchase!U:U,"LA") -> 2160 | K8: =F8-G8 -> 1152 | L8: =H8-K8 -> 4032 | M8: =H8+I8-K8 -> 4032 | N8: =_xlfn.XLOOKUP(A8,'Product List'!B:B,'Product List'!F:F) -> B | O8: =SUMIFS('Weekly Sales'!R:R,'Weekly Sales'!B:B,A8,'Weekly Sales'!U:U,"LA") -> 160.33333 | P8: =IF(O8=0,999,ROUNDDOWN((L8)/O8,0)) -> 25 | Q8: =IF(O8=0,999,ROUNDDOWN((M8)/O8,0)) -> 25 | R8: =_xlfn.XLOOKUP(A8,'Product List'!B:B,'Product List'!P:P) -> 10 | S8: =IF(N8="A",6,IF(N8="B",5,2)) -> 5 | T8: =SUMIFS('Weekly Sales'!T:T,'Weekly Sales'!B:B,A8,'Weekly Sales'!U:U,"LA") -> 521.08333 | U8: =_xlfn.XLOOKUP(A8,'Product List'!B:B,'Product List'!O:O) -> 1000 | V8: =ROUNDUP(MAX(0,O8*(R8+S8+2)+T8-M8)/W8,0)*W8 -> 0 | W8: {=_xlfn.XLOOKUP(1,('Case Pack'!A:A=A8)*('Case Pack'!F:F<=TODAY()),'Case Pack'!D:D,"未找到箱规")} -> 72 | X8: =_xlfn.XLOOKUP(A8,'Product List'!B:B,'Product List'!M:M) -> PetcoUS, Pet Supermarket，PSP | Y8: {=_xlfn.XLOOKUP(1,('Case Pack'!A:A=A8)*('Case Pack'!F:F<=TODAY()),'Case Pack'!G:G,"未找到箱规")} -> B | Z8: =V8/W8 -> 0 | AA8: =_xlfn.XLOOKUP(Y8,'Case Type'!A:A,'Case Type'!H:H)*Z8 -> 0
A9: CFLS71000WH | B9: =_xlfn.XLOOKUP(A9,'Product List'!B:B,'Product List'!I:I) -> MMO-SHELL PEARL HAMSTER CHEW | C9: 0 | D9: =SUMIFS(Purchase!F:F,Purchase!C:C,A9,Purchase!I:I,">"&$C$1,Purchase!V:V,"<>暂缓发货",Purchase!U:U,"LA") -> 5248 | E9: =SUMIFS(Purchase!F:F,Purchase!C:C,A9,Purchase!J:J,">0",Purchase!I:I,">"&$C$1,Purchase!U:U,"LA") -> 5248 | F9: =SUMIFS(Sales!E:E,Sales!C:C,A9,Sales!K:K,">"&$C$1,Sales!I:I,"LA") -> 2112 | G9: =SUMIFS(Sales!E:E,Sales!C:C,A9,Sales!K:K,">"&$C$1,Sales!L:L,">0",Sales!I:I,"LA") -> 2112 | H9: =C9+E9-G9+SUMIFS(Transfer!W:W,Transfer!O:O,A9,Transfer!Q:Q,"LA",Transfer!U:U,">"&$C$1)-SUMIFS(Transfer!V:V,Transfer!O:O,A9,Transfer!P:P,"LA",Transfer!T:T,">"&$C$1) -> 3136 | I9: =D9-E9+SUMIFS(Transfer!V:V,Transfer!O:O,A9,Transfer!Q:Q,"LA")-SUMIFS(Transfer!W:W,Transfer!O:O,A9,Transfer!Q:Q,"LA") -> 0 | J9: =SUMIFS(Purchase!F:F,Purchase!C:C,A9,Purchase!V:V,"暂缓发货",Purchase!U:U,"LA") -> 640 | K9: =F9-G9 -> 0 | L9: =H9-K9 -> 3136 | M9: =H9+I9-K9 -> 3136 | N9: =_xlfn.XLOOKUP(A9,'Product List'!B:B,'Product List'!F:F) -> C | O9: =SUMIFS('Weekly Sales'!R:R,'Weekly Sales'!B:B,A9,'Weekly Sales'!U:U,"LA") -> 31.166667 | P9: =IF(O9=0,999,ROUNDDOWN((L9)/O9,0)) -> 100 | Q9: =IF(O9=0,999,ROUNDDOWN((M9)/O9,0)) -> 100 | R9: =_xlfn.XLOOKUP(A9,'Product List'!B:B,'Product List'!P:P) -> 10 | S9: =IF(N9="A",6,IF(N9="B",5,2)) -> 2 | T9: =SUMIFS('Weekly Sales'!T:T,'Weekly Sales'!B:B,A9,'Weekly Sales'!U:U,"LA") -> 0 | U9: =_xlfn.XLOOKUP(A9,'Product List'!B:B,'Product List'!O:O) -> 1000 | V9: =ROUNDUP(MAX(0,O9*(R9+S9+2)+T9-M9)/W9,0)*W9 -> 0 | W9: {=_xlfn.XLOOKUP(1,('Case Pack'!A:A=A9)*('Case Pack'!F:F<=TODAY()),'Case Pack'!D:D,"未找到箱规")} -> 64 | X9: =_xlfn.XLOOKUP(A9,'Product List'!B:B,'Product List'!M:M) -> PetcoUS | Y9: {=_xlfn.XLOOKUP(1,('Case Pack'!A:A=A9)*('Case Pack'!F:F<=TODAY()),'Case Pack'!G:G,"未找到箱规")} -> B | Z9: =V9/W9 -> 0 | AA9: =_xlfn.XLOOKUP(Y9,'Case Type'!A:A,'Case Type'!H:H)*Z9 -> 0
A10: CPSH54000WH | B10: =_xlfn.XLOOKUP(A10,'Product List'!B:B,'Product List'!I:I) -> NONO Magnetic Water Bottle (220 ML) | C10: 0 | D10: =SUMIFS(Purchase!F:F,Purchase!C:C,A10,Purchase!I:I,">"&$C$1,Purchase!V:V,"<>暂缓发货",Purchase!U:U,"LA") -> 1260 | E10: =SUMIFS(Purchase!F:F,Purchase!C:C,A10,Purchase!J:J,">0",Purchase!I:I,">"&$C$1,Purchase!U:U,"LA") -> 1260 | F10: =SUMIFS(Sales!E:E,Sales!C:C,A10,Sales!K:K,">"&$C$1,Sales!I:I,"LA") -> 660 | G10: =SUMIFS(Sales!E:E,Sales!C:C,A10,Sales!K:K,">"&$C$1,Sales!L:L,">0",Sales!I:I,"LA") -> 660 | H10: =C10+E10-G10+SUMIFS(Transfer!W:W,Transfer!O:O,A10,Transfer!Q:Q,"LA",Transfer!U:U,">"&$C$1)-SUMIFS(Transfer!V:V,Transfer!O:O,A10,Transfer!P:P,"LA",Transfer!T:T,">"&$C$1) -> 600 | I10: =D10-E10+SUMIFS(Transfer!V:V,Transfer!O:O,A10,Transfer!Q:Q,"LA")-SUMIFS(Transfer!W:W,Transfer!O:O,A10,Transfer!Q:Q,"LA") -> 0 | J10: =SUMIFS(Purchase!F:F,Purchase!C:C,A10,Purchase!V:V,"暂缓发货",Purchase!U:U,"LA") -> 0 | K10: =F10-G10 -> 0 | L10: =H10-K10 -> 600 | M10: =H10+I10-K10 -> 600 | N10: =_xlfn.XLOOKUP(A10,'Product List'!B:B,'Product List'!F:F) -> C | O10: =SUMIFS('Weekly Sales'!R:R,'Weekly Sales'!B:B,A10,'Weekly Sales'!U:U,"LA") -> 0 | P10: =IF(O10=0,999,ROUNDDOWN((L10)/O10,0)) -> 999 | Q10: =IF(O10=0,999,ROUNDDOWN((M10)/O10,0)) -> 999 | R10: =_xlfn.XLOOKUP(A10,'Product List'!B:B,'Product List'!P:P) -> 10 | S10: =IF(N10="A",6,IF(N10="B",5,2)) -> 2 | T10: =SUMIFS('Weekly Sales'!T:T,'Weekly Sales'!B:B,A10,'Weekly Sales'!U:U,"LA") -> 0 | U10: =_xlfn.XLOOKUP(A10,'Product List'!B:B,'Product List'!O:O) -> 500 | V10: =ROUNDUP(MAX(0,O10*(R10+S10+2)+T10-M10)/W10,0)*W10 -> 0 | W10: {=_xlfn.XLOOKUP(1,('Case Pack'!A:A=A10)*('Case Pack'!F:F<=TODAY()),'Case Pack'!D:D,"未找到箱规")} -> 60 | X10: =_xlfn.XLOOKUP(A10,'Product List'!B:B,'Product List'!M:M) -> PetcoMX,PSP | Y10: {=_xlfn.XLOOKUP(1,('Case Pack'!A:A=A10)*('Case Pack'!F:F<=TODAY()),'Case Pack'!G:G,"未找到箱规")} -> A | Z10: =V10/W10 -> 0 | AA10: =_xlfn.XLOOKUP(Y10,'Case Type'!A:A,'Case Type'!H:H)*Z10 -> 0
A11: CPSH60007BK | B11: =_xlfn.XLOOKUP(A11,'Product List'!B:B,'Product List'!I:I) -> MINI & MOE MAG CONECT WTR BTL 4 OZ | C11: 0 | D11: =SUMIFS(Purchase!F:F,Purchase!C:C,A11,Purchase!I:I,">"&$C$1,Purchase!V:V,"<>暂缓发货",Purchase!U:U,"LA") -> 15606 | E11: =SUMIFS(Purchase!F:F,Purchase!C:C,A11,Purchase!J:J,">0",Purchase!I:I,">"&$C$1,Purchase!U:U,"LA") -> 15606 | F11: =SUMIFS(Sales!E:E,Sales!C:C,A11,Sales!K:K,">"&$C$1,Sales!I:I,"LA") -> 6912 | G11: =SUMIFS(Sales!E:E,Sales!C:C,A11,Sales!K:K,">"&$C$1,Sales!L:L,">0",Sales!I:I,"LA") -> 6912 | H11: =C11+E11-G11+SUMIFS(Transfer!W:W,Transfer!O:O,A11,Transfer!Q:Q,"LA",Transfer!U:U,">"&$C$1)-SUMIFS(Transfer!V:V,Transfer!O:O,A11,Transfer!P:P,"LA",Transfer!T:T,">"&$C$1) -> 8694 | I11: =D11-E11+SUMIFS(Transfer!V:V,Transfer!O:O,A11,Transfer!Q:Q,"LA")-SUMIFS(Transfer!W:W,Transfer!O:O,A11,Transfer!Q:Q,"LA") -> 0 | J11: =SUMIFS(Purchase!F:F,Purchase!C:C,A11,Purchase!V:V,"暂缓发货",Purchase!U:U,"LA") -> 432 | K11: =F11-G11 -> 0 | L11: =H11-K11 -> 8694 | M11: =H11+I11-K11 -> 8694 | N11: =_xlfn.XLOOKUP(A11,'Product List'!B:B,'Product List'!F:F) -> A | O11: =SUMIFS('Weekly Sales'!R:R,'Weekly Sales'!B:B,A11,'Weekly Sales'!U:U,"LA") -> 315 | P11: =IF(O11=0,999,ROUNDDOWN((L11)/O11,0)) -> 27 | Q11: =IF(O11=0,999,ROUNDDOWN((M11)/O11,0)) -> 27 | R11: =_xlfn.XLOOKUP(A11,'Product List'!B:B,'Product List'!P:P) -> 10 | S11: =IF(N11="A",6,IF(N11="B",5,2)) -> 6 | T11: =SUMIFS('Weekly Sales'!T:T,'Weekly Sales'!B:B,A11,'Weekly Sales'!U:U,"LA") -> 2047.5 | U11: =_xlfn.XLOOKUP(A11,'Product List'!B:B,'Product List'!O:O) -> 500 | V11: =ROUNDUP(MAX(0,O11*(R11+S11+2)+T11-M11)/W11,0)*W11 -> 0 | W11: {=_xlfn.XLOOKUP(1,('Case Pack'!A:A=A11)*('Case Pack'!F:F<=TODAY()),'Case Pack'!D:D,"未找到箱规")} -> 54 | X11: =_xlfn.XLOOKUP(A11,'Product List'!B:B,'Product List'!M:M) -> Petsmart | Y11: {=_xlfn.XLOOKUP(1,('Case Pack'!A:A=A11)*('Case Pack'!F:F<=TODAY()),'Case Pack'!G:G,"未找到箱规")} -> A | Z11: =V11/W11 -> 0 | AA11: =_xlfn.XLOOKUP(Y11,'Case Type'!A:A,'Case Type'!H:H)*Z11 -> 0
A12: CPSL22004GN | B12: =_xlfn.XLOOKUP(A12,'Product List'!B:B,'Product List'!I:I) -> Ceramic Candy Bowl | C12: 0 | D12: =SUMIFS(Purchase!F:F,Purchase!C:C,A12,Purchase!I:I,">"&$C$1,Purchase!V:V,"<>暂缓发货",Purchase!U:U,"LA") -> 1248 | E12: =SUMIFS(Purchase!F:F,Purchase!C:C,A12,Purchase!J:J,">0",Purchase!I:I,">"&$C$1,Purchase!U:U,"LA") -> 1248 | F12: =SUMIFS(Sales!E:E,Sales!C:C,A12,Sales!K:K,">"&$C$1,Sales!I:I,"LA") -> 672 | G12: =SUMIFS(Sales!E:E,Sales!C:C,A12,Sales!K:K,">"&$C$1,Sales!L:L,">0",Sales!I:I,"LA") -> 672 | H12: =C12+E12-G12+SUMIFS(Transfer!W:W,Transfer!O:O,A12,Transfer!Q:Q,"LA",Transfer!U:U,">"&$C$1)-SUMIFS(Transfer!V:V,Transfer!O:O,A12,Transfer!P:P,"LA",Transfer!T:T,">"&$C$1) -> 576 | I12: =D12-E12+SUMIFS(Transfer!V:V,Transfer!O:O,A12,Transfer!Q:Q,"LA")-SUMIFS(Transfer!W:W,Transfer!O:O,A12,Transfer!Q:Q,"LA") -> 0 | J12: =SUMIFS(Purchase!F:F,Purchase!C:C,A12,Purchase!V:V,"暂缓发货",Purchase!U:U,"LA") -> 0 | K12: =F12-G12 -> 0 | L12: =H12-K12 -> 576 | M12: =H12+I12-K12 -> 576 | N12: =_xlfn.XLOOKUP(A12,'Product List'!B:B,'Product List'!F:F) -> C | O12: =SUMIFS('Weekly Sales'!R:R,'Weekly Sales'!B:B,A12,'Weekly Sales'!U:U,"LA") -> 0 | P12: =IF(O12=0,999,ROUNDDOWN((L12)/O12,0)) -> 999 | Q12: =IF(O12=0,999,ROUNDDOWN((M12)/O12,0)) -> 999 | R12: =_xlfn.XLOOKUP(A12,'Product List'!B:B,'Product List'!P:P) -> 15 | S12: =IF(N12="A",6,IF(N12="B",5,2)) -> 2 | T12: =SUMIFS('Weekly Sales'!T:T,'Weekly Sales'!B:B,A12,'Weekly Sales'!U:U,"LA") -> 0 | U12: =_xlfn.XLOOKUP(A12,'Product List'!B:B,'Product List'!O:O) -> 2000 | V12: =ROUNDUP(MAX(0,O12*(R12+S12+2)+T12-M12)/W12,0)*W12 -> 0 | W12: {=_xlfn.XLOOKUP(1,('Case Pack'!A:A=A12)*('Case Pack'!F:F<=TODAY()),'Case Pack'!D:D,"未找到箱规")} -> 48 | X12: =_xlfn.XLOOKUP(A12,'Product List'!B:B,'Product List'!M:M) -> PetcoMX,PSP | Y12: {=_xlfn.XLOOKUP(1,('Case Pack'!A:A=A12)*('Case Pack'!F:F<=TODAY()),'Case Pack'!G:G,"未找到箱规")} -> B | Z12: =V12/W12 -> 0 | AA12: =_xlfn.XLOOKUP(Y12,'Case Type'!A:A,'Case Type'!H:H)*Z12 -> 0
A13: CPWJ0011 | B13: =_xlfn.XLOOKUP(A13,'Product List'!B:B,'Product List'!I:I) -> MINI/MOE MUSHROOM CABIN | C13: 0 | D13: =SUMIFS(Purchase!F:F,Purchase!C:C,A13,Purchase!I:I,">"&$C$1,Purchase!V:V,"<>暂缓发货",Purchase!U:U,"LA") -> 2368 | E13: =SUMIFS(Purchase!F:F,Purchase!C:C,A13,Purchase!J:J,">0",Purchase!I:I,">"&$C$1,Purchase!U:U,"LA") -> 1856 | F13: =SUMIFS(Sales!E:E,Sales!C:C,A13,Sales!K:K,">"&$C$1,Sales!I:I,"LA") -> 1360 | G13: =SUMIFS(Sales!E:E,Sales!C:C,A13,Sales!K:K,">"&$C$1,Sales!L:L,">0",Sales!I:I,"LA") -> 1296 | H13: =C13+E13-G13+SUMIFS(Transfer!W:W,Transfer!O:O,A13,Transfer!Q:Q,"LA",Transfer!U:U,">"&$C$1)-SUMIFS(Transfer!V:V,Transfer!O:O,A13,Transfer!P:P,"LA",Transfer!T:T,">"&$C$1) -> 560 | I13: =D13-E13+SUMIFS(Transfer!V:V,Transfer!O:O,A13,Transfer!Q:Q,"LA")-SUMIFS(Transfer!W:W,Transfer!O:O,A13,Transfer!Q:Q,"LA") -> 512 | J13: =SUMIFS(Purchase!F:F,Purchase!C:C,A13,Purchase!V:V,"暂缓发货",Purchase!U:U,"LA") -> 0 | K13: =F13-G13 -> 64 | L13: =H13-K13 -> 496 | M13: =H13+I13-K13 -> 1008 | N13: =_xlfn.XLOOKUP(A13,'Product List'!B:B,'Product List'!F:F) -> B | O13: =SUMIFS('Weekly Sales'!R:R,'Weekly Sales'!B:B,A13,'Weekly Sales'!U:U,"LA") -> 0 | P13: =IF(O13=0,999,ROUNDDOWN((L13)/O13,0)) -> 999 | Q13: =IF(O13=0,999,ROUNDDOWN((M13)/O13,0)) -> 999 | R13: =_xlfn.XLOOKUP(A13,'Product List'!B:B,'Product List'!P:P) -> 15 | S13: =IF(N13="A",6,IF(N13="B",5,2)) -> 5 | T13: =SUMIFS('Weekly Sales'!T:T,'Weekly Sales'!B:B,A13,'Weekly Sales'!U:U,"LA") -> 0 | U13: =_xlfn.XLOOKUP(A13,'Product List'!B:B,'Product List'!O:O) -> 500 | V13: =ROUNDUP(MAX(0,O13*(R13+S13+2)+T13-M13)/W13,0)*W13 -> 0 | W13: {=_xlfn.XLOOKUP(1,('Case Pack'!A:A=A13)*('Case Pack'!F:F<=TODAY()),'Case Pack'!D:D,"未找到箱规")} -> 16 | X13: =_xlfn.XLOOKUP(A13,'Product List'!B:B,'Product List'!M:M) -> PSP | Y13: {=_xlfn.XLOOKUP(1,('Case Pack'!A:A=A13)*('Case Pack'!F:F<=TODAY()),'Case Pack'!G:G,"未找到箱规")} -> C | Z13: =V13/W13 -> 0 | AA13: =_xlfn.XLOOKUP(Y13,'Case Type'!A:A,'Case Type'!H:H)*Z13 -> 0
... A35: R-72 | B35: =_xlfn.XLOOKUP(A35,'Product List'!B:B,'Product List'!I:I) -> MMO-WAVE BRIDGE | C35: 352 | D35: =SUMIFS(Purchase!F:F,Purchase!C:C,A35,Purchase!I:I,">"&$C$1,Purchase!V:V,"<>暂缓发货",Purchase!U:U,"LA") -> 2508 | E35: =SUMIFS(Purchase!F:F,Purchase!C:C,A35,Purchase!J:J,">0",Purchase!I:I,">"&$C$1,Purchase!U:U,"LA") -> 2508 | F35: =SUMIFS(Sales!E:E,Sales!C:C,A35,Sales!K:K,">"&$C$1,Sales!I:I,"LA") -> 2853 | G35: =SUMIFS(Sales!E:E,Sales!C:C,A35,Sales!K:K,">"&$C$1,Sales!L:L,">0",Sales!I:I,"LA") -> 2853 | H35: =C35+E35-G35+SUMIFS(Transfer!W:W,Transfer!O:O,A35,Transfer!Q:Q,"LA",Transfer!U:U,">"&$C$1)-SUMIFS(Transfer!V:V,Transfer!O:O,A35,Transfer!P:P,"LA",Transfer!T:T,">"&$C$1) -> 7 | I35: =D35-E35+SUMIFS(Transfer!V:V,Transfer!O:O,A35,Transfer!Q:Q,"LA")-SUMIFS(Transfer!W:W,Transfer!O:O,A35,Transfer!Q:Q,"LA") -> 0 | J35: =SUMIFS(Purchase!F:F,Purchase!C:C,A35,Purchase!V:V,"暂缓发货",Purchase!U:U,"LA") -> 0 | K35: =F35-G35 -> 0 | L35: =H35-K35 -> 7 | M35: =H35+I35-K35 -> 7 | N35: =_xlfn.XLOOKUP(A35,'Product List'!B:B,'Product List'!F:F) -> B | O35: =SUMIFS('Weekly Sales'!R:R,'Weekly Sales'!B:B,A35,'Weekly Sales'!U:U,"LA") -> 0 | P35: =IF(O35=0,999,ROUNDDOWN((L35)/O35,0)) -> 999 | Q35: =IF(O35=0,999,ROUNDDOWN((M35)/O35,0)) -> 999 | R35: =_xlfn.XLOOKUP(A35,'Product List'!B:B,'Product List'!P:P) -> 15 | S35: =IF(N35="A",6,IF(N35="B",5,2)) -> 5 | T35: =SUMIFS('Weekly Sales'!T:T,'Weekly Sales'!B:B,A35,'Weekly Sales'!U:U,"LA") -> 0 | U35: =_xlfn.XLOOKUP(A35,'Product List'!B:B,'Product List'!O:O) -> 500 | V35: =ROUNDUP(MAX(0,O35*(R35+S35+2)+T35-M35)/W35,0)*W35 -> 0 | W35: {=_xlfn.XLOOKUP(1,('Case Pack'!A:A=A35)*('Case Pack'!F:F<=TODAY()),'Case Pack'!D:D,"未找到箱规")} -> 33 | X35: =_xlfn.XLOOKUP(A35,'Product List'!B:B,'Product List'!M:M) -> PetcoUS，Canada | Y35: {=_xlfn.XLOOKUP(1,('Case Pack'!A:A=A35)*('Case Pack'!F:F<=TODAY()),'Case Pack'!G:G,"未找到箱规")} -> C | Z35: =V35/W35 -> 0 | AA35: =_xlfn.XLOOKUP(Y35,'Case Type'!A:A,'Case Type'!H:H)*Z35 -> 0
A36: R-8 | B36: =_xlfn.XLOOKUP(A36,'Product List'!B:B,'Product List'!I:I) -> MINI/MOE BENDABLE BIRCHWOOD FENCE | C36: =746 -> 746 | D36: =SUMIFS(Purchase!F:F,Purchase!C:C,A36,Purchase!I:I,">"&$C$1,Purchase!V:V,"<>暂缓发货",Purchase!U:U,"LA") -> 2592 | E36: =SUMIFS(Purchase!F:F,Purchase!C:C,A36,Purchase!J:J,">0",Purchase!I:I,">"&$C$1,Purchase!U:U,"LA") -> 2592 | F36: =SUMIFS(Sales!E:E,Sales!C:C,A36,Sales!K:K,">"&$C$1,Sales!I:I,"LA") -> 2634 | G36: =SUMIFS(Sales!E:E,Sales!C:C,A36,Sales!K:K,">"&$C$1,Sales!L:L,">0",Sales!I:I,"LA") -> 2634 | H36: =C36+E36-G36+SUMIFS(Transfer!W:W,Transfer!O:O,A36,Transfer!Q:Q,"LA",Transfer!U:U,">"&$C$1)-SUMIFS(Transfer!V:V,Transfer!O:O,A36,Transfer!P:P,"LA",Transfer!T:T,">"&$C$1) -> 704 | I36: =D36-E36+SUMIFS(Transfer!V:V,Transfer!O:O,A36,Transfer!Q:Q,"LA")-SUMIFS(Transfer!W:W,Transfer!O:O,A36,Transfer!Q:Q,"LA") -> 0 | J36: =SUMIFS(Purchase!F:F,Purchase!C:C,A36,Purchase!V:V,"暂缓发货",Purchase!U:U,"LA") -> 0 | K36: =F36-G36 -> 0 | L36: =H36-K36 -> 704 | M36: =H36+I36-K36 -> 704 | N36: =_xlfn.XLOOKUP(A36,'Product List'!B:B,'Product List'!F:F) -> B | O36: =SUMIFS('Weekly Sales'!R:R,'Weekly Sales'!B:B,A36,'Weekly Sales'!U:U,"LA") -> 0 | P36: =IF(O36=0,999,ROUNDDOWN((L36)/O36,0)) -> 999 | Q36: =IF(O36=0,999,ROUNDDOWN((M36)/O36,0)) -> 999 | R36: =_xlfn.XLOOKUP(A36,'Product List'!B:B,'Product List'!P:P) -> 15 | S36: =IF(N36="A",6,IF(N36="B",5,2)) -> 5 | T36: =SUMIFS('Weekly Sales'!T:T,'Weekly Sales'!B:B,A36,'Weekly Sales'!U:U,"LA") -> 0 | U36: =_xlfn.XLOOKUP(A36,'Product List'!B:B,'Product List'!O:O) -> 500 | V36: =ROUNDUP(MAX(0,O36*(R36+S36+2)+T36-M36)/W36,0)*W36 -> 0 | W36: {=_xlfn.XLOOKUP(1,('Case Pack'!A:A=A36)*('Case Pack'!F:F<=TODAY()),'Case Pack'!D:D,"未找到箱规")} -> 32 | X36: =_xlfn.XLOOKUP(A36,'Product List'!B:B,'Product List'!M:M) -> PSP, PetcoUS | Y36: {=_xlfn.XLOOKUP(1,('Case Pack'!A:A=A36)*('Case Pack'!F:F<=TODAY()),'Case Pack'!G:G,"未找到箱规")} -> F | Z36: =V36/W36 -> 0 | AA36: =_xlfn.XLOOKUP(Y36,'Case Type'!A:A,'Case Type'!H:H)*Z36 -> 0
A37: RJ510-BL | B37: =_xlfn.XLOOKUP(A37,'Product List'!B:B,'Product List'!I:I) -> Crystal Outdoor Cage | C37: 0 | D37: =SUMIFS(Purchase!F:F,Purchase!C:C,A37,Purchase!I:I,">"&$C$1,Purchase!V:V,"<>暂缓发货",Purchase!U:U,"LA") -> 1250 | E37: =SUMIFS(Purchase!F:F,Purchase!C:C,A37,Purchase!J:J,">0",Purchase!I:I,">"&$C$1,Purchase!U:U,"LA") -> 1250 | F37: =SUMIFS(Sales!E:E,Sales!C:C,A37,Sales!K:K,">"&$C$1,Sales!I:I,"LA") -> 305 | G37: =SUMIFS(Sales!E:E,Sales!C:C,A37,Sales!K:K,">"&$C$1,Sales!L:L,">0",Sales!I:I,"LA") -> 305 | H37: =C37+E37-G37+SUMIFS(Transfer!W:W,Transfer!O:O,A37,Transfer!Q:Q,"LA",Transfer!U:U,">"&$C$1)-SUMIFS(Transfer!V:V,Transfer!O:O,A37,Transfer!P:P,"LA",Transfer!T:T,">"&$C$1) -> 945 | I37: =D37-E37+SUMIFS(Transfer!V:V,Transfer!O:O,A37,Transfer!Q:Q,"LA")-SUMIFS(Transfer!W:W,Transfer!O:O,A37,Transfer!Q:Q,"LA") -> 0 | J37: =SUMIFS(Purchase!F:F,Purchase!C:C,A37,Purchase!V:V,"暂缓发货",Purchase!U:U,"LA") -> 0 | K37: =F37-G37 -> 0 | L37: =H37-K37 -> 945 | M37: =H37+I37-K37 -> 945 | N37: =_xlfn.XLOOKUP(A37,'Product List'!B:B,'Product List'!F:F) -> C | O37: =SUMIFS('Weekly Sales'!R:R,'Weekly Sales'!B:B,A37,'Weekly Sales'!U:U,"LA") -> 0 | P37: =IF(O37=0,999,ROUNDDOWN((L37)/O37,0)) -> 999 | Q37: =IF(O37=0,999,ROUNDDOWN((M37)/O37,0)) -> 999 | R37: =_xlfn.XLOOKUP(A37,'Product List'!B:B,'Product List'!P:P) -> 10 | S37: =IF(N37="A",6,IF(N37="B",5,2)) -> 2 | T37: =SUMIFS('Weekly Sales'!T:T,'Weekly Sales'!B:B,A37,'Weekly Sales'!U:U,"LA") -> 0 | U37: =_xlfn.XLOOKUP(A37,'Product List'!B:B,'Product List'!O:O) -> 1000 | V37: =ROUNDUP(MAX(0,O37*(R37+S37+2)+T37-M37)/W37,0)*W37 -> 0 | W37: {=_xlfn.XLOOKUP(1,('Case Pack'!A:A=A37)*('Case Pack'!F:F<=TODAY()),'Case Pack'!D:D,"未找到箱规")} -> 5 | X37: =_xlfn.XLOOKUP(A37,'Product List'!B:B,'Product List'!M:M) -> PetcoMX,PSP，Canada | Y37: {=_xlfn.XLOOKUP(1,('Case Pack'!A:A=A37)*('Case Pack'!F:F<=TODAY()),'Case Pack'!G:G,"未找到箱规")} -> A | Z37: =V37/W37 -> 0 | AA37: =_xlfn.XLOOKUP(Y37,'Case Type'!A:A,'Case Type'!H:H)*Z37 -> 0
A38: SP-4 | B38: =_xlfn.XLOOKUP(A38,'Product List'!B:B,'Product List'!I:I) -> D. MMO-COTTAGE VIEW CAGE | C38: 0 | D38: =SUMIFS(Purchase!F:F,Purchase!C:C,A38,Purchase!I:I,">"&$C$1,Purchase!V:V,"<>暂缓发货",Purchase!U:U,"LA") -> 741 | E38: =SUMIFS(Purchase!F:F,Purchase!C:C,A38,Purchase!J:J,">0",Purchase!I:I,">"&$C$1,Purchase!U:U,"LA") -> 741 | F38: =SUMIFS(Sales!E:E,Sales!C:C,A38,Sales!K:K,">"&$C$1,Sales!I:I,"LA") -> 306 | G38: =SUMIFS(Sales!E:E,Sales!C:C,A38,Sales!K:K,">"&$C$1,Sales!L:L,">0",Sales!I:I,"LA") -> 137 | H38: =C38+E38-G38+SUMIFS(Transfer!W:W,Transfer!O:O,A38,Transfer!Q:Q,"LA",Transfer!U:U,">"&$C$1)-SUMIFS(Transfer!V:V,Transfer!O:O,A38,Transfer!P:P,"LA",Transfer!T:T,">"&$C$1) -> 604 | I38: =D38-E38+SUMIFS(Transfer!V:V,Transfer!O:O,A38,Transfer!Q:Q,"LA")-SUMIFS(Transfer!W:W,Transfer!O:O,A38,Transfer!Q:Q,"LA") -> 0 | J38: =SUMIFS(Purchase!F:F,Purchase!C:C,A38,Purchase!V:V,"暂缓发货",Purchase!U:U,"LA") -> 0 | K38: =F38-G38 -> 169 | L38: =H38-K38 -> 435 | M38: =H38+I38-K38 -> 435 | N38: =_xlfn.XLOOKUP(A38,'Product List'!B:B,'Product List'!F:F) -> A | O38: =SUMIFS('Weekly Sales'!R:R,'Weekly Sales'!B:B,A38,'Weekly Sales'!U:U,"LA") -> 0 | P38: =IF(O38=0,999,ROUNDDOWN((L38)/O38,0)) -> 999 | Q38: =IF(O38=0,999,ROUNDDOWN((M38)/O38,0)) -> 999 | R38: =_xlfn.XLOOKUP(A38,'Product List'!B:B,'Product List'!P:P) -> 10 | S38: =IF(N38="A",6,IF(N38="B",5,2)) -> 6 | T38: =SUMIFS('Weekly Sales'!T:T,'Weekly Sales'!B:B,A38,'Weekly Sales'!U:U,"LA") -> 0 | U38: =_xlfn.XLOOKUP(A38,'Product List'!B:B,'Product List'!O:O) -> 1000 | V38: =ROUNDUP(MAX(0,O38*(R38+S38+2)+T38-M38)/W38,0)*W38 -> 0 | W38: {=_xlfn.XLOOKUP(1,('Case Pack'!A:A=A38)*('Case Pack'!F:F<=TODAY()),'Case Pack'!D:D,"未找到箱规")} -> 1 | X38: =_xlfn.XLOOKUP(A38,'Product List'!B:B,'Product List'!M:M) -> PSP, PetcoUS, PetcoMX | Y38: {=_xlfn.XLOOKUP(1,('Case Pack'!A:A=A38)*('Case Pack'!F:F<=TODAY()),'Case Pack'!G:G,"未找到箱规")} -> S3 | Z38: =V38/W38 -> 0 | AA38: =_xlfn.XLOOKUP(Y38,'Case Type'!A:A,'Case Type'!H:H)*Z38 -> 0
A39: SP-7 | B39: =_xlfn.XLOOKUP(A39,'Product List'!B:B,'Product List'!I:I) -> MINI/MOE ROCKING BIRDHOUSE HIDE 1EA | C39: 0 | D39: =SUMIFS(Purchase!F:F,Purchase!C:C,A39,Purchase!I:I,">"&$C$1,Purchase!V:V,"<>暂缓发货",Purchase!U:U,"LA") -> 0 | E39: =SUMIFS(Purchase!F:F,Purchase!C:C,A39,Purchase!J:J,">0",Purchase!I:I,">"&$C$1,Purchase!U:U,"LA") -> 0 | F39: =SUMIFS(Sales!E:E,Sales!C:C,A39,Sales!K:K,">"&$C$1,Sales!I:I,"LA") -> 0 | G39: =SUMIFS(Sales!E:E,Sales!C:C,A39,Sales!K:K,">"&$C$1,Sales!L:L,">0",Sales!I:I,"LA") -> 0 | H39: =C39+E39-G39+SUMIFS(Transfer!W:W,Transfer!O:O,A39,Transfer!Q:Q,"LA",Transfer!U:U,">"&$C$1)-SUMIFS(Transfer!V:V,Transfer!O:O,A39,Transfer!P:P,"LA",Transfer!T:T,">"&$C$1) -> 0 | I39: =D39-E39+SUMIFS(Transfer!V:V,Transfer!O:O,A39,Transfer!Q:Q,"LA")-SUMIFS(Transfer!W:W,Transfer!O:O,A39,Transfer!Q:Q,"LA") -> 0 | J39: =SUMIFS(Purchase!F:F,Purchase!C:C,A39,Purchase!V:V,"暂缓发货",Purchase!U:U,"LA") -> 0 | K39: =F39-G39 -> 0 | L39: =H39-K39 -> 0 | M39: =H39+I39-K39 -> 0 | N39: =_xlfn.XLOOKUP(A39,'Product List'!B:B,'Product List'!F:F) -> C | O39: =SUMIFS('Weekly Sales'!R:R,'Weekly Sales'!B:B,A39,'Weekly Sales'!U:U,"LA") -> 0 | P39: =IF(O39=0,999,ROUNDDOWN((L39)/O39,0)) -> 999 | Q39: =IF(O39=0,999,ROUNDDOWN((M39)/O39,0)) -> 999 | R39: =_xlfn.XLOOKUP(A39,'Product List'!B:B,'Product List'!P:P) -> 10 | S39: =IF(N39="A",6,IF(N39="B",5,2)) -> 2 | T39: =SUMIFS('Weekly Sales'!T:T,'Weekly Sales'!B:B,A39,'Weekly Sales'!U:U,"LA") -> 0 | U39: =_xlfn.XLOOKUP(A39,'Product List'!B:B,'Product List'!O:O) -> 500 | V39: =ROUNDUP(MAX(0,O39*(R39+S39+2)+T39-M39)/W39,0)*W39 -> 0 | W39: {=_xlfn.XLOOKUP(1,('Case Pack'!A:A=A39)*('Case Pack'!F:F<=TODAY()),'Case Pack'!D:D,"未找到箱规")} -> 18 | X39: =_xlfn.XLOOKUP(A39,'Product List'!B:B,'Product List'!M:M) -> PSP | Y39: {=_xlfn.XLOOKUP(1,('Case Pack'!A:A=A39)*('Case Pack'!F:F<=TODAY()),'Case Pack'!G:G,"未找到箱规")} -> C | Z39: =V39/W39 -> 0 | AA39: =_xlfn.XLOOKUP(Y39,'Case Type'!A:A,'Case Type'!H:H)*Z39 -> 0
A40: SZP542-GN | B40: =_xlfn.XLOOKUP(A40,'Product List'!B:B,'Product List'!I:I) -> Bubble water bottle (color:green) | C40: 144 | D40: =SUMIFS(Purchase!F:F,Purchase!C:C,A40,Purchase!I:I,">"&$C$1,Purchase!V:V,"<>暂缓发货",Purchase!U:U,"LA") -> 288 | E40: =SUMIFS(Purchase!F:F,Purchase!C:C,A40,Purchase!J:J,">0",Purchase!I:I,">"&$C$1,Purchase!U:U,"LA") -> 288 | F40: =SUMIFS(Sales!E:E,Sales!C:C,A40,Sales!K:K,">"&$C$1,Sales!I:I,"LA") -> 198 | G40: =SUMIFS(Sales!E:E,Sales!C:C,A40,Sales!K:K,">"&$C$1,Sales!L:L,">0",Sales!I:I,"LA") -> 198 | H40: =C40+E40-G40+SUMIFS(Transfer!W:W,Transfer!O:O,A40,Transfer!Q:Q,"LA",Transfer!U:U,">"&$C$1)-SUMIFS(Transfer!V:V,Transfer!O:O,A40,Transfer!P:P,"LA",Transfer!T:T,">"&$C$1) -> 234 | I40: =D40-E40+SUMIFS(Transfer!V:V,Transfer!O:O,A40,Transfer!Q:Q,"LA")-SUMIFS(Transfer!W:W,Transfer!O:O,A40,Transfer!Q:Q,"LA") -> 0 | J40: =SUMIFS(Purchase!F:F,Purchase!C:C,A40,Purchase!V:V,"暂缓发货",Purchase!U:U,"LA") -> 0 | K40: =F40-G40 -> 0 | L40: =H40-K40 -> 234 | M40: =H40+I40-K40 -> 234 | N40: =_xlfn.XLOOKUP(A40,'Product List'!B:B,'Product List'!F:F) -> C | O40: =SUMIFS('Weekly Sales'!R:R,'Weekly Sales'!B:B,A40,'Weekly Sales'!U:U,"LA") -> 0 | P40: =IF(O40=0,999,ROUNDDOWN((L40)/O40,0)) -> 999 | Q40: =IF(O40=0,999,ROUNDDOWN((M40)/O40,0)) -> 999 | R40: =_xlfn.XLOOKUP(A40,'Product List'!B:B,'Product List'!P:P) -> 10 | S40: =IF(N40="A",6,IF(N40="B",5,2)) -> 2 | T40: =SUMIFS('Weekly Sales'!T:T,'Weekly Sales'!B:B,A40,'Weekly Sales'!U:U,"LA") -> 0 | U40: =_xlfn.XLOOKUP(A40,'Product List'!B:B,'Product List'!O:O) -> 1000 | V40: =ROUNDUP(MAX(0,O40*(R40+S40+2)+T40-M40)/W40,0)*W40 -> 0 | W40: {=_xlfn.XLOOKUP(1,('Case Pack'!A:A=A40)*('Case Pack'!F:F<=TODAY()),'Case Pack'!D:D,"未找到箱规")} -> 18 | X40: =_xlfn.XLOOKUP(A40,'Product List'!B:B,'Product List'!M:M) -> Pet Supermarket,PetcoMX | Y40: {=_xlfn.XLOOKUP(1,('Case Pack'!A:A=A40)*('Case Pack'!F:F<=TODAY()),'Case Pack'!G:G,"未找到箱规")} -> B | Z40: =V40/W40 -> 0 | AA40: =_xlfn.XLOOKUP(Y40,'Case Type'!A:A,'Case Type'!H:H)*Z40 -> 0
A41: SZP542-WH | B41: =_xlfn.XLOOKUP(A41,'Product List'!B:B,'Product List'!I:I) -> MMO-BUBBLE WATER BOTTLE | C41: 360 | D41: =SUMIFS(Purchase!F:F,Purchase!C:C,A41,Purchase!I:I,">"&$C$1,Purchase!V:V,"<>暂缓发货",Purchase!U:U,"LA") -> 18648 | E41: =SUMIFS(Purchase!F:F,Purchase!C:C,A41,Purchase!J:J,">0",Purchase!I:I,">"&$C$1,Purchase!U:U,"LA") -> 18648 | F41: =SUMIFS(Sales!E:E,Sales!C:C,A41,Sales!K:K,">"&$C$1,Sales!I:I,"LA") -> 13590 | G41: =SUMIFS(Sales!E:E,Sales!C:C,A41,Sales!K:K,">"&$C$1,Sales!L:L,">0",Sales!I:I,"LA") -> 10566 | H41: =C41+E41-G41+SUMIFS(Transfer!W:W,Transfer!O:O,A41,Transfer!Q:Q,"LA",Transfer!U:U,">"&$C$1)-SUMIFS(Transfer!V:V,Transfer!O:O,A41,Transfer!P:P,"LA",Transfer!T:T,">"&$C$1) -> 8442 | I41: =D41-E41+SUMIFS(Transfer!V:V,Transfer!O:O,A41,Transfer!Q:Q,"LA")-SUMIFS(Transfer!W:W,Transfer!O:O,A41,Transfer!Q:Q,"LA") -> 0 | J41: =SUMIFS(Purchase!F:F,Purchase!C:C,A41,Purchase!V:V,"暂缓发货",Purchase!U:U,"LA") -> 5124 | K41: =F41-G41 -> 3024 | L41: =H41-K41 -> 5418 | M41: =H41+I41-K41 -> 5418 | N41: =_xlfn.XLOOKUP(A41,'Product List'!B:B,'Product List'!F:F) -> A | O41: =SUMIFS('Weekly Sales'!R:R,'Weekly Sales'!B:B,A41,'Weekly Sales'!U:U,"LA") -> 317.66667 | P41: =IF(O41=0,999,ROUNDDOWN((L41)/O41,0)) -> 17 | Q41: =IF(O41=0,999,ROUNDDOWN((M41)/O41,0)) -> 17 | R41: =_xlfn.XLOOKUP(A41,'Product List'!B:B,'Product List'!P:P) -> 10 | S41: =IF(N41="A",6,IF(N41="B",5,2)) -> 6 | T41: =SUMIFS('Weekly Sales'!T:T,'Weekly Sales'!B:B,A41,'Weekly Sales'!U:U,"LA") -> 2064.8333 | U41: =_xlfn.XLOOKUP(A41,'Product List'!B:B,'Product List'!O:O) -> 1000 | V41: =ROUNDUP(MAX(0,O41*(R41+S41+2)+T41-M41)/W41,0)*W41 -> 2394 | W41: {=_xlfn.XLOOKUP(1,('Case Pack'!A:A=A41)*('Case Pack'!F:F<=TODAY()),'Case Pack'!D:D,"未找到箱规")} -> 42 | X41: =_xlfn.XLOOKUP(A41,'Product List'!B:B,'Product List'!M:M) -> PetcoUS,PSP | Y41: {=_xlfn.XLOOKUP(1,('Case Pack'!A:A=A41)*('Case Pack'!F:F<=TODAY()),'Case Pack'!G:G,"未找到箱规")} -> C | Z41: =V41/W41 -> 57 | AA41: =_xlfn.XLOOKUP(Y41,'Case Type'!A:A,'Case Type'!H:H)*Z41 -> 8.9670014
A42: T-1-BL | B42: =_xlfn.XLOOKUP(A42,'Product List'!B:B,'Product List'!I:I) -> MMO-PAPER TWIST BLU/WHT | C42: 936 | D42: =SUMIFS(Purchase!F:F,Purchase!C:C,A42,Purchase!I:I,">"&$C$1,Purchase!V:V,"<>暂缓发货",Purchase!U:U,"LA") -> 4740 | E42: =SUMIFS(Purchase!F:F,Purchase!C:C,A42,Purchase!J:J,">0",Purchase!I:I,">"&$C$1,Purchase!U:U,"LA") -> 4740 | F42: =SUMIFS(Sales!E:E,Sales!C:C,A42,Sales!K:K,">"&$C$1,Sales!I:I,"LA") -> 2136 | G42: =SUMIFS(Sales!E:E,Sales!C:C,A42,Sales!K:K,">"&$C$1,Sales!L:L,">0",Sales!I:I,"LA") -> 2136 | H42: =C42+E42-G42+SUMIFS(Transfer!W:W,Transfer!O:O,A42,Transfer!Q:Q,"LA",Transfer!U:U,">"&$C$1)-SUMIFS(Transfer!V:V,Transfer!O:O,A42,Transfer!P:P,"LA",Transfer!T:T,">"&$C$1) -> 3540 | I42: =D42-E42+SUMIFS(Transfer!V:V,Transfer!O:O,A42,Transfer!Q:Q,"LA")-SUMIFS(Transfer!W:W,Transfer!O:O,A42,Transfer!Q:Q,"LA") -> 0 | J42: =SUMIFS(Purchase!F:F,Purchase!C:C,A42,Purchase!V:V,"暂缓发货",Purchase!U:U,"LA") -> 0 | K42: =F42-G42 -> 0 | L42: =H42-K42 -> 3540 | M42: =H42+I42-K42 -> 3540 | N42: =_xlfn.XLOOKUP(A42,'Product List'!B:B,'Product List'!F:F) -> B | O42: =SUMIFS('Weekly Sales'!R:R,'Weekly Sales'!B:B,A42,'Weekly Sales'!U:U,"LA") -> 48.5 | P42: =IF(O42=0,999,ROUNDDOWN((L42)/O42,0)) -> 72 | Q42: =IF(O42=0,999,ROUNDDOWN((M42)/O42,0)) -> 72 | R42: =_xlfn.XLOOKUP(A42,'Product List'!B:B,'Product List'!P:P) -> 10 | S42: =IF(N42="A",6,IF(N42="B",5,2)) -> 5 | T42: =SUMIFS('Weekly Sales'!T:T,'Weekly Sales'!B:B,A42,'Weekly Sales'!U:U,"LA") -> 157.625 | U42: =_xlfn.XLOOKUP(A42,'Product List'!B:B,'Product List'!O:O) -> 500 | V42: =ROUNDUP(MAX(0,O42*(R42+S42+2)+T42-M42)/W42,0)*W42 -> 0 | W42: {=_xlfn.XLOOKUP(1,('Case Pack'!A:A=A42)*('Case Pack'!F:F<=TODAY()),'Case Pack'!D:D,"未找到箱规")} -> 30 | X42: =_xlfn.XLOOKUP(A42,'Product List'!B:B,'Product List'!M:M) -> PetcoUS，PSP | Y42: {=_xlfn.XLOOKUP(1,('Case Pack'!A:A=A42)*('Case Pack'!F:F<=TODAY()),'Case Pack'!G:G,"未找到箱规")} -> A | Z42: =V42/W42 -> 0 | AA42: =_xlfn.XLOOKUP(Y42,'Case Type'!A:A,'Case Type'!H:H)*Z42 -> 0
A43: T-1-BL-WH | B43: =_xlfn.XLOOKUP(A43,'Product List'!B:B,'Product List'!I:I) -> MINI/MOE SMALL ANIMAL BEDDING PAPER TWISTS | C43: 0 | D43: =SUMIFS(Purchase!F:F,Purchase!C:C,A43,Purchase!I:I,">"&$C$1,Purchase!V:V,"<>暂缓发货",Purchase!U:U,"LA") -> 3420 | E43: =SUMIFS(Purchase!F:F,Purchase!C:C,A43,Purchase!J:J,">0",Purchase!I:I,">"&$C$1,Purchase!U:U,"LA") -> 3390 | F43: =SUMIFS(Sales!E:E,Sales!C:C,A43,Sales!K:K,">"&$C$1,Sales!I:I,"LA") -> 2010 | G43: =SUMIFS(Sales!E:E,Sales!C:C,A43,Sales!K:K,">"&$C$1,Sales!L:L,">0",Sales!I:I,"LA") -> 2010 | H43: =C43+E43-G43+SUMIFS(Transfer!W:W,Transfer!O:O,A43,Transfer!Q:Q,"LA",Transfer!U:U,">"&$C$1)-SUMIFS(Transfer!V:V,Transfer!O:O,A43,Transfer!P:P,"LA",Transfer!T:T,">"&$C$1) -> 1380 | I43: =D43-E43+SUMIFS(Transfer!V:V,Transfer!O:O,A43,Transfer!Q:Q,"LA")-SUMIFS(Transfer!W:W,Transfer!O:O,A43,Transfer!Q:Q,"LA") -> 30 | J43: =SUMIFS(Purchase!F:F,Purchase!C:C,A43,Purchase!V:V,"暂缓发货",Purchase!U:U,"LA") -> 0 | K43: =F43-G43 -> 0 | L43: =H43-K43 -> 1380 | M43: =H43+I43-K43 -> 1410 | N43: =_xlfn.XLOOKUP(A43,'Product List'!B:B,'Product List'!F:F) -> C | O43: =SUMIFS('Weekly Sales'!R:R,'Weekly Sales'!B:B,A43,'Weekly Sales'!U:U,"LA") -> 0 | P43: =IF(O43=0,999,ROUNDDOWN((L43)/O43,0)) -> 999 | Q43: =IF(O43=0,999,ROUNDDOWN((M43)/O43,0)) -> 999 | R43: =_xlfn.XLOOKUP(A43,'Product List'!B:B,'Product List'!P:P) -> 10 | S43: =IF(N43="A",6,IF(N43="B",5,2)) -> 2 | T43: =SUMIFS('Weekly Sales'!T:T,'Weekly Sales'!B:B,A43,'Weekly Sales'!U:U,"LA") -> 0 | U43: =_xlfn.XLOOKUP(A43,'Product List'!B:B,'Product List'!O:O) -> 1000 | V43: =ROUNDUP(MAX(0,O43*(R43+S43+2)+T43-M43)/W43,0)*W43 -> 0 | W43: {=_xlfn.XLOOKUP(1,('Case Pack'!A:A=A43)*('Case Pack'!F:F<=TODAY()),'Case Pack'!D:D,"未找到箱规")} -> 30 | X43: =_xlfn.XLOOKUP(A43,'Product List'!B:B,'Product List'!M:M) -> PSP | Y43: {=_xlfn.XLOOKUP(1,('Case Pack'!A:A=A43)*('Case Pack'!F:F<=TODAY()),'Case Pack'!G:G,"未找到箱规")} -> A | Z43: =V43/W43 -> 0 | AA43: =_xlfn.XLOOKUP(Y43,'Case Type'!A:A,'Case Type'!H:H)*Z43 -> 0
A44: T-1-BR-WH | B44: =_xlfn.XLOOKUP(A44,'Product List'!B:B,'Product List'!I:I) -> Paper twist brown / white bedding | C44: 0 | D44: =SUMIFS(Purchase!F:F,Purchase!C:C,A44,Purchase!I:I,">"&$C$1,Purchase!V:V,"<>暂缓发货",Purchase!U:U,"LA") -> 1860 | E44: =SUMIFS(Purchase!F:F,Purchase!C:C,A44,Purchase!J:J,">0",Purchase!I:I,">"&$C$1,Purchase!U:U,"LA") -> 1860 | F44: =SUMIFS(Sales!E:E,Sales!C:C,A44,Sales!K:K,">"&$C$1,Sales!I:I,"LA") -> 930 | G44: =SUMIFS(Sales!E:E,Sales!C:C,A44,Sales!K:K,">"&$C$1,Sales!L:L,">0",Sales!I:I,"LA") -> 930 | H44: =C44+E44-G44+SUMIFS(Transfer!W:W,Transfer!O:O,A44,Transfer!Q:Q,"LA",Transfer!U:U,">"&$C$1)-SUMIFS(Transfer!V:V,Transfer!O:O,A44,Transfer!P:P,"LA",Transfer!T:T,">"&$C$1) -> 930 | I44: =D44-E44+SUMIFS(Transfer!V:V,Transfer!O:O,A44,Transfer!Q:Q,"LA")-SUMIFS(Transfer!W:W,Transfer!O:O,A44,Transfer!Q:Q,"LA") -> 0 | J44: =SUMIFS(Purchase!F:F,Purchase!C:C,A44,Purchase!V:V,"暂缓发货",Purchase!U:U,"LA") -> 0 | K44: =F44-G44 -> 0 | L44: =H44-K44 -> 930 | M44: =H44+I44-K44 -> 930 | N44: =_xlfn.XLOOKUP(A44,'Product List'!B:B,'Product List'!F:F) -> C | O44: =SUMIFS('Weekly Sales'!R:R,'Weekly Sales'!B:B,A44,'Weekly Sales'!U:U,"LA") -> 0 | P44: =IF(O44=0,999,ROUNDDOWN((L44)/O44,0)) -> 999 | Q44: =IF(O44=0,999,ROUNDDOWN((M44)/O44,0)) -> 999 | R44: =_xlfn.XLOOKUP(A44,'Product List'!B:B,'Product List'!P:P) -> 10 | S44: =IF(N44="A",6,IF(N44="B",5,2)) -> 2 | T44: =SUMIFS('Weekly Sales'!T:T,'Weekly Sales'!B:B,A44,'Weekly Sales'!U:U,"LA") -> 0 | U44: =_xlfn.XLOOKUP(A44,'Product List'!B:B,'Product List'!O:O) -> 1000 | V44: =ROUNDUP(MAX(0,O44*(R44+S44+2)+T44-M44)/W44,0)*W44 -> 0 | W44: {=_xlfn.XLOOKUP(1,('Case Pack'!A:A=A44)*('Case Pack'!F:F<=TODAY()),'Case Pack'!D:D,"未找到箱规")} -> 30 | X44: =_xlfn.XLOOKUP(A44,'Product List'!B:B,'Product List'!M:M) -> Pet Supermarket，PSP | Y44: {=_xlfn.XLOOKUP(1,('Case Pack'!A:A=A44)*('Case Pack'!F:F<=TODAY()),'Case Pack'!G:G,"未找到箱规")} -> A | Z44: =V44/W44 -> 0 | AA44: =_xlfn.XLOOKUP(Y44,'Case Type'!A:A,'Case Type'!H:H)*Z44 -> 0
A45: T-1-PK | B45: =_xlfn.XLOOKUP(A45,'Product List'!B:B,'Product List'!I:I) -> MINI/MOE SMALL ANIMAL BEDDING PAPER TWISTS BUBBLEGUM 1EA | C45: 0 | D45: =SUMIFS(Purchase!F:F,Purchase!C:C,A45,Purchase!I:I,">"&$C$1,Purchase!V:V,"<>暂缓发货",Purchase!U:U,"LA") -> 1260 | E45: =SUMIFS(Purchase!F:F,Purchase!C:C,A45,Purchase!J:J,">0",Purchase!I:I,">"&$C$1,Purchase!U:U,"LA") -> 1260 | F45: =SUMIFS(Sales!E:E,Sales!C:C,A45,Sales!K:K,">"&$C$1,Sales!I:I,"LA") -> 660 | G45: =SUMIFS(Sales!E:E,Sales!C:C,A45,Sales!K:K,">"&$C$1,Sales!L:L,">0",Sales!I:I,"LA") -> 660 | H45: =C45+E45-G45+SUMIFS(Transfer!W:W,Transfer!O:O,A45,Transfer!Q:Q,"LA",Transfer!U:U,">"&$C$1)-SUMIFS(Transfer!V:V,Transfer!O:O,A45,Transfer!P:P,"LA",Transfer!T:T,">"&$C$1) -> 600 | I45: =D45-E45+SUMIFS(Transfer!V:V,Transfer!O:O,A45,Transfer!Q:Q,"LA")-SUMIFS(Transfer!W:W,Transfer!O:O,A45,Transfer!Q:Q,"LA") -> 0 | J45: =SUMIFS(Purchase!F:F,Purchase!C:C,A45,Purchase!V:V,"暂缓发货",Purchase!U:U,"LA") -> 0 | K45: =F45-G45 -> 0 | L45: =H45-K45 -> 600 | M45: =H45+I45-K45 -> 600 | N45: =_xlfn.XLOOKUP(A45,'Product List'!B:B,'Product List'!F:F) -> C | O45: =SUMIFS('Weekly Sales'!R:R,'Weekly Sales'!B:B,A45,'Weekly Sales'!U:U,"LA") -> 0 | P45: =IF(O45=0,999,ROUNDDOWN((L45)/O45,0)) -> 999 | Q45: =IF(O45=0,999,ROUNDDOWN((M45)/O45,0)) -> 999 | R45: =_xlfn.XLOOKUP(A45,'Product List'!B:B,'Product List'!P:P) -> 10 | S45: =IF(N45="A",6,IF(N45="B",5,2)) -> 2 | T45: =SUMIFS('Weekly Sales'!T:T,'Weekly Sales'!B:B,A45,'Weekly Sales'!U:U,"LA") -> 0 | U45: =_xlfn.XLOOKUP(A45,'Product List'!B:B,'Product List'!O:O) -> 1000 | V45: =ROUNDUP(MAX(0,O45*(R45+S45+2)+T45-M45)/W45,0)*W45 -> 0 | W45: {=_xlfn.XLOOKUP(1,('Case Pack'!A:A=A45)*('Case Pack'!F:F<=TODAY()),'Case Pack'!D:D,"未找到箱规")} -> 30 | X45: =_xlfn.XLOOKUP(A45,'Product List'!B:B,'Product List'!M:M) -> PSP | Y45: {=_xlfn.XLOOKUP(1,('Case Pack'!A:A=A45)*('Case Pack'!F:F<=TODAY()),'Case Pack'!G:G,"未找到箱规")} -> A | Z45: =V45/W45 -> 0 | AA45: =_xlfn.XLOOKUP(Y45,'Case Type'!A:A,'Case Type'!H:H)*Z45 -> 0
A46: T-41 | B46: =_xlfn.XLOOKUP(A46,'Product List'!B:B,'Product List'!I:I) -> Forest Series Hamster Chew Toy & Treat | C46: 0 | D46: =SUMIFS(Purchase!F:F,Purchase!C:C,A46,Purchase!I:I,">"&$C$1,Purchase!V:V,"<>暂缓发货",Purchase!U:U,"LA") -> 1560 | E46: =SUMIFS(Purchase!F:F,Purchase!C:C,A46,Purchase!J:J,">0",Purchase!I:I,">"&$C$1,Purchase!U:U,"LA") -> 1560 | F46: =SUMIFS(Sales!E:E,Sales!C:C,A46,Sales!K:K,">"&$C$1,Sales!I:I,"LA") -> 1020 | G46: =SUMIFS(Sales!E:E,Sales!C:C,A46,Sales!K:K,">"&$C$1,Sales!L:L,">0",Sales!I:I,"LA") -> 1020 | H46: =C46+E46-G46+SUMIFS(Transfer!W:W,Transfer!O:O,A46,Transfer!Q:Q,"LA",Transfer!U:U,">"&$C$1)-SUMIFS(Transfer!V:V,Transfer!O:O,A46,Transfer!P:P,"LA",Transfer!T:T,">"&$C$1) -> 540 | I46: =D46-E46+SUMIFS(Transfer!V:V,Transfer!O:O,A46,Transfer!Q:Q,"LA")-SUMIFS(Transfer!W:W,Transfer!O:O,A46,Transfer!Q:Q,"LA") -> 0 | J46: =SUMIFS(Purchase!F:F,Purchase!C:C,A46,Purchase!V:V,"暂缓发货",Purchase!U:U,"LA") -> 0 | K46: =F46-G46 -> 0 | L46: =H46-K46 -> 540 | M46: =H46+I46-K46 -> 540 | N46: =_xlfn.XLOOKUP(A46,'Product List'!B:B,'Product List'!F:F) -> C | O46: =SUMIFS('Weekly Sales'!R:R,'Weekly Sales'!B:B,A46,'Weekly Sales'!U:U,"LA") -> 0 | P46: =IF(O46=0,999,ROUNDDOWN((L46)/O46,0)) -> 999 | Q46: =IF(O46=0,999,ROUNDDOWN((M46)/O46,0)) -> 999 | R46: =_xlfn.XLOOKUP(A46,'Product List'!B:B,'Product List'!P:P) -> 10 | S46: =IF(N46="A",6,IF(N46="B",5,2)) -> 2 | T46: =SUMIFS('Weekly Sales'!T:T,'Weekly Sales'!B:B,A46,'Weekly Sales'!U:U,"LA") -> 0 | U46: =_xlfn.XLOOKUP(A46,'Product List'!B:B,'Product List'!O:O) -> 1000 | V46: =ROUNDUP(MAX(0,O46*(R46+S46+2)+T46-M46)/W46,0)*W46 -> 0 | W46: {=_xlfn.XLOOKUP(1,('Case Pack'!A:A=A46)*('Case Pack'!F:F<=TODAY()),'Case Pack'!D:D,"未找到箱规")} -> 60 | X46: =_xlfn.XLOOKUP(A46,'Product List'!B:B,'Product List'!M:M) -> Pet Supermarket,PSP | Y46: {=_xlfn.XLOOKUP(1,('Case Pack'!A:A=A46)*('Case Pack'!F:F<=TODAY()),'Case Pack'!G:G,"未找到箱规")} -> B | Z46: =V46/W46 -> 0 | AA46: =_xlfn.XLOOKUP(Y46,'Case Type'!A:A,'Case Type'!H:H)*Z46 -> 0
A47: WJ-13 | B47: =_xlfn.XLOOKUP(A47,'Product List'!B:B,'Product List'!I:I) -> MINI/MOE CAMPING TENT HIDE | C47: 132 | D47: =SUMIFS(Purchase!F:F,Purchase!C:C,A47,Purchase!I:I,">"&$C$1,Purchase!V:V,"<>暂缓发货",Purchase!U:U,"LA") -> 16584 | E47: =SUMIFS(Purchase!F:F,Purchase!C:C,A47,Purchase!J:J,">0",Purchase!I:I,">"&$C$1,Purchase!U:U,"LA") -> 10068 | F47: =SUMIFS(Sales!E:E,Sales!C:C,A47,Sales!K:K,">"&$C$1,Sales!I:I,"LA") -> 9348 | G47: =SUMIFS(Sales!E:E,Sales!C:C,A47,Sales!K:K,">"&$C$1,Sales!L:L,">0",Sales!I:I,"LA") -> 9276 | H47: =C47+E47-G47+SUMIFS(Transfer!W:W,Transfer!O:O,A47,Transfer!Q:Q,"LA",Transfer!U:U,">"&$C$1)-SUMIFS(Transfer!V:V,Transfer!O:O,A47,Transfer!P:P,"LA",Transfer!T:T,">"&$C$1) -> 924 | I47: =D47-E47+SUMIFS(Transfer!V:V,Transfer!O:O,A47,Transfer!Q:Q,"LA")-SUMIFS(Transfer!W:W,Transfer!O:O,A47,Transfer!Q:Q,"LA") -> 6516 | J47: =SUMIFS(Purchase!F:F,Purchase!C:C,A47,Purchase!V:V,"暂缓发货",Purchase!U:U,"LA") -> 0 | K47: =F47-G47 -> 72 | L47: =H47-K47 -> 852 | M47: =H47+I47-K47 -> 7368 | N47: =_xlfn.XLOOKUP(A47,'Product List'!B:B,'Product List'!F:F) -> A | O47: =SUMIFS('Weekly Sales'!R:R,'Weekly Sales'!B:B,A47,'Weekly Sales'!U:U,"LA") -> 189 | P47: =IF(O47=0,999,ROUNDDOWN((L47)/O47,0)) -> 4 | Q47: =IF(O47=0,999,ROUNDDOWN((M47)/O47,0)) -> 38 | R47: =_xlfn.XLOOKUP(A47,'Product List'!B:B,'Product List'!P:P) -> 15 | S47: =IF(N47="A",6,IF(N47="B",5,2)) -> 6 | T47: =SUMIFS('Weekly Sales'!T:T,'Weekly Sales'!B:B,A47,'Weekly Sales'!U:U,"LA") -> 1228.5 | U47: =_xlfn.XLOOKUP(A47,'Product List'!B:B,'Product List'!O:O) -> 500 | V47: =ROUNDUP(MAX(0,O47*(R47+S47+2)+T47-M47)/W47,0)*W47 -> 0 | W47: {=_xlfn.XLOOKUP(1,('Case Pack'!A:A=A47)*('Case Pack'!F:F<=TODAY()),'Case Pack'!D:D,"未找到箱规")} -> 18 | X47: =_xlfn.XLOOKUP(A47,'Product List'!B:B,'Product List'!M:M) -> PSP, Petsmart, Pet Supermarket,Canada | Y47: {=_xlfn.XLOOKUP(1,('Case Pack'!A:A=A47)*('Case Pack'!F:F<=TODAY()),'Case Pack'!G:G,"未找到箱规")} -> B | Z47: =V47/W47 -> 0 | AA47: =_xlfn.XLOOKUP(Y47,'Case Type'!A:A,'Case Type'!H:H)*Z47 -> 0
A48: WJ-14-B | B48: =_xlfn.XLOOKUP(A48,'Product List'!B:B,'Product List'!I:I) -> Little Devil Travel Cage | C48: 0 | D48: =SUMIFS(Purchase!F:F,Purchase!C:C,A48,Purchase!I:I,">"&$C$1,Purchase!V:V,"<>暂缓发货",Purchase!U:U,"LA") -> 1260 | E48: =SUMIFS(Purchase!F:F,Purchase!C:C,A48,Purchase!J:J,">0",Purchase!I:I,">"&$C$1,Purchase!U:U,"LA") -> 1260 | F48: =SUMIFS(Sales!E:E,Sales!C:C,A48,Sales!K:K,">"&$C$1,Sales!I:I,"LA") -> 612 | G48: =SUMIFS(Sales!E:E,Sales!C:C,A48,Sales!K:K,">"&$C$1,Sales!L:L,">0",Sales!I:I,"LA") -> 612 | H48: =C48+E48-G48+SUMIFS(Transfer!W:W,Transfer!O:O,A48,Transfer!Q:Q,"LA",Transfer!U:U,">"&$C$1)-SUMIFS(Transfer!V:V,Transfer!O:O,A48,Transfer!P:P,"LA",Transfer!T:T,">"&$C$1) -> 648 | I48: =D48-E48+SUMIFS(Transfer!V:V,Transfer!O:O,A48,Transfer!Q:Q,"LA")-SUMIFS(Transfer!W:W,Transfer!O:O,A48,Transfer!Q:Q,"LA") -> 0 | J48: =SUMIFS(Purchase!F:F,Purchase!C:C,A48,Purchase!V:V,"暂缓发货",Purchase!U:U,"LA") -> 0 | K48: =F48-G48 -> 0 | L48: =H48-K48 -> 648 | M48: =H48+I48-K48 -> 648 | N48: =_xlfn.XLOOKUP(A48,'Product List'!B:B,'Product List'!F:F) -> C | O48: =SUMIFS('Weekly Sales'!R:R,'Weekly Sales'!B:B,A48,'Weekly Sales'!U:U,"LA") -> 0 | P48: =IF(O48=0,999,ROUNDDOWN((L48)/O48,0)) -> 999 | Q48: =IF(O48=0,999,ROUNDDOWN((M48)/O48,0)) -> 999 | R48: =_xlfn.XLOOKUP(A48,'Product List'!B:B,'Product List'!P:P) -> 10 | S48: =IF(N48="A",6,IF(N48="B",5,2)) -> 2 | T48: =SUMIFS('Weekly Sales'!T:T,'Weekly Sales'!B:B,A48,'Weekly Sales'!U:U,"LA") -> 0 | U48: =_xlfn.XLOOKUP(A48,'Product List'!B:B,'Product List'!O:O) -> 1000 | V48: =ROUNDUP(MAX(0,O48*(R48+S48+2)+T48-M48)/W48,0)*W48 -> 0 | W48: {=_xlfn.XLOOKUP(1,('Case Pack'!A:A=A48)*('Case Pack'!F:F<=TODAY()),'Case Pack'!D:D,"未找到箱规")} -> 18 | X48: =_xlfn.XLOOKUP(A48,'Product List'!B:B,'Product List'!M:M) -> PetcoMX,PSP，Canada | Y48: {=_xlfn.XLOOKUP(1,('Case Pack'!A:A=A48)*('Case Pack'!F:F<=TODAY()),'Case Pack'!G:G,"未找到箱规")} -> C | Z48: =V48/W48 -> 0 | AA48: =_xlfn.XLOOKUP(Y48,'Case Type'!A:A,'Case Type'!H:H)*Z48 -> 0
... A62: ZM1.2-RD-GN | B62: =_xlfn.XLOOKUP(A62,'Product List'!B:B,'Product List'!I:I) -> MINI/MOE SMALL ANIMAL BEDDING PAPER FLK XMAS CRAN/MATCHA 1EA | C62: 0 | D62: =SUMIFS(Purchase!F:F,Purchase!C:C,A62,Purchase!I:I,">"&$C$1,Purchase!V:V,"<>暂缓发货",Purchase!U:U,"LA") -> 1260 | E62: =SUMIFS(Purchase!F:F,Purchase!C:C,A62,Purchase!J:J,">0",Purchase!I:I,">"&$C$1,Purchase!U:U,"LA") -> 1260 | F62: =SUMIFS(Sales!E:E,Sales!C:C,A62,Sales!K:K,">"&$C$1,Sales!I:I,"LA") -> 630 | G62: =SUMIFS(Sales!E:E,Sales!C:C,A62,Sales!K:K,">"&$C$1,Sales!L:L,">0",Sales!I:I,"LA") -> 630 | H62: =C62+E62-G62+SUMIFS(Transfer!W:W,Transfer!O:O,A62,Transfer!Q:Q,"LA",Transfer!U:U,">"&$C$1)-SUMIFS(Transfer!V:V,Transfer!O:O,A62,Transfer!P:P,"LA",Transfer!T:T,">"&$C$1) -> 630 | I62: =D62-E62+SUMIFS(Transfer!V:V,Transfer!O:O,A62,Transfer!Q:Q,"LA")-SUMIFS(Transfer!W:W,Transfer!O:O,A62,Transfer!Q:Q,"LA") -> 0 | J62: =SUMIFS(Purchase!F:F,Purchase!C:C,A62,Purchase!V:V,"暂缓发货",Purchase!U:U,"LA") -> 0 | K62: =F62-G62 -> 0 | L62: =H62-K62 -> 630 | M62: =H62+I62-K62 -> 630 | N62: =_xlfn.XLOOKUP(A62,'Product List'!B:B,'Product List'!F:F) -> C | O62: =SUMIFS('Weekly Sales'!R:R,'Weekly Sales'!B:B,A62,'Weekly Sales'!U:U,"LA") -> 0 | P62: =IF(O62=0,999,ROUNDDOWN((L62)/O62,0)) -> 999 | Q62: =IF(O62=0,999,ROUNDDOWN((M62)/O62,0)) -> 999 | R62: =_xlfn.XLOOKUP(A62,'Product List'!B:B,'Product List'!P:P) -> 10 | S62: =IF(N62="A",6,IF(N62="B",5,2)) -> 2 | T62: =SUMIFS('Weekly Sales'!T:T,'Weekly Sales'!B:B,A62,'Weekly Sales'!U:U,"LA") -> 0 | U62: =_xlfn.XLOOKUP(A62,'Product List'!B:B,'Product List'!O:O) -> 1000 | V62: =ROUNDUP(MAX(0,O62*(R62+S62+2)+T62-M62)/W62,0)*W62 -> 0 | W62: {=_xlfn.XLOOKUP(1,('Case Pack'!A:A=A62)*('Case Pack'!F:F<=TODAY()),'Case Pack'!D:D,"未找到箱规")} -> 14 | X62: =_xlfn.XLOOKUP(A62,'Product List'!B:B,'Product List'!M:M) -> PSP | Y62: {=_xlfn.XLOOKUP(1,('Case Pack'!A:A=A62)*('Case Pack'!F:F<=TODAY()),'Case Pack'!G:G,"未找到箱规")} -> C | Z62: =V62/W62 -> 0 | AA62: =_xlfn.XLOOKUP(Y62,'Case Type'!A:A,'Case Type'!H:H)*Z62 -> 0

Sheet Sum_HOU
A1: Item Code | B1: Product Name | C1: 46307 | D1: Purchased | E1: Arrived | F1: Sales Order | G1: Cons. | H1: OH Stock | I1: In-Transit | J1: On Hold | K1: Alloc. | L1: Avail. | M1: Total Stock | N1: ABC | O1: Wkly Fcst. | P1: OH TO | Q1: Inv. TO | R1: LT | S1: SS | T1: Extra | U1: MOQ | V1: Plan | W1: Case Pack | X1: Channel | Y1: Case Type | Z1: Case Qty | AA1: CBM
A2: BOBO22-GN | B2: =_xlfn.XLOOKUP(A2,'Product List'!B:B,'Product List'!I:I) -> MINI/MOE SILENT CRSTL RUN WHEEL LG 8.5-Green | C2: 0 | D2: =SUMIFS(Purchase!F:F,Purchase!C:C,A2,Purchase!I:I,">"&$C$1,Purchase!V:V,"<>暂缓发货",Purchase!U:U,"HOU") -> 0 | E2: =SUMIFS(Purchase!F:F,Purchase!C:C,A2,Purchase!J:J,">0",Purchase!I:I,">"&$C$1,Purchase!U:U,"HOU") -> 0 | F2: =SUMIFS(Sales!E:E,Sales!C:C,A2,Sales!K:K,">"&$C$1,Sales!I:I,"HOU") -> 0 | G2: =SUMIFS(Sales!E:E,Sales!C:C,A2,Sales!K:K,">"&$C$1,Sales!L:L,">0",Sales!I:I,"HOU") -> 0 | H2: =C2+E2-G2+SUMIFS(Transfer!W:W,Transfer!O:O,A2,Transfer!Q:Q,"HOU",Transfer!U:U,">"&$C$1)-SUMIFS(Transfer!V:V,Transfer!O:O,A2,Transfer!P:P,"HOU",Transfer!T:T,">"&$C$1) -> 0 | I2: =D2-E2+SUMIFS(Transfer!V:V,Transfer!O:O,A2,Transfer!Q:Q,"HOU")-SUMIFS(Transfer!W:W,Transfer!O:O,A2,Transfer!Q:Q,"HOU") -> 0 | J2: =SUMIFS(Purchase!F:F,Purchase!C:C,A2,Purchase!V:V,"暂缓发货",Purchase!U:U,"HOU") -> 0 | K2: =F2-G2 -> 0 | L2: =H2-K2 -> 0 | M2: =H2+I2-K2 -> 0 | N2: =_xlfn.XLOOKUP(A2,'Product List'!B:B,'Product List'!F:F) -> C | O2: =SUMIFS('Weekly Sales'!R:R,'Weekly Sales'!B:B,A2,'Weekly Sales'!U:U,"HOU") -> 12.666667 | P2: =IF(O2=0,999,ROUNDDOWN((L2)/O2,0)) -> 0 | Q2: =IF(O2=0,999,ROUNDDOWN((M2)/O2,0)) -> 0 | R2: =_xlfn.XLOOKUP(A2,'Product List'!B:B,'Product List'!P:P) -> 10 | S2: =IF(N2="A",6,IF(N2="B",5,2)) -> 2 | T2: =SUMIFS('Weekly Sales'!T:T,'Weekly Sales'!B:B,A2,'Weekly Sales'!U:U,"HOU") -> 0 | U2: =_xlfn.XLOOKUP(A2,'Product List'!B:B,'Product List'!O:O) -> 1000 | V2: =ROUNDUP(MAX(0,O2*(R2+S2+2)+T2-M2)/W2,0)*W2 -> 192 | W2: {=_xlfn.XLOOKUP(1,('Case Pack'!A:A=A2)*('Case Pack'!F:F<=TODAY()),'Case Pack'!D:D,"未找到箱规")} -> 16 | X2: =_xlfn.XLOOKUP(A2,'Product List'!B:B,'Product List'!M:M) -> PSP | Y2: {=_xlfn.XLOOKUP(1,('Case Pack'!A:A=A2)*('Case Pack'!F:F<=TODAY()),'Case Pack'!G:G,"未找到箱规")} -> C | Z2: =V2/W2 -> 12 | AA2: =_xlfn.XLOOKUP(Y2,'Case Type'!A:A,'Case Type'!H:H)*Z2 -> 1.8877898
A3: BOBO22-WH | B3: =_xlfn.XLOOKUP(A3,'Product List'!B:B,'Product List'!I:I) -> MINI/MOE SILENT CRSTL RUN WHEEL LG 8.5-White | C3: 0 | D3: =SUMIFS(Purchase!F:F,Purchase!C:C,A3,Purchase!I:I,">"&$C$1,Purchase!V:V,"<>暂缓发货",Purchase!U:U,"HOU") -> 0 | E3: =SUMIFS(Purchase!F:F,Purchase!C:C,A3,Purchase!J:J,">0",Purchase!I:I,">"&$C$1,Purchase!U:U,"HOU") -> 0 | F3: =SUMIFS(Sales!E:E,Sales!C:C,A3,Sales!K:K,">"&$C$1,Sales!I:I,"HOU") -> 0 | G3: =SUMIFS(Sales!E:E,Sales!C:C,A3,Sales!K:K,">"&$C$1,Sales!L:L,">0",Sales!I:I,"HOU") -> 0 | H3: =C3+E3-G3+SUMIFS(Transfer!W:W,Transfer!O:O,A3,Transfer!Q:Q,"HOU",Transfer!U:U,">"&$C$1)-SUMIFS(Transfer!V:V,Transfer!O:O,A3,Transfer!P:P,"HOU",Transfer!T:T,">"&$C$1) -> 0 | I3: =D3-E3+SUMIFS(Transfer!V:V,Transfer!O:O,A3,Transfer!Q:Q,"HOU")-SUMIFS(Transfer!W:W,Transfer!O:O,A3,Transfer!Q:Q,"HOU") -> 0 | J3: =SUMIFS(Purchase!F:F,Purchase!C:C,A3,Purchase!V:V,"暂缓发货",Purchase!U:U,"HOU") -> 0 | K3: =F3-G3 -> 0 | L3: =H3-K3 -> 0 | M3: =H3+I3-K3 -> 0 | N3: =_xlfn.XLOOKUP(A3,'Product List'!B:B,'Product List'!F:F) -> A | O3: =SUMIFS('Weekly Sales'!R:R,'Weekly Sales'!B:B,A3,'Weekly Sales'!U:U,"HOU") -> 0 | P3: =IF(O3=0,999,ROUNDDOWN((L3)/O3,0)) -> 999 | Q3: =IF(O3=0,999,ROUNDDOWN((M3)/O3,0)) -> 999 | R3: =_xlfn.XLOOKUP(A3,'Product List'!B:B,'Product List'!P:P) -> 10 | S3: =IF(N3="A",6,IF(N3="B",5,2)) -> 6 | T3: =SUMIFS('Weekly Sales'!T:T,'Weekly Sales'!B:B,A3,'Weekly Sales'!U:U,"HOU") -> 0 | U3: =_xlfn.XLOOKUP(A3,'Product List'!B:B,'Product List'!O:O) -> 1000 | V3: =ROUNDUP(MAX(0,O3*(R3+S3+2)+T3-M3)/W3,0)*W3 -> 0 | W3: {=_xlfn.XLOOKUP(1,('Case Pack'!A:A=A3)*('Case Pack'!F:F<=TODAY()),'Case Pack'!D:D,"未找到箱规")} -> 16 | X3: =_xlfn.XLOOKUP(A3,'Product List'!B:B,'Product List'!M:M) -> PetcoUS, PetcoMX, Pet Supermarket，PSP | Y3: {=_xlfn.XLOOKUP(1,('Case Pack'!A:A=A3)*('Case Pack'!F:F<=TODAY()),'Case Pack'!G:G,"未找到箱规")} -> C | Z3: =V3/W3 -> 0 | AA3: =_xlfn.XLOOKUP(Y3,'Case Type'!A:A,'Case Type'!H:H)*Z3 -> 0
A4: CFDL1090-BR | B4: =_xlfn.XLOOKUP(A4,'Product List'!B:B,'Product List'!I:I) -> MINI/MOE SMALL ANIMAL BEDDING CRINKLE PAPER BROWN 1EA | C4: 0 | D4: =SUMIFS(Purchase!F:F,Purchase!C:C,A4,Purchase!I:I,">"&$C$1,Purchase!V:V,"<>暂缓发货",Purchase!U:U,"HOU") -> 0 | E4: =SUMIFS(Purchase!F:F,Purchase!C:C,A4,Purchase!J:J,">0",Purchase!I:I,">"&$C$1,Purchase!U:U,"HOU") -> 0 | F4: =SUMIFS(Sales!E:E,Sales!C:C,A4,Sales!K:K,">"&$C$1,Sales!I:I,"HOU") -> 0 | G4: =SUMIFS(Sales!E:E,Sales!C:C,A4,Sales!K:K,">"&$C$1,Sales!L:L,">0",Sales!I:I,"HOU") -> 0 | H4: =C4+E4-G4+SUMIFS(Transfer!W:W,Transfer!O:O,A4,Transfer!Q:Q,"HOU",Transfer!U:U,">"&$C$1)-SUMIFS(Transfer!V:V,Transfer!O:O,A4,Transfer!P:P,"HOU",Transfer!T:T,">"&$C$1) -> 0 | I4: =D4-E4+SUMIFS(Transfer!V:V,Transfer!O:O,A4,Transfer!Q:Q,"HOU")-SUMIFS(Transfer!W:W,Transfer!O:O,A4,Transfer!Q:Q,"HOU") -> 0 | J4: =SUMIFS(Purchase!F:F,Purchase!C:C,A4,Purchase!V:V,"暂缓发货",Purchase!U:U,"HOU") -> 0 | K4: =F4-G4 -> 0 | L4: =H4-K4 -> 0 | M4: =H4+I4-K4 -> 0 | N4: =_xlfn.XLOOKUP(A4,'Product List'!B:B,'Product List'!F:F) -> C | O4: =SUMIFS('Weekly Sales'!R:R,'Weekly Sales'!B:B,A4,'Weekly Sales'!U:U,"HOU") -> 6 | P4: =IF(O4=0,999,ROUNDDOWN((L4)/O4,0)) -> 0 | Q4: =IF(O4=0,999,ROUNDDOWN((M4)/O4,0)) -> 0 | R4: =_xlfn.XLOOKUP(A4,'Product List'!B:B,'Product List'!P:P) -> 10 | S4: =IF(N4="A",6,IF(N4="B",5,2)) -> 2 | T4: =SUMIFS('Weekly Sales'!T:T,'Weekly Sales'!B:B,A4,'Weekly Sales'!U:U,"HOU") -> 0 | U4: =_xlfn.XLOOKUP(A4,'Product List'!B:B,'Product List'!O:O) -> 1000 | V4: =ROUNDUP(MAX(0,O4*(R4+S4+2)+T4-M4)/W4,0)*W4 -> 90 | W4: {=_xlfn.XLOOKUP(1,('Case Pack'!A:A=A4)*('Case Pack'!F:F<=TODAY()),'Case Pack'!D:D,"未找到箱规")} -> 30 | X4: =_xlfn.XLOOKUP(A4,'Product List'!B:B,'Product List'!M:M) -> PSP | Y4: {=_xlfn.XLOOKUP(1,('Case Pack'!A:A=A4)*('Case Pack'!F:F<=TODAY()),'Case Pack'!G:G,"未找到箱规")} -> A | Z4: =V4/W4 -> 3 | AA4: =_xlfn.XLOOKUP(Y4,'Case Type'!A:A,'Case Type'!H:H)*Z4 -> 0.33036321
A5: CFDL1090-PK | B5: =_xlfn.XLOOKUP(A5,'Product List'!B:B,'Product List'!I:I) -> MINI/MOE SMALL ANIMAL BEDDING PAPER PEBBLES PSTCH/CREAM 1EA | C5: 0 | D5: =SUMIFS(Purchase!F:F,Purchase!C:C,A5,Purchase!I:I,">"&$C$1,Purchase!V:V,"<>暂缓发货",Purchase!U:U,"HOU") -> 0 | E5: =SUMIFS(Purchase!F:F,Purchase!C:C,A5,Purchase!J:J,">0",Purchase!I:I,">"&$C$1,Purchase!U:U,"HOU") -> 0 | F5: =SUMIFS(Sales!E:E,Sales!C:C,A5,Sales!K:K,">"&$C$1,Sales!I:I,"HOU") -> 0 | G5: =SUMIFS(Sales!E:E,Sales!C:C,A5,Sales!K:K,">"&$C$1,Sales!L:L,">0",Sales!I:I,"HOU") -> 0 | H5: =C5+E5-G5+SUMIFS(Transfer!W:W,Transfer!O:O,A5,Transfer!Q:Q,"HOU",Transfer!U:U,">"&$C$1)-SUMIFS(Transfer!V:V,Transfer!O:O,A5,Transfer!P:P,"HOU",Transfer!T:T,">"&$C$1) -> 0 | I5: =D5-E5+SUMIFS(Transfer!V:V,Transfer!O:O,A5,Transfer!Q:Q,"HOU")-SUMIFS(Transfer!W:W,Transfer!O:O,A5,Transfer!Q:Q,"HOU") -> 0 | J5: =SUMIFS(Purchase!F:F,Purchase!C:C,A5,Purchase!V:V,"暂缓发货",Purchase!U:U,"HOU") -> 0 | K5: =F5-G5 -> 0 | L5: =H5-K5 -> 0 | M5: =H5+I5-K5 -> 0 | N5: =_xlfn.XLOOKUP(A5,'Product List'!B:B,'Product List'!F:F) -> C | O5: =SUMIFS('Weekly Sales'!R:R,'Weekly Sales'!B:B,A5,'Weekly Sales'!U:U,"HOU") -> 1.3333333 | P5: =IF(O5=0,999,ROUNDDOWN((L5)/O5,0)) -> 0 | Q5: =IF(O5=0,999,ROUNDDOWN((M5)/O5,0)) -> 0 | R5: =_xlfn.XLOOKUP(A5,'Product List'!B:B,'Product List'!P:P) -> 10 | S5: =IF(N5="A",6,IF(N5="B",5,2)) -> 2 | T5: =SUMIFS('Weekly Sales'!T:T,'Weekly Sales'!B:B,A5,'Weekly Sales'!U:U,"HOU") -> 0 | U5: =_xlfn.XLOOKUP(A5,'Product List'!B:B,'Product List'!O:O) -> 1000 | V5: =ROUNDUP(MAX(0,O5*(R5+S5+2)+T5-M5)/W5,0)*W5 -> 30 | W5: {=_xlfn.XLOOKUP(1,('Case Pack'!A:A=A5)*('Case Pack'!F:F<=TODAY()),'Case Pack'!D:D,"未找到箱规")} -> 30 | X5: =_xlfn.XLOOKUP(A5,'Product List'!B:B,'Product List'!M:M) -> PSP | Y5: {=_xlfn.XLOOKUP(1,('Case Pack'!A:A=A5)*('Case Pack'!F:F<=TODAY()),'Case Pack'!G:G,"未找到箱规")} -> A | Z5: =V5/W5 -> 1 | AA5: =_xlfn.XLOOKUP(Y5,'Case Type'!A:A,'Case Type'!H:H)*Z5 -> 0.11012107
A6: CFDL9000-GN-YL | B6: =_xlfn.XLOOKUP(A6,'Product List'!B:B,'Product List'!I:I) -> MINI/MOE SMALL ANIMAL BEDDING ROLLED PAPER FOREST MIX 1EA | C6: 0 | D6: =SUMIFS(Purchase!F:F,Purchase!C:C,A6,Purchase!I:I,">"&$C$1,Purchase!V:V,"<>暂缓发货",Purchase!U:U,"HOU") -> 0 | E6: =SUMIFS(Purchase!F:F,Purchase!C:C,A6,Purchase!J:J,">0",Purchase!I:I,">"&$C$1,Purchase!U:U,"HOU") -> 0 | F6: =SUMIFS(Sales!E:E,Sales!C:C,A6,Sales!K:K,">"&$C$1,Sales!I:I,"HOU") -> 0 | G6: =SUMIFS(Sales!E:E,Sales!C:C,A6,Sales!K:K,">"&$C$1,Sales!L:L,">0",Sales!I:I,"HOU") -> 0 | H6: =C6+E6-G6+SUMIFS(Transfer!W:W,Transfer!O:O,A6,Transfer!Q:Q,"HOU",Transfer!U:U,">"&$C$1)-SUMIFS(Transfer!V:V,Transfer!O:O,A6,Transfer!P:P,"HOU",Transfer!T:T,">"&$C$1) -> 0 | I6: =D6-E6+SUMIFS(Transfer!V:V,Transfer!O:O,A6,Transfer!Q:Q,"HOU")-SUMIFS(Transfer!W:W,Transfer!O:O,A6,Transfer!Q:Q,"HOU") -> 0 | J6: =SUMIFS(Purchase!F:F,Purchase!C:C,A6,Purchase!V:V,"暂缓发货",Purchase!U:U,"HOU") -> 0 | K6: =F6-G6 -> 0 | L6: =H6-K6 -> 0 | M6: =H6+I6-K6 -> 0 | N6: =_xlfn.XLOOKUP(A6,'Product List'!B:B,'Product List'!F:F) -> B | O6: =SUMIFS('Weekly Sales'!R:R,'Weekly Sales'!B:B,A6,'Weekly Sales'!U:U,"HOU") -> 4 | P6: =IF(O6=0,999,ROUNDDOWN((L6)/O6,0)) -> 0 | Q6: =IF(O6=0,999,ROUNDDOWN((M6)/O6,0)) -> 0 | R6: =_xlfn.XLOOKUP(A6,'Product List'!B:B,'Product List'!P:P) -> 10 | S6: =IF(N6="A",6,IF(N6="B",5,2)) -> 5 | T6: =SUMIFS('Weekly Sales'!T:T,'Weekly Sales'!B:B,A6,'Weekly Sales'!U:U,"HOU") -> 21 | U6: =_xlfn.XLOOKUP(A6,'Product List'!B:B,'Product List'!O:O) -> 1000 | V6: =ROUNDUP(MAX(0,O6*(R6+S6+2)+T6-M6)/W6,0)*W6 -> 90 | W6: {=_xlfn.XLOOKUP(1,('Case Pack'!A:A=A6)*('Case Pack'!F:F<=TODAY()),'Case Pack'!D:D,"未找到箱规")} -> 30 | X6: =_xlfn.XLOOKUP(A6,'Product List'!B:B,'Product List'!M:M) -> PSP | Y6: {=_xlfn.XLOOKUP(1,('Case Pack'!A:A=A6)*('Case Pack'!F:F<=TODAY()),'Case Pack'!G:G,"未找到箱规")} -> A | Z6: =V6/W6 -> 3 | AA6: =_xlfn.XLOOKUP(Y6,'Case Type'!A:A,'Case Type'!H:H)*Z6 -> 0.33036321
A7: CFLS18000 | B7: =_xlfn.XLOOKUP(A7,'Product List'!B:B,'Product List'!I:I) -> MMO-GREEN APPLE CHEW | C7: 0 | D7: =SUMIFS(Purchase!F:F,Purchase!C:C,A7,Purchase!I:I,">"&$C$1,Purchase!V:V,"<>暂缓发货",Purchase!U:U,"HOU") -> 0 | E7: =SUMIFS(Purchase!F:F,Purchase!C:C,A7,Purchase!J:J,">0",Purchase!I:I,">"&$C$1,Purchase!U:U,"HOU") -> 0 | F7: =SUMIFS(Sales!E:E,Sales!C:C,A7,Sales!K:K,">"&$C$1,Sales!I:I,"HOU") -> 0 | G7: =SUMIFS(Sales!E:E,Sales!C:C,A7,Sales!K:K,">"&$C$1,Sales!L:L,">0",Sales!I:I,"HOU") -> 0 | H7: =C7+E7-G7+SUMIFS(Transfer!W:W,Transfer!O:O,A7,Transfer!Q:Q,"HOU",Transfer!U:U,">"&$C$1)-SUMIFS(Transfer!V:V,Transfer!O:O,A7,Transfer!P:P,"HOU",Transfer!T:T,">"&$C$1) -> 0 | I7: =D7-E7+SUMIFS(Transfer!V:V,Transfer!O:O,A7,Transfer!Q:Q,"HOU")-SUMIFS(Transfer!W:W,Transfer!O:O,A7,Transfer!Q:Q,"HOU") -> 0 | J7: =SUMIFS(Purchase!F:F,Purchase!C:C,A7,Purchase!V:V,"暂缓发货",Purchase!U:U,"HOU") -> 0 | K7: =F7-G7 -> 0 | L7: =H7-K7 -> 0 | M7: =H7+I7-K7 -> 0 | N7: =_xlfn.XLOOKUP(A7,'Product List'!B:B,'Product List'!F:F) -> B | O7: =SUMIFS('Weekly Sales'!R:R,'Weekly Sales'!B:B,A7,'Weekly Sales'!U:U,"HOU") -> 5.3333333 | P7: =IF(O7=0,999,ROUNDDOWN((L7)/O7,0)) -> 0 | Q7: =IF(O7=0,999,ROUNDDOWN((M7)/O7,0)) -> 0 | R7: =_xlfn.XLOOKUP(A7,'Product List'!B:B,'Product List'!P:P) -> 10 | S7: =IF(N7="A",6,IF(N7="B",5,2)) -> 5 | T7: =SUMIFS('Weekly Sales'!T:T,'Weekly Sales'!B:B,A7,'Weekly Sales'!U:U,"HOU") -> 28 | U7: =_xlfn.XLOOKUP(A7,'Product List'!B:B,'Product List'!O:O) -> 1000 | V7: =ROUNDUP(MAX(0,O7*(R7+S7+2)+T7-M7)/W7,0)*W7 -> 144 | W7: {=_xlfn.XLOOKUP(1,('Case Pack'!A:A=A7)*('Case Pack'!F:F<=TODAY()),'Case Pack'!D:D,"未找到箱规")} -> 48 | X7: =_xlfn.XLOOKUP(A7,'Product List'!B:B,'Product List'!M:M) -> PetcoUS，PSP | Y7: {=_xlfn.XLOOKUP(1,('Case Pack'!A:A=A7)*('Case Pack'!F:F<=TODAY()),'Case Pack'!G:G,"未找到箱规")} -> B | Z7: =V7/W7 -> 3 | AA7: =_xlfn.XLOOKUP(Y7,'Case Type'!A:A,'Case Type'!H:H)*Z7 -> 0.22024214
A8: CFLS64000YE | B8: =_xlfn.XLOOKUP(A8,'Product List'!B:B,'Product List'!I:I) -> MMO-CAMP LUNCH BOX CHEW | C8: 0 | D8: =SUMIFS(Purchase!F:F,Purchase!C:C,A8,Purchase!I:I,">"&$C$1,Purchase!V:V,"<>暂缓发货",Purchase!U:U,"HOU") -> 0 | E8: =SUMIFS(Purchase!F:F,Purchase!C:C,A8,Purchase!J:J,">0",Purchase!I:I,">"&$C$1,Purchase!U:U,"HOU") -> 0 | F8: =SUMIFS(Sales!E:E,Sales!C:C,A8,Sales!K:K,">"&$C$1,Sales!I:I,"HOU") -> 0 | G8: =SUMIFS(Sales!E:E,Sales!C:C,A8,Sales!K:K,">"&$C$1,Sales!L:L,">0",Sales!I:I,"HOU") -> 0 | H8: =C8+E8-G8+SUMIFS(Transfer!W:W,Transfer!O:O,A8,Transfer!Q:Q,"HOU",Transfer!U:U,">"&$C$1)-SUMIFS(Transfer!V:V,Transfer!O:O,A8,Transfer!P:P,"HOU",Transfer!T:T,">"&$C$1) -> 0 | I8: =D8-E8+SUMIFS(Transfer!V:V,Transfer!O:O,A8,Transfer!Q:Q,"HOU")-SUMIFS(Transfer!W:W,Transfer!O:O,A8,Transfer!Q:Q,"HOU") -> 0 | J8: =SUMIFS(Purchase!F:F,Purchase!C:C,A8,Purchase!V:V,"暂缓发货",Purchase!U:U,"HOU") -> 0 | K8: =F8-G8 -> 0 | L8: =H8-K8 -> 0 | M8: =H8+I8-K8 -> 0 | N8: =_xlfn.XLOOKUP(A8,'Product List'!B:B,'Product List'!F:F) -> B | O8: =SUMIFS('Weekly Sales'!R:R,'Weekly Sales'!B:B,A8,'Weekly Sales'!U:U,"HOU") -> 7.5 | P8: =IF(O8=0,999,ROUNDDOWN((L8)/O8,0)) -> 0 | Q8: =IF(O8=0,999,ROUNDDOWN((M8)/O8,0)) -> 0 | R8: =_xlfn.XLOOKUP(A8,'Product List'!B:B,'Product List'!P:P) -> 10 | S8: =IF(N8="A",6,IF(N8="B",5,2)) -> 5 | T8: =SUMIFS('Weekly Sales'!T:T,'Weekly Sales'!B:B,A8,'Weekly Sales'!U:U,"HOU") -> 39.375 | U8: =_xlfn.XLOOKUP(A8,'Product List'!B:B,'Product List'!O:O) -> 1000 | V8: =ROUNDUP(MAX(0,O8*(R8+S8+2)+T8-M8)/W8,0)*W8 -> 216 | W8: {=_xlfn.XLOOKUP(1,('Case Pack'!A:A=A8)*('Case Pack'!F:F<=TODAY()),'Case Pack'!D:D,"未找到箱规")} -> 72 | X8: =_xlfn.XLOOKUP(A8,'Product List'!B:B,'Product List'!M:M) -> PetcoUS, Pet Supermarket，PSP | Y8: {=_xlfn.XLOOKUP(1,('Case Pack'!A:A=A8)*('Case Pack'!F:F<=TODAY()),'Case Pack'!G:G,"未找到箱规")} -> B | Z8: =V8/W8 -> 3 | AA8: =_xlfn.XLOOKUP(Y8,'Case Type'!A:A,'Case Type'!H:H)*Z8 -> 0.22024214
A9: CFLS71000WH | B9: =_xlfn.XLOOKUP(A9,'Product List'!B:B,'Product List'!I:I) -> MMO-SHELL PEARL HAMSTER CHEW | C9: 0 | D9: =SUMIFS(Purchase!F:F,Purchase!C:C,A9,Purchase!I:I,">"&$C$1,Purchase!V:V,"<>暂缓发货",Purchase!U:U,"HOU") -> 0 | E9: =SUMIFS(Purchase!F:F,Purchase!C:C,A9,Purchase!J:J,">0",Purchase!I:I,">"&$C$1,Purchase!U:U,"HOU") -> 0 | F9: =SUMIFS(Sales!E:E,Sales!C:C,A9,Sales!K:K,">"&$C$1,Sales!I:I,"HOU") -> 0 | G9: =SUMIFS(Sales!E:E,Sales!C:C,A9,Sales!K:K,">"&$C$1,Sales!L:L,">0",Sales!I:I,"HOU") -> 0 | H9: =C9+E9-G9+SUMIFS(Transfer!W:W,Transfer!O:O,A9,Transfer!Q:Q,"HOU",Transfer!U:U,">"&$C$1)-SUMIFS(Transfer!V:V,Transfer!O:O,A9,Transfer!P:P,"HOU",Transfer!T:T,">"&$C$1) -> 0 | I9: =D9-E9+SUMIFS(Transfer!V:V,Transfer!O:O,A9,Transfer!Q:Q,"HOU")-SUMIFS(Transfer!W:W,Transfer!O:O,A9,Transfer!Q:Q,"HOU") -> 0 | J9: =SUMIFS(Purchase!F:F,Purchase!C:C,A9,Purchase!V:V,"暂缓发货",Purchase!U:U,"HOU") -> 0 | K9: =F9-G9 -> 0 | L9: =H9-K9 -> 0 | M9: =H9+I9-K9 -> 0 | N9: =_xlfn.XLOOKUP(A9,'Product List'!B:B,'Product List'!F:F) -> C | O9: =SUMIFS('Weekly Sales'!R:R,'Weekly Sales'!B:B,A9,'Weekly Sales'!U:U,"HOU") -> 0 | P9: =IF(O9=0,999,ROUNDDOWN((L9)/O9,0)) -> 999 | Q9: =IF(O9=0,999,ROUNDDOWN((M9)/O9,0)) -> 999 | R9: =_xlfn.XLOOKUP(A9,'Product List'!B:B,'Product List'!P:P) -> 10 | S9: =IF(N9="A",6,IF(N9="B",5,2)) -> 2 | T9: =SUMIFS('Weekly Sales'!T:T,'Weekly Sales'!B:B,A9,'Weekly Sales'!U:U,"HOU") -> 0 | U9: =_xlfn.XLOOKUP(A9,'Product List'!B:B,'Product List'!O:O) -> 1000 | V9: =ROUNDUP(MAX(0,O9*(R9+S9+2)+T9-M9)/W9,0)*W9 -> 0 | W9: {=_xlfn.XLOOKUP(1,('Case Pack'!A:A=A9)*('Case Pack'!F:F<=TODAY()),'Case Pack'!D:D,"未找到箱规")} -> 64 | X9: =_xlfn.XLOOKUP(A9,'Product List'!B:B,'Product List'!M:M) -> PetcoUS | Y9: {=_xlfn.XLOOKUP(1,('Case Pack'!A:A=A9)*('Case Pack'!F:F<=TODAY()),'Case Pack'!G:G,"未找到箱规")} -> B | Z9: =V9/W9 -> 0 | AA9: =_xlfn.XLOOKUP(Y9,'Case Type'!A:A,'Case Type'!H:H)*Z9 -> 0
A10: CPSH54000WH | B10: =_xlfn.XLOOKUP(A10,'Product List'!B:B,'Product List'!I:I) -> NONO Magnetic Water Bottle (220 ML) | C10: 0 | D10: =SUMIFS(Purchase!F:F,Purchase!C:C,A10,Purchase!I:I,">"&$C$1,Purchase!V:V,"<>暂缓发货",Purchase!U:U,"HOU") -> 0 | E10: =SUMIFS(Purchase!F:F,Purchase!C:C,A10,Purchase!J:J,">0",Purchase!I:I,">"&$C$1,Purchase!U:U,"HOU") -> 0 | F10: =SUMIFS(Sales!E:E,Sales!C:C,A10,Sales!K:K,">"&$C$1,Sales!I:I,"HOU") -> 0 | G10: =SUMIFS(Sales!E:E,Sales!C:C,A10,Sales!K:K,">"&$C$1,Sales!L:L,">0",Sales!I:I,"HOU") -> 0 | H10: =C10+E10-G10+SUMIFS(Transfer!W:W,Transfer!O:O,A10,Transfer!Q:Q,"HOU",Transfer!U:U,">"&$C$1)-SUMIFS(Transfer!V:V,Transfer!O:O,A10,Transfer!P:P,"HOU",Transfer!T:T,">"&$C$1) -> 0 | I10: =D10-E10+SUMIFS(Transfer!V:V,Transfer!O:O,A10,Transfer!Q:Q,"HOU")-SUMIFS(Transfer!W:W,Transfer!O:O,A10,Transfer!Q:Q,"HOU") -> 0 | J10: =SUMIFS(Purchase!F:F,Purchase!C:C,A10,Purchase!V:V,"暂缓发货",Purchase!U:U,"HOU") -> 0 | K10: =F10-G10 -> 0 | L10: =H10-K10 -> 0 | M10: =H10+I10-K10 -> 0 | N10: =_xlfn.XLOOKUP(A10,'Product List'!B:B,'Product List'!F:F) -> C | O10: =SUMIFS('Weekly Sales'!R:R,'Weekly Sales'!B:B,A10,'Weekly Sales'!U:U,"HOU") -> 7.6666667 | P10: =IF(O10=0,999,ROUNDDOWN((L10)/O10,0)) -> 0 | Q10: =IF(O10=0,999,ROUNDDOWN((M10)/O10,0)) -> 0 | R10: =_xlfn.XLOOKUP(A10,'Product List'!B:B,'Product List'!P:P) -> 10 | S10: =IF(N10="A",6,IF(N10="B",5,2)) -> 2 | T10: =SUMIFS('Weekly Sales'!T:T,'Weekly Sales'!B:B,A10,'Weekly Sales'!U:U,"HOU") -> 0 | U10: =_xlfn.XLOOKUP(A10,'Product List'!B:B,'Product List'!O:O) -> 500 | V10: =ROUNDUP(MAX(0,O10*(R10+S10+2)+T10-M10)/W10,0)*W10 -> 120 | W10: {=_xlfn.XLOOKUP(1,('Case Pack'!A:A=A10)*('Case Pack'!F:F<=TODAY()),'Case Pack'!D:D,"未找到箱规")} -> 60 | X10: =_xlfn.XLOOKUP(A10,'Product List'!B:B,'Product List'!M:M) -> PetcoMX,PSP | Y10: {=_xlfn.XLOOKUP(1,('Case Pack'!A:A=A10)*('Case Pack'!F:F<=TODAY()),'Case Pack'!G:G,"未找到箱规")} -> A | Z10: =V10/W10 -> 2 | AA10: =_xlfn.XLOOKUP(Y10,'Case Type'!A:A,'Case Type'!H:H)*Z10 -> 0.22024214
A11: CPSH60007BK | B11: =_xlfn.XLOOKUP(A11,'Product List'!B:B,'Product List'!I:I) -> MINI & MOE MAG CONECT WTR BTL 4 OZ | C11: 0 | D11: =SUMIFS(Purchase!F:F,Purchase!C:C,A11,Purchase!I:I,">"&$C$1,Purchase!V:V,"<>暂缓发货",Purchase!U:U,"HOU") -> 0 | E11: =SUMIFS(Purchase!F:F,Purchase!C:C,A11,Purchase!J:J,">0",Purchase!I:I,">"&$C$1,Purchase!U:U,"HOU") -> 0 | F11: =SUMIFS(Sales!E:E,Sales!C:C,A11,Sales!K:K,">"&$C$1,Sales!I:I,"HOU") -> 0 | G11: =SUMIFS(Sales!E:E,Sales!C:C,A11,Sales!K:K,">"&$C$1,Sales!L:L,">0",Sales!I:I,"HOU") -> 0 | H11: =C11+E11-G11+SUMIFS(Transfer!W:W,Transfer!O:O,A11,Transfer!Q:Q,"HOU",Transfer!U:U,">"&$C$1)-SUMIFS(Transfer!V:V,Transfer!O:O,A11,Transfer!P:P,"HOU",Transfer!T:T,">"&$C$1) -> 0 | I11: =D11-E11+SUMIFS(Transfer!V:V,Transfer!O:O,A11,Transfer!Q:Q,"HOU")-SUMIFS(Transfer!W:W,Transfer!O:O,A11,Transfer!Q:Q,"HOU") -> 0 | J11: =SUMIFS(Purchase!F:F,Purchase!C:C,A11,Purchase!V:V,"暂缓发货",Purchase!U:U,"HOU") -> 0 | K11: =F11-G11 -> 0 | L11: =H11-K11 -> 0 | M11: =H11+I11-K11 -> 0 | N11: =_xlfn.XLOOKUP(A11,'Product List'!B:B,'Product List'!F:F) -> A | O11: =SUMIFS('Weekly Sales'!R:R,'Weekly Sales'!B:B,A11,'Weekly Sales'!U:U,"HOU") -> 0 | P11: =IF(O11=0,999,ROUNDDOWN((L11)/O11,0)) -> 999 | Q11: =IF(O11=0,999,ROUNDDOWN((M11)/O11,0)) -> 999 | R11: =_xlfn.XLOOKUP(A11,'Product List'!B:B,'Product List'!P:P) -> 10 | S11: =IF(N11="A",6,IF(N11="B",5,2)) -> 6 | T11: =SUMIFS('Weekly Sales'!T:T,'Weekly Sales'!B:B,A11,'Weekly Sales'!U:U,"HOU") -> 0 | U11: =_xlfn.XLOOKUP(A11,'Product List'!B:B,'Product List'!O:O) -> 500 | V11: =ROUNDUP(MAX(0,O11*(R11+S11+2)+T11-M11)/W11,0)*W11 -> 0 | W11: {=_xlfn.XLOOKUP(1,('Case Pack'!A:A=A11)*('Case Pack'!F:F<=TODAY()),'Case Pack'!D:D,"未找到箱规")} -> 54 | X11: =_xlfn.XLOOKUP(A11,'Product List'!B:B,'Product List'!M:M) -> Petsmart | Y11: {=_xlfn.XLOOKUP(1,('Case Pack'!A:A=A11)*('Case Pack'!F:F<=TODAY()),'Case Pack'!G:G,"未找到箱规")} -> A | Z11: =V11/W11 -> 0 | AA11: =_xlfn.XLOOKUP(Y11,'Case Type'!A:A,'Case Type'!H:H)*Z11 -> 0
A12: CPSL22004GN | B12: =_xlfn.XLOOKUP(A12,'Product List'!B:B,'Product List'!I:I) -> Ceramic Candy Bowl | C12: 0 | D12: =SUMIFS(Purchase!F:F,Purchase!C:C,A12,Purchase!I:I,">"&$C$1,Purchase!V:V,"<>暂缓发货",Purchase!U:U,"HOU") -> 0 | E12: =SUMIFS(Purchase!F:F,Purchase!C:C,A12,Purchase!J:J,">0",Purchase!I:I,">"&$C$1,Purchase!U:U,"HOU") -> 0 | F12: =SUMIFS(Sales!E:E,Sales!C:C,A12,Sales!K:K,">"&$C$1,Sales!I:I,"HOU") -> 0 | G12: =SUMIFS(Sales!E:E,Sales!C:C,A12,Sales!K:K,">"&$C$1,Sales!L:L,">0",Sales!I:I,"HOU") -> 0 | H12: =C12+E12-G12+SUMIFS(Transfer!W:W,Transfer!O:O,A12,Transfer!Q:Q,"HOU",Transfer!U:U,">"&$C$1)-SUMIFS(Transfer!V:V,Transfer!O:O,A12,Transfer!P:P,"HOU",Transfer!T:T,">"&$C$1) -> 0 | I12: =D12-E12+SUMIFS(Transfer!V:V,Transfer!O:O,A12,Transfer!Q:Q,"HOU")-SUMIFS(Transfer!W:W,Transfer!O:O,A12,Transfer!Q:Q,"HOU") -> 0 | J12: =SUMIFS(Purchase!F:F,Purchase!C:C,A12,Purchase!V:V,"暂缓发货",Purchase!U:U,"HOU") -> 0 | K12: =F12-G12 -> 0 | L12: =H12-K12 -> 0 | M12: =H12+I12-K12 -> 0 | N12: =_xlfn.XLOOKUP(A12,'Product List'!B:B,'Product List'!F:F) -> C | O12: =SUMIFS('Weekly Sales'!R:R,'Weekly Sales'!B:B,A12,'Weekly Sales'!U:U,"HOU") -> 2.1666667 | P12: =IF(O12=0,999,ROUNDDOWN((L12)/O12,0)) -> 0 | Q12: =IF(O12=0,999,ROUNDDOWN((M12)/O12,0)) -> 0 | R12: =_xlfn.XLOOKUP(A12,'Product List'!B:B,'Product List'!P:P) -> 15 | S12: =IF(N12="A",6,IF(N12="B",5,2)) -> 2 | T12: =SUMIFS('Weekly Sales'!T:T,'Weekly Sales'!B:B,A12,'Weekly Sales'!U:U,"HOU") -> 0 | U12: =_xlfn.XLOOKUP(A12,'Product List'!B:B,'Product List'!O:O) -> 2000 | V12: =ROUNDUP(MAX(0,O12*(R12+S12+2)+T12-M12)/W12,0)*W12 -> 48 | W12: {=_xlfn.XLOOKUP(1,('Case Pack'!A:A=A12)*('Case Pack'!F:F<=TODAY()),'Case Pack'!D:D,"未找到箱规")} -> 48 | X12: =_xlfn.XLOOKUP(A12,'Product List'!B:B,'Product List'!M:M) -> PetcoMX,PSP | Y12: {=_xlfn.XLOOKUP(1,('Case Pack'!A:A=A12)*('Case Pack'!F:F<=TODAY()),'Case Pack'!G:G,"未找到箱规")} -> B | Z12: =V12/W12 -> 1 | AA12: =_xlfn.XLOOKUP(Y12,'Case Type'!A:A,'Case Type'!H:H)*Z12 -> 0.073414047
A13: CPWJ0011 | B13: =_xlfn.XLOOKUP(A13,'Product List'!B:B,'Product List'!I:I) -> MINI/MOE MUSHROOM CABIN | C13: 0 | D13: =SUMIFS(Purchase!F:F,Purchase!C:C,A13,Purchase!I:I,">"&$C$1,Purchase!V:V,"<>暂缓发货",Purchase!U:U,"HOU") -> 0 | E13: =SUMIFS(Purchase!F:F,Purchase!C:C,A13,Purchase!J:J,">0",Purchase!I:I,">"&$C$1,Purchase!U:U,"HOU") -> 0 | F13: =SUMIFS(Sales!E:E,Sales!C:C,A13,Sales!K:K,">"&$C$1,Sales!I:I,"HOU") -> 0 | G13: =SUMIFS(Sales!E:E,Sales!C:C,A13,Sales!K:K,">"&$C$1,Sales!L:L,">0",Sales!I:I,"HOU") -> 0 | H13: =C13+E13-G13+SUMIFS(Transfer!W:W,Transfer!O:O,A13,Transfer!Q:Q,"HOU",Transfer!U:U,">"&$C$1)-SUMIFS(Transfer!V:V,Transfer!O:O,A13,Transfer!P:P,"HOU",Transfer!T:T,">"&$C$1) -> 0 | I13: =D13-E13+SUMIFS(Transfer!V:V,Transfer!O:O,A13,Transfer!Q:Q,"HOU")-SUMIFS(Transfer!W:W,Transfer!O:O,A13,Transfer!Q:Q,"HOU") -> 0 | J13: =SUMIFS(Purchase!F:F,Purchase!C:C,A13,Purchase!V:V,"暂缓发货",Purchase!U:U,"HOU") -> 0 | K13: =F13-G13 -> 0 | L13: =H13-K13 -> 0 | M13: =H13+I13-K13 -> 0 | N13: =_xlfn.XLOOKUP(A13,'Product List'!B:B,'Product List'!F:F) -> B | O13: =SUMIFS('Weekly Sales'!R:R,'Weekly Sales'!B:B,A13,'Weekly Sales'!U:U,"HOU") -> 28.333333 | P13: =IF(O13=0,999,ROUNDDOWN((L13)/O13,0)) -> 0 | Q13: =IF(O13=0,999,ROUNDDOWN((M13)/O13,0)) -> 0 | R13: =_xlfn.XLOOKUP(A13,'Product List'!B:B,'Product List'!P:P) -> 15 | S13: =IF(N13="A",6,IF(N13="B",5,2)) -> 5 | T13: =SUMIFS('Weekly Sales'!T:T,'Weekly Sales'!B:B,A13,'Weekly Sales'!U:U,"HOU") -> 148.75 | U13: =_xlfn.XLOOKUP(A13,'Product List'!B:B,'Product List'!O:O) -> 500 | V13: =ROUNDUP(MAX(0,O13*(R13+S13+2)+T13-M13)/W13,0)*W13 -> 784 | W13: {=_xlfn.XLOOKUP(1,('Case Pack'!A:A=A13)*('Case Pack'!F:F<=TODAY()),'Case Pack'!D:D,"未找到箱规")} -> 16 | X13: =_xlfn.XLOOKUP(A13,'Product List'!B:B,'Product List'!M:M) -> PSP | Y13: {=_xlfn.XLOOKUP(1,('Case Pack'!A:A=A13)*('Case Pack'!F:F<=TODAY()),'Case Pack'!G:G,"未找到箱规")} -> C | Z13: =V13/W13 -> 49 | AA13: =_xlfn.XLOOKUP(Y13,'Case Type'!A:A,'Case Type'!H:H)*Z13 -> 7.7084749
... A62: ZM1.2-RD-GN | B62: =_xlfn.XLOOKUP(A62,'Product List'!B:B,'Product List'!I:I) -> MINI/MOE SMALL ANIMAL BEDDING PAPER FLK XMAS CRAN/MATCHA 1EA | C62: 0 | D62: =SUMIFS(Purchase!F:F,Purchase!C:C,A62,Purchase!I:I,">"&$C$1,Purchase!V:V,"<>暂缓发货",Purchase!U:U,"HOU") -> 0 | E62: =SUMIFS(Purchase!F:F,Purchase!C:C,A62,Purchase!J:J,">0",Purchase!I:I,">"&$C$1,Purchase!U:U,"HOU") -> 0 | F62: =SUMIFS(Sales!E:E,Sales!C:C,A62,Sales!K:K,">"&$C$1,Sales!I:I,"HOU") -> 0 | G62: =SUMIFS(Sales!E:E,Sales!C:C,A62,Sales!K:K,">"&$C$1,Sales!L:L,">0",Sales!I:I,"HOU") -> 0 | H62: =C62+E62-G62+SUMIFS(Transfer!W:W,Transfer!O:O,A62,Transfer!Q:Q,"HOU",Transfer!U:U,">"&$C$1)-SUMIFS(Transfer!V:V,Transfer!O:O,A62,Transfer!P:P,"HOU",Transfer!T:T,">"&$C$1) -> 0 | I62: =D62-E62+SUMIFS(Transfer!V:V,Transfer!O:O,A62,Transfer!Q:Q,"HOU")-SUMIFS(Transfer!W:W,Transfer!O:O,A62,Transfer!Q:Q,"HOU") -> 0 | J62: =SUMIFS(Purchase!F:F,Purchase!C:C,A62,Purchase!V:V,"暂缓发货",Purchase!U:U,"HOU") -> 0 | K62: =F62-G62 -> 0 | L62: =H62-K62 -> 0 | M62: =H62+I62-K62 -> 0 | N62: =_xlfn.XLOOKUP(A62,'Product List'!B:B,'Product List'!F:F) -> C | O62: =SUMIFS('Weekly Sales'!R:R,'Weekly Sales'!B:B,A62,'Weekly Sales'!U:U,"HOU") -> 0.33333333 | P62: =IF(O62=0,999,ROUNDDOWN((L62)/O62,0)) -> 0 | Q62: =IF(O62=0,999,ROUNDDOWN((M62)/O62,0)) -> 0 | R62: =_xlfn.XLOOKUP(A62,'Product List'!B:B,'Product List'!P:P) -> 10 | S62: =IF(N62="A",6,IF(N62="B",5,2)) -> 2 | T62: =SUMIFS('Weekly Sales'!T:T,'Weekly Sales'!B:B,A62,'Weekly Sales'!U:U,"HOU") -> 0 | U62: =_xlfn.XLOOKUP(A62,'Product List'!B:B,'Product List'!O:O) -> 1000 | V62: =ROUNDUP(MAX(0,O62*(R62+S62+2)+T62-M62)/W62,0)*W62 -> 14 | W62: {=_xlfn.XLOOKUP(1,('Case Pack'!A:A=A62)*('Case Pack'!F:F<=TODAY()),'Case Pack'!D:D,"未找到箱规")} -> 14 | X62: =_xlfn.XLOOKUP(A62,'Product List'!B:B,'Product List'!M:M) -> PSP | Y62: {=_xlfn.XLOOKUP(1,('Case Pack'!A:A=A62)*('Case Pack'!F:F<=TODAY()),'Case Pack'!G:G,"未找到箱规")} -> C | Z62: =V62/W62 -> 1 | AA62: =_xlfn.XLOOKUP(Y62,'Case Type'!A:A,'Case Type'!H:H)*Z62 -> 0.15731581

Sheet Transfer
A1: SKU | B1: LA | D1: HOU | F1: Case Pack | G1: Case Type | H1: =SUM(I3:I63) -> 47.388506 | J1: =SUM(K3:K63) -> 0 | N1: Batch No. | O1: SKU | P1: From WH | Q1: To WH | R1: Planned Qty | S1: Actual Received Qty | T1: Ship Date | U1: Receipt Date | V1: Counted Shipped Qty | W1: Counted Received Qty | X1: Check
B2: Shortage | C2: Available | D2: Shortage | E2: Available | G2: Case Type | H2: LA→HOU Qty | I2: CBM | J2: HOU→LA Qty | K2: CBM | N2: TF20261013 | O2: xx | P2: LA | Q2: HOU | R2: 208 | T2: 46307 | V2: =IF(AND(ISNUMBER(T2),T2>0,T2<=TODAY(),ISNUMBER(R2),R2>0,COUNTIF(Sum!A:A,O2)>0,P2<>Q2,OR(P2="LA",P2="HOU"),OR(Q2="LA",Q2="HOU")),R2,0) -> 0 | W2: =IF(AND(V2>0,ISNUMBER(U2),U2>=T2,U2<=TODAY(),ISNUMBER(S2),S2>0,S2<=V2),S2,0) -> 0 | X2: =IF(O2="","",IF(COUNTIF(Sum!A:A,O2)=0,"SKU不存在",IF(OR(P2=Q2,AND(P2<>"LA",P2<>"HOU"),AND(Q2<>"LA",Q2<>"HOU")),"仓库错误",IF(AND(ISNUMBER(S2),S2>R2),"收货超过发出",IF(AND(ISNUMBER(U2),OR(NOT(ISNUMBER(T2)),U2<T2)),"收发日期错误",""))))) -> SKU不存在
A3: =Sum!A2 -> BOBO22-GN | B3: =_xlfn.XLOOKUP(A3,Sum_LA!A:A,Sum_LA!V:V) -> 0 | C3: =MAX(0,MIN(_xlfn.XLOOKUP(A3,Sum_LA!A:A,Sum_LA!L:L),_xlfn.XLOOKUP(A3,Sum_LA!A:A,Sum_LA!M:M)-_xlfn.XLOOKUP(A3,Sum_LA!A:A,Sum_LA!O:O)*(_xlfn.XLOOKUP(A3,Sum_LA!A:A,Sum_LA!R:R)+_xlfn.XLOOKUP(A3,Sum_LA!A:A,Sum_LA!S:S)+2)-_xlfn.XLOOKUP(A3,Sum_LA!A:A,Sum_LA!T:T))) -> 368 | D3: =_xlfn.XLOOKUP(A3,Sum_HOU!A:A,Sum_HOU!V:V) -> 192 | E3: =MAX(0,MIN(_xlfn.XLOOKUP(A3,Sum_HOU!A:A,Sum_HOU!L:L),_xlfn.XLOOKUP(A3,Sum_HOU!A:A,Sum_HOU!M:M)-_xlfn.XLOOKUP(A3,Sum_HOU!A:A,Sum_HOU!O:O)*(_xlfn.XLOOKUP(A3,Sum_HOU!A:A,Sum_HOU!R:R)+_xlfn.XLOOKUP(A3,Sum_HOU!A:A,Sum_HOU!S:S)+2)-_xlfn.XLOOKUP(A3,Sum_HOU!A:A,Sum_HOU!T:T))) -> 0 | F3: =_xlfn.XLOOKUP(A3,Sum!A:A,Sum!Y:Y) -> 16 | G3: =_xlfn.XLOOKUP(A3,Sum!A:A,Sum!AA:AA) -> C | H3: =ROUNDDOWN(MIN(D3,C3)/F3,0)*F3 -> 192 | I3: =_xlfn.XLOOKUP(G3,'Case Type'!A:A,'Case Type'!H:H)*(H3/F3) -> 1.8877898 | J3: =ROUNDDOWN(MIN(B3,E3)/F3,0)*F3 -> 0 | K3: =_xlfn.XLOOKUP(G3,'Case Type'!A:A,'Case Type'!H:H)*(J3/F3) -> 0 | N3: TF20261013 | V3: =IF(AND(ISNUMBER(T3),T3>0,T3<=TODAY(),ISNUMBER(R3),R3>0,COUNTIF(Sum!A:A,O3)>0,P3<>Q3,OR(P3="LA",P3="HOU"),OR(Q3="LA",Q3="HOU")),R3,0) -> 0 | W3: =IF(AND(V3>0,ISNUMBER(U3),U3>=T3,U3<=TODAY(),ISNUMBER(S3),S3>0,S3<=V3),S3,0) -> 0 | X3: =IF(O3="","",IF(COUNTIF(Sum!A:A,O3)=0,"SKU不存在",IF(OR(P3=Q3,AND(P3<>"LA",P3<>"HOU"),AND(Q3<>"LA",Q3<>"HOU")),"仓库错误",IF(AND(ISNUMBER(S3),S3>R3),"收货超过发出",IF(AND(ISNUMBER(U3),OR(NOT(ISNUMBER(T3)),U3<T3)),"收发日期错误","")))))
A4: =Sum!A3 -> BOBO22-WH | B4: =_xlfn.XLOOKUP(A4,Sum_LA!A:A,Sum_LA!V:V) -> 0 | C4: =MAX(0,MIN(_xlfn.XLOOKUP(A4,Sum_LA!A:A,Sum_LA!L:L),_xlfn.XLOOKUP(A4,Sum_LA!A:A,Sum_LA!M:M)-_xlfn.XLOOKUP(A4,Sum_LA!A:A,Sum_LA!O:O)*(_xlfn.XLOOKUP(A4,Sum_LA!A:A,Sum_LA!R:R)+_xlfn.XLOOKUP(A4,Sum_LA!A:A,Sum_LA!S:S)+2)-_xlfn.XLOOKUP(A4,Sum_LA!A:A,Sum_LA!T:T))) -> 660.25 | D4: =_xlfn.XLOOKUP(A4,Sum_HOU!A:A,Sum_HOU!V:V) -> 0 | E4: =MAX(0,MIN(_xlfn.XLOOKUP(A4,Sum_HOU!A:A,Sum_HOU!L:L),_xlfn.XLOOKUP(A4,Sum_HOU!A:A,Sum_HOU!M:M)-_xlfn.XLOOKUP(A4,Sum_HOU!A:A,Sum_HOU!O:O)*(_xlfn.XLOOKUP(A4,Sum_HOU!A:A,Sum_HOU!R:R)+_xlfn.XLOOKUP(A4,Sum_HOU!A:A,Sum_HOU!S:S)+2)-_xlfn.XLOOKUP(A4,Sum_HOU!A:A,Sum_HOU!T:T))) -> 0 | F4: =_xlfn.XLOOKUP(A4,Sum!A:A,Sum!Y:Y) -> 16 | G4: =_xlfn.XLOOKUP(A4,Sum!A:A,Sum!AA:AA) -> C | H4: =ROUNDDOWN(MIN(D4,C4)/F4,0)*F4 -> 0 | I4: =_xlfn.XLOOKUP(G4,'Case Type'!A:A,'Case Type'!H:H)*(H4/F4) -> 0 | J4: =ROUNDDOWN(MIN(B4,E4)/F4,0)*F4 -> 0 | K4: =_xlfn.XLOOKUP(G4,'Case Type'!A:A,'Case Type'!H:H)*(J4/F4) -> 0 | N4: TF20261013 | V4: =IF(AND(ISNUMBER(T4),T4>0,T4<=TODAY(),ISNUMBER(R4),R4>0,COUNTIF(Sum!A:A,O4)>0,P4<>Q4,OR(P4="LA",P4="HOU"),OR(Q4="LA",Q4="HOU")),R4,0) -> 0 | W4: =IF(AND(V4>0,ISNUMBER(U4),U4>=T4,U4<=TODAY(),ISNUMBER(S4),S4>0,S4<=V4),S4,0) -> 0 | X4: =IF(O4="","",IF(COUNTIF(Sum!A:A,O4)=0,"SKU不存在",IF(OR(P4=Q4,AND(P4<>"LA",P4<>"HOU"),AND(Q4<>"LA",Q4<>"HOU")),"仓库错误",IF(AND(ISNUMBER(S4),S4>R4),"收货超过发出",IF(AND(ISNUMBER(U4),OR(NOT(ISNUMBER(T4)),U4<T4)),"收发日期错误","")))))
A5: =Sum!A4 -> CFDL1090-BR | B5: =_xlfn.XLOOKUP(A5,Sum_LA!A:A,Sum_LA!V:V) -> 0 | C5: =MAX(0,MIN(_xlfn.XLOOKUP(A5,Sum_LA!A:A,Sum_LA!L:L),_xlfn.XLOOKUP(A5,Sum_LA!A:A,Sum_LA!M:M)-_xlfn.XLOOKUP(A5,Sum_LA!A:A,Sum_LA!O:O)*(_xlfn.XLOOKUP(A5,Sum_LA!A:A,Sum_LA!R:R)+_xlfn.XLOOKUP(A5,Sum_LA!A:A,Sum_LA!S:S)+2)-_xlfn.XLOOKUP(A5,Sum_LA!A:A,Sum_LA!T:T))) -> 630 | D5: =_xlfn.XLOOKUP(A5,Sum_HOU!A:A,Sum_HOU!V:V) -> 90 | E5: =MAX(0,MIN(_xlfn.XLOOKUP(A5,Sum_HOU!A:A,Sum_HOU!L:L),_xlfn.XLOOKUP(A5,Sum_HOU!A:A,Sum_HOU!M:M)-_xlfn.XLOOKUP(A5,Sum_HOU!A:A,Sum_HOU!O:O)*(_xlfn.XLOOKUP(A5,Sum_HOU!A:A,Sum_HOU!R:R)+_xlfn.XLOOKUP(A5,Sum_HOU!A:A,Sum_HOU!S:S)+2)-_xlfn.XLOOKUP(A5,Sum_HOU!A:A,Sum_HOU!T:T))) -> 0 | F5: =_xlfn.XLOOKUP(A5,Sum!A:A,Sum!Y:Y) -> 30 | G5: =_xlfn.XLOOKUP(A5,Sum!A:A,Sum!AA:AA) -> A | H5: =ROUNDDOWN(MIN(D5,C5)/F5,0)*F5 -> 90 | I5: =_xlfn.XLOOKUP(G5,'Case Type'!A:A,'Case Type'!H:H)*(H5/F5) -> 0.33036321 | J5: =ROUNDDOWN(MIN(B5,E5)/F5,0)*F5 -> 0 | K5: =_xlfn.XLOOKUP(G5,'Case Type'!A:A,'Case Type'!H:H)*(J5/F5) -> 0 | N5: TF20261013 | V5: =IF(AND(ISNUMBER(T5),T5>0,T5<=TODAY(),ISNUMBER(R5),R5>0,COUNTIF(Sum!A:A,O5)>0,P5<>Q5,OR(P5="LA",P5="HOU"),OR(Q5="LA",Q5="HOU")),R5,0) -> 0 | W5: =IF(AND(V5>0,ISNUMBER(U5),U5>=T5,U5<=TODAY(),ISNUMBER(S5),S5>0,S5<=V5),S5,0) -> 0 | X5: =IF(O5="","",IF(COUNTIF(Sum!A:A,O5)=0,"SKU不存在",IF(OR(P5=Q5,AND(P5<>"LA",P5<>"HOU"),AND(Q5<>"LA",Q5<>"HOU")),"仓库错误",IF(AND(ISNUMBER(S5),S5>R5),"收货超过发出",IF(AND(ISNUMBER(U5),OR(NOT(ISNUMBER(T5)),U5<T5)),"收发日期错误","")))))
A6: =Sum!A5 -> CFDL1090-PK | B6: =_xlfn.XLOOKUP(A6,Sum_LA!A:A,Sum_LA!V:V) -> 0 | C6: =MAX(0,MIN(_xlfn.XLOOKUP(A6,Sum_LA!A:A,Sum_LA!L:L),_xlfn.XLOOKUP(A6,Sum_LA!A:A,Sum_LA!M:M)-_xlfn.XLOOKUP(A6,Sum_LA!A:A,Sum_LA!O:O)*(_xlfn.XLOOKUP(A6,Sum_LA!A:A,Sum_LA!R:R)+_xlfn.XLOOKUP(A6,Sum_LA!A:A,Sum_LA!S:S)+2)-_xlfn.XLOOKUP(A6,Sum_LA!A:A,Sum_LA!T:T))) -> 630 | D6: =_xlfn.XLOOKUP(A6,Sum_HOU!A:A,Sum_HOU!V:V) -> 30 | E6: =MAX(0,MIN(_xlfn.XLOOKUP(A6,Sum_HOU!A:A,Sum_HOU!L:L),_xlfn.XLOOKUP(A6,Sum_HOU!A:A,Sum_HOU!M:M)-_xlfn.XLOOKUP(A6,Sum_HOU!A:A,Sum_HOU!O:O)*(_xlfn.XLOOKUP(A6,Sum_HOU!A:A,Sum_HOU!R:R)+_xlfn.XLOOKUP(A6,Sum_HOU!A:A,Sum_HOU!S:S)+2)-_xlfn.XLOOKUP(A6,Sum_HOU!A:A,Sum_HOU!T:T))) -> 0 | F6: =_xlfn.XLOOKUP(A6,Sum!A:A,Sum!Y:Y) -> 30 | G6: =_xlfn.XLOOKUP(A6,Sum!A:A,Sum!AA:AA) -> A | H6: =ROUNDDOWN(MIN(D6,C6)/F6,0)*F6 -> 30 | I6: =_xlfn.XLOOKUP(G6,'Case Type'!A:A,'Case Type'!H:H)*(H6/F6) -> 0.11012107 | J6: =ROUNDDOWN(MIN(B6,E6)/F6,0)*F6 -> 0 | K6: =_xlfn.XLOOKUP(G6,'Case Type'!A:A,'Case Type'!H:H)*(J6/F6) -> 0 | N6: TF20261013 | V6: =IF(AND(ISNUMBER(T6),T6>0,T6<=TODAY(),ISNUMBER(R6),R6>0,COUNTIF(Sum!A:A,O6)>0,P6<>Q6,OR(P6="LA",P6="HOU"),OR(Q6="LA",Q6="HOU")),R6,0) -> 0 | W6: =IF(AND(V6>0,ISNUMBER(U6),U6>=T6,U6<=TODAY(),ISNUMBER(S6),S6>0,S6<=V6),S6,0) -> 0 | X6: =IF(O6="","",IF(COUNTIF(Sum!A:A,O6)=0,"SKU不存在",IF(OR(P6=Q6,AND(P6<>"LA",P6<>"HOU"),AND(Q6<>"LA",Q6<>"HOU")),"仓库错误",IF(AND(ISNUMBER(S6),S6>R6),"收货超过发出",IF(AND(ISNUMBER(U6),OR(NOT(ISNUMBER(T6)),U6<T6)),"收发日期错误","")))))
A7: =Sum!A6 -> CFDL9000-GN-YL | B7: =_xlfn.XLOOKUP(A7,Sum_LA!A:A,Sum_LA!V:V) -> 0 | C7: =MAX(0,MIN(_xlfn.XLOOKUP(A7,Sum_LA!A:A,Sum_LA!L:L),_xlfn.XLOOKUP(A7,Sum_LA!A:A,Sum_LA!M:M)-_xlfn.XLOOKUP(A7,Sum_LA!A:A,Sum_LA!O:O)*(_xlfn.XLOOKUP(A7,Sum_LA!A:A,Sum_LA!R:R)+_xlfn.XLOOKUP(A7,Sum_LA!A:A,Sum_LA!S:S)+2)-_xlfn.XLOOKUP(A7,Sum_LA!A:A,Sum_LA!T:T))) -> 1380 | D7: =_xlfn.XLOOKUP(A7,Sum_HOU!A:A,Sum_HOU!V:V) -> 90 | E7: =MAX(0,MIN(_xlfn.XLOOKUP(A7,Sum_HOU!A:A,Sum_HOU!L:L),_xlfn.XLOOKUP(A7,Sum_HOU!A:A,Sum_HOU!M:M)-_xlfn.XLOOKUP(A7,Sum_HOU!A:A,Sum_HOU!O:O)*(_xlfn.XLOOKUP(A7,Sum_HOU!A:A,Sum_HOU!R:R)+_xlfn.XLOOKUP(A7,Sum_HOU!A:A,Sum_HOU!S:S)+2)-_xlfn.XLOOKUP(A7,Sum_HOU!A:A,Sum_HOU!T:T))) -> 0 | F7: =_xlfn.XLOOKUP(A7,Sum!A:A,Sum!Y:Y) -> 30 | G7: =_xlfn.XLOOKUP(A7,Sum!A:A,Sum!AA:AA) -> A | H7: =ROUNDDOWN(MIN(D7,C7)/F7,0)*F7 -> 90 | I7: =_xlfn.XLOOKUP(G7,'Case Type'!A:A,'Case Type'!H:H)*(H7/F7) -> 0.33036321 | J7: =ROUNDDOWN(MIN(B7,E7)/F7,0)*F7 -> 0 | K7: =_xlfn.XLOOKUP(G7,'Case Type'!A:A,'Case Type'!H:H)*(J7/F7) -> 0 | N7: TF20261013 | V7: =IF(AND(ISNUMBER(T7),T7>0,T7<=TODAY(),ISNUMBER(R7),R7>0,COUNTIF(Sum!A:A,O7)>0,P7<>Q7,OR(P7="LA",P7="HOU"),OR(Q7="LA",Q7="HOU")),R7,0) -> 0 | W7: =IF(AND(V7>0,ISNUMBER(U7),U7>=T7,U7<=TODAY(),ISNUMBER(S7),S7>0,S7<=V7),S7,0) -> 0 | X7: =IF(O7="","",IF(COUNTIF(Sum!A:A,O7)=0,"SKU不存在",IF(OR(P7=Q7,AND(P7<>"LA",P7<>"HOU"),AND(Q7<>"LA",Q7<>"HOU")),"仓库错误",IF(AND(ISNUMBER(S7),S7>R7),"收货超过发出",IF(AND(ISNUMBER(U7),OR(NOT(ISNUMBER(T7)),U7<T7)),"收发日期错误","")))))
A8: =Sum!A7 -> CFLS18000 | B8: =_xlfn.XLOOKUP(A8,Sum_LA!A:A,Sum_LA!V:V) -> 0 | C8: =MAX(0,MIN(_xlfn.XLOOKUP(A8,Sum_LA!A:A,Sum_LA!L:L),_xlfn.XLOOKUP(A8,Sum_LA!A:A,Sum_LA!M:M)-_xlfn.XLOOKUP(A8,Sum_LA!A:A,Sum_LA!O:O)*(_xlfn.XLOOKUP(A8,Sum_LA!A:A,Sum_LA!R:R)+_xlfn.XLOOKUP(A8,Sum_LA!A:A,Sum_LA!S:S)+2)-_xlfn.XLOOKUP(A8,Sum_LA!A:A,Sum_LA!T:T))) -> 1435.125 | D8: =_xlfn.XLOOKUP(A8,Sum_HOU!A:A,Sum_HOU!V:V) -> 144 | E8: =MAX(0,MIN(_xlfn.XLOOKUP(A8,Sum_HOU!A:A,Sum_HOU!L:L),_xlfn.XLOOKUP(A8,Sum_HOU!A:A,Sum_HOU!M:M)-_xlfn.XLOOKUP(A8,Sum_HOU!A:A,Sum_HOU!O:O)*(_xlfn.XLOOKUP(A8,Sum_HOU!A:A,Sum_HOU!R:R)+_xlfn.XLOOKUP(A8,Sum_HOU!A:A,Sum_HOU!S:S)+2)-_xlfn.XLOOKUP(A8,Sum_HOU!A:A,Sum_HOU!T:T))) -> 0 | F8: =_xlfn.XLOOKUP(A8,Sum!A:A,Sum!Y:Y) -> 48 | G8: =_xlfn.XLOOKUP(A8,Sum!A:A,Sum!AA:AA) -> B | H8: =ROUNDDOWN(MIN(D8,C8)/F8,0)*F8 -> 144 | I8: =_xlfn.XLOOKUP(G8,'Case Type'!A:A,'Case Type'!H:H)*(H8/F8) -> 0.22024214 | J8: =ROUNDDOWN(MIN(B8,E8)/F8,0)*F8 -> 0 | K8: =_xlfn.XLOOKUP(G8,'Case Type'!A:A,'Case Type'!H:H)*(J8/F8) -> 0 | N8: TF20261013 | V8: =IF(AND(ISNUMBER(T8),T8>0,T8<=TODAY(),ISNUMBER(R8),R8>0,COUNTIF(Sum!A:A,O8)>0,P8<>Q8,OR(P8="LA",P8="HOU"),OR(Q8="LA",Q8="HOU")),R8,0) -> 0 | W8: =IF(AND(V8>0,ISNUMBER(U8),U8>=T8,U8<=TODAY(),ISNUMBER(S8),S8>0,S8<=V8),S8,0) -> 0 | X8: =IF(O8="","",IF(COUNTIF(Sum!A:A,O8)=0,"SKU不存在",IF(OR(P8=Q8,AND(P8<>"LA",P8<>"HOU"),AND(Q8<>"LA",Q8<>"HOU")),"仓库错误",IF(AND(ISNUMBER(S8),S8>R8),"收货超过发出",IF(AND(ISNUMBER(U8),OR(NOT(ISNUMBER(T8)),U8<T8)),"收发日期错误","")))))
A9: =Sum!A8 -> CFLS64000YE | B9: =_xlfn.XLOOKUP(A9,Sum_LA!A:A,Sum_LA!V:V) -> 0 | C9: =MAX(0,MIN(_xlfn.XLOOKUP(A9,Sum_LA!A:A,Sum_LA!L:L),_xlfn.XLOOKUP(A9,Sum_LA!A:A,Sum_LA!M:M)-_xlfn.XLOOKUP(A9,Sum_LA!A:A,Sum_LA!O:O)*(_xlfn.XLOOKUP(A9,Sum_LA!A:A,Sum_LA!R:R)+_xlfn.XLOOKUP(A9,Sum_LA!A:A,Sum_LA!S:S)+2)-_xlfn.XLOOKUP(A9,Sum_LA!A:A,Sum_LA!T:T))) -> 785.25 | D9: =_xlfn.XLOOKUP(A9,Sum_HOU!A:A,Sum_HOU!V:V) -> 216 | E9: =MAX(0,MIN(_xlfn.XLOOKUP(A9,Sum_HOU!A:A,Sum_HOU!L:L),_xlfn.XLOOKUP(A9,Sum_HOU!A:A,Sum_HOU!M:M)-_xlfn.XLOOKUP(A9,Sum_HOU!A:A,Sum_HOU!O:O)*(_xlfn.XLOOKUP(A9,Sum_HOU!A:A,Sum_HOU!R:R)+_xlfn.XLOOKUP(A9,Sum_HOU!A:A,Sum_HOU!S:S)+2)-_xlfn.XLOOKUP(A9,Sum_HOU!A:A,Sum_HOU!T:T))) -> 0 | F9: =_xlfn.XLOOKUP(A9,Sum!A:A,Sum!Y:Y) -> 72 | G9: =_xlfn.XLOOKUP(A9,Sum!A:A,Sum!AA:AA) -> B | H9: =ROUNDDOWN(MIN(D9,C9)/F9,0)*F9 -> 216 | I9: =_xlfn.XLOOKUP(G9,'Case Type'!A:A,'Case Type'!H:H)*(H9/F9) -> 0.22024214 | J9: =ROUNDDOWN(MIN(B9,E9)/F9,0)*F9 -> 0 | K9: =_xlfn.XLOOKUP(G9,'Case Type'!A:A,'Case Type'!H:H)*(J9/F9) -> 0 | V9: =IF(AND(ISNUMBER(T9),T9>0,T9<=TODAY(),ISNUMBER(R9),R9>0,COUNTIF(Sum!A:A,O9)>0,P9<>Q9,OR(P9="LA",P9="HOU"),OR(Q9="LA",Q9="HOU")),R9,0) -> 0 | W9: =IF(AND(V9>0,ISNUMBER(U9),U9>=T9,U9<=TODAY(),ISNUMBER(S9),S9>0,S9<=V9),S9,0) -> 0 | X9: =IF(O9="","",IF(COUNTIF(Sum!A:A,O9)=0,"SKU不存在",IF(OR(P9=Q9,AND(P9<>"LA",P9<>"HOU"),AND(Q9<>"LA",Q9<>"HOU")),"仓库错误",IF(AND(ISNUMBER(S9),S9>R9),"收货超过发出",IF(AND(ISNUMBER(U9),OR(NOT(ISNUMBER(T9)),U9<T9)),"收发日期错误","")))))
A10: =Sum!A9 -> CFLS71000WH | B10: =_xlfn.XLOOKUP(A10,Sum_LA!A:A,Sum_LA!V:V) -> 0 | C10: =MAX(0,MIN(_xlfn.XLOOKUP(A10,Sum_LA!A:A,Sum_LA!L:L),_xlfn.XLOOKUP(A10,Sum_LA!A:A,Sum_LA!M:M)-_xlfn.XLOOKUP(A10,Sum_LA!A:A,Sum_LA!O:O)*(_xlfn.XLOOKUP(A10,Sum_LA!A:A,Sum_LA!R:R)+_xlfn.XLOOKUP(A10,Sum_LA!A:A,Sum_LA!S:S)+2)-_xlfn.XLOOKUP(A10,Sum_LA!A:A,Sum_LA!T:T))) -> 2699.6667 | D10: =_xlfn.XLOOKUP(A10,Sum_HOU!A:A,Sum_HOU!V:V) -> 0 | E10: =MAX(0,MIN(_xlfn.XLOOKUP(A10,Sum_HOU!A:A,Sum_HOU!L:L),_xlfn.XLOOKUP(A10,Sum_HOU!A:A,Sum_HOU!M:M)-_xlfn.XLOOKUP(A10,Sum_HOU!A:A,Sum_HOU!O:O)*(_xlfn.XLOOKUP(A10,Sum_HOU!A:A,Sum_HOU!R:R)+_xlfn.XLOOKUP(A10,Sum_HOU!A:A,Sum_HOU!S:S)+2)-_xlfn.XLOOKUP(A10,Sum_HOU!A:A,Sum_HOU!T:T))) -> 0 | F10: =_xlfn.XLOOKUP(A10,Sum!A:A,Sum!Y:Y) -> 64 | G10: =_xlfn.XLOOKUP(A10,Sum!A:A,Sum!AA:AA) -> B | H10: =ROUNDDOWN(MIN(D10,C10)/F10,0)*F10 -> 0 | I10: =_xlfn.XLOOKUP(G10,'Case Type'!A:A,'Case Type'!H:H)*(H10/F10) -> 0 | J10: =ROUNDDOWN(MIN(B10,E10)/F10,0)*F10 -> 0 | K10: =_xlfn.XLOOKUP(G10,'Case Type'!A:A,'Case Type'!H:H)*(J10/F10) -> 0 | V10: =IF(AND(ISNUMBER(T10),T10>0,T10<=TODAY(),ISNUMBER(R10),R10>0,COUNTIF(Sum!A:A,O10)>0,P10<>Q10,OR(P10="LA",P10="HOU"),OR(Q10="LA",Q10="HOU")),R10,0) -> 0 | W10: =IF(AND(V10>0,ISNUMBER(U10),U10>=T10,U10<=TODAY(),ISNUMBER(S10),S10>0,S10<=V10),S10,0) -> 0 | X10: =IF(O10="","",IF(COUNTIF(Sum!A:A,O10)=0,"SKU不存在",IF(OR(P10=Q10,AND(P10<>"LA",P10<>"HOU"),AND(Q10<>"LA",Q10<>"HOU")),"仓库错误",IF(AND(ISNUMBER(S10),S10>R10),"收货超过发出",IF(AND(ISNUMBER(U10),OR(NOT(ISNUMBER(T10)),U10<T10)),"收发日期错误","")))))
A11: =Sum!A10 -> CPSH54000WH | B11: =_xlfn.XLOOKUP(A11,Sum_LA!A:A,Sum_LA!V:V) -> 0 | C11: =MAX(0,MIN(_xlfn.XLOOKUP(A11,Sum_LA!A:A,Sum_LA!L:L),_xlfn.XLOOKUP(A11,Sum_LA!A:A,Sum_LA!M:M)-_xlfn.XLOOKUP(A11,Sum_LA!A:A,Sum_LA!O:O)*(_xlfn.XLOOKUP(A11,Sum_LA!A:A,Sum_LA!R:R)+_xlfn.XLOOKUP(A11,Sum_LA!A:A,Sum_LA!S:S)+2)-_xlfn.XLOOKUP(A11,Sum_LA!A:A,Sum_LA!T:T))) -> 600 | D11: =_xlfn.XLOOKUP(A11,Sum_HOU!A:A,Sum_HOU!V:V) -> 120 | E11: =MAX(0,MIN(_xlfn.XLOOKUP(A11,Sum_HOU!A:A,Sum_HOU!L:L),_xlfn.XLOOKUP(A11,Sum_HOU!A:A,Sum_HOU!M:M)-_xlfn.XLOOKUP(A11,Sum_HOU!A:A,Sum_HOU!O:O)*(_xlfn.XLOOKUP(A11,Sum_HOU!A:A,Sum_HOU!R:R)+_xlfn.XLOOKUP(A11,Sum_HOU!A:A,Sum_HOU!S:S)+2)-_xlfn.XLOOKUP(A11,Sum_HOU!A:A,Sum_HOU!T:T))) -> 0 | F11: =_xlfn.XLOOKUP(A11,Sum!A:A,Sum!Y:Y) -> 60 | G11: =_xlfn.XLOOKUP(A11,Sum!A:A,Sum!AA:AA) -> A | H11: =ROUNDDOWN(MIN(D11,C11)/F11,0)*F11 -> 120 | I11: =_xlfn.XLOOKUP(G11,'Case Type'!A:A,'Case Type'!H:H)*(H11/F11) -> 0.22024214 | J11: =ROUNDDOWN(MIN(B11,E11)/F11,0)*F11 -> 0 | K11: =_xlfn.XLOOKUP(G11,'Case Type'!A:A,'Case Type'!H:H)*(J11/F11) -> 0 | V11: =IF(AND(ISNUMBER(T11),T11>0,T11<=TODAY(),ISNUMBER(R11),R11>0,COUNTIF(Sum!A:A,O11)>0,P11<>Q11,OR(P11="LA",P11="HOU"),OR(Q11="LA",Q11="HOU")),R11,0) -> 0 | W11: =IF(AND(V11>0,ISNUMBER(U11),U11>=T11,U11<=TODAY(),ISNUMBER(S11),S11>0,S11<=V11),S11,0) -> 0 | X11: =IF(O11="","",IF(COUNTIF(Sum!A:A,O11)=0,"SKU不存在",IF(OR(P11=Q11,AND(P11<>"LA",P11<>"HOU"),AND(Q11<>"LA",Q11<>"HOU")),"仓库错误",IF(AND(ISNUMBER(S11),S11>R11),"收货超过发出",IF(AND(ISNUMBER(U11),OR(NOT(ISNUMBER(T11)),U11<T11)),"收发日期错误","")))))
A12: =Sum!A11 -> CPSH60007BK | B12: =_xlfn.XLOOKUP(A12,Sum_LA!A:A,Sum_LA!V:V) -> 0 | C12: =MAX(0,MIN(_xlfn.XLOOKUP(A12,Sum_LA!A:A,Sum_LA!L:L),_xlfn.XLOOKUP(A12,Sum_LA!A:A,Sum_LA!M:M)-_xlfn.XLOOKUP(A12,Sum_LA!A:A,Sum_LA!O:O)*(_xlfn.XLOOKUP(A12,Sum_LA!A:A,Sum_LA!R:R)+_xlfn.XLOOKUP(A12,Sum_LA!A:A,Sum_LA!S:S)+2)-_xlfn.XLOOKUP(A12,Sum_LA!A:A,Sum_LA!T:T))) -> 976.5 | D12: =_xlfn.XLOOKUP(A12,Sum_HOU!A:A,Sum_HOU!V:V) -> 0 | E12: =MAX(0,MIN(_xlfn.XLOOKUP(A12,Sum_HOU!A:A,Sum_HOU!L:L),_xlfn.XLOOKUP(A12,Sum_HOU!A:A,Sum_HOU!M:M)-_xlfn.XLOOKUP(A12,Sum_HOU!A:A,Sum_HOU!O:O)*(_xlfn.XLOOKUP(A12,Sum_HOU!A:A,Sum_HOU!R:R)+_xlfn.XLOOKUP(A12,Sum_HOU!A:A,Sum_HOU!S:S)+2)-_xlfn.XLOOKUP(A12,Sum_HOU!A:A,Sum_HOU!T:T))) -> 0 | F12: =_xlfn.XLOOKUP(A12,Sum!A:A,Sum!Y:Y) -> 54 | G12: =_xlfn.XLOOKUP(A12,Sum!A:A,Sum!AA:AA) -> A | H12: =ROUNDDOWN(MIN(D12,C12)/F12,0)*F12 -> 0 | I12: =_xlfn.XLOOKUP(G12,'Case Type'!A:A,'Case Type'!H:H)*(H12/F12) -> 0 | J12: =ROUNDDOWN(MIN(B12,E12)/F12,0)*F12 -> 0 | K12: =_xlfn.XLOOKUP(G12,'Case Type'!A:A,'Case Type'!H:H)*(J12/F12) -> 0 | V12: =IF(AND(ISNUMBER(T12),T12>0,T12<=TODAY(),ISNUMBER(R12),R12>0,COUNTIF(Sum!A:A,O12)>0,P12<>Q12,OR(P12="LA",P12="HOU"),OR(Q12="LA",Q12="HOU")),R12,0) -> 0 | W12: =IF(AND(V12>0,ISNUMBER(U12),U12>=T12,U12<=TODAY(),ISNUMBER(S12),S12>0,S12<=V12),S12,0) -> 0 | X12: =IF(O12="","",IF(COUNTIF(Sum!A:A,O12)=0,"SKU不存在",IF(OR(P12=Q12,AND(P12<>"LA",P12<>"HOU"),AND(Q12<>"LA",Q12<>"HOU")),"仓库错误",IF(AND(ISNUMBER(S12),S12>R12),"收货超过发出",IF(AND(ISNUMBER(U12),OR(NOT(ISNUMBER(T12)),U12<T12)),"收发日期错误","")))))
A13: =Sum!A12 -> CPSL22004GN | B13: =_xlfn.XLOOKUP(A13,Sum_LA!A:A,Sum_LA!V:V) -> 0 | C13: =MAX(0,MIN(_xlfn.XLOOKUP(A13,Sum_LA!A:A,Sum_LA!L:L),_xlfn.XLOOKUP(A13,Sum_LA!A:A,Sum_LA!M:M)-_xlfn.XLOOKUP(A13,Sum_LA!A:A,Sum_LA!O:O)*(_xlfn.XLOOKUP(A13,Sum_LA!A:A,Sum_LA!R:R)+_xlfn.XLOOKUP(A13,Sum_LA!A:A,Sum_LA!S:S)+2)-_xlfn.XLOOKUP(A13,Sum_LA!A:A,Sum_LA!T:T))) -> 576 | D13: =_xlfn.XLOOKUP(A13,Sum_HOU!A:A,Sum_HOU!V:V) -> 48 | E13: =MAX(0,MIN(_xlfn.XLOOKUP(A13,Sum_HOU!A:A,Sum_HOU!L:L),_xlfn.XLOOKUP(A13,Sum_HOU!A:A,Sum_HOU!M:M)-_xlfn.XLOOKUP(A13,Sum_HOU!A:A,Sum_HOU!O:O)*(_xlfn.XLOOKUP(A13,Sum_HOU!A:A,Sum_HOU!R:R)+_xlfn.XLOOKUP(A13,Sum_HOU!A:A,Sum_HOU!S:S)+2)-_xlfn.XLOOKUP(A13,Sum_HOU!A:A,Sum_HOU!T:T))) -> 0 | F13: =_xlfn.XLOOKUP(A13,Sum!A:A,Sum!Y:Y) -> 48 | G13: =_xlfn.XLOOKUP(A13,Sum!A:A,Sum!AA:AA) -> B | H13: =ROUNDDOWN(MIN(D13,C13)/F13,0)*F13 -> 48 | I13: =_xlfn.XLOOKUP(G13,'Case Type'!A:A,'Case Type'!H:H)*(H13/F13) -> 0.073414047 | J13: =ROUNDDOWN(MIN(B13,E13)/F13,0)*F13 -> 0 | K13: =_xlfn.XLOOKUP(G13,'Case Type'!A:A,'Case Type'!H:H)*(J13/F13) -> 0 | V13: =IF(AND(ISNUMBER(T13),T13>0,T13<=TODAY(),ISNUMBER(R13),R13>0,COUNTIF(Sum!A:A,O13)>0,P13<>Q13,OR(P13="LA",P13="HOU"),OR(Q13="LA",Q13="HOU")),R13,0) -> 0 | W13: =IF(AND(V13>0,ISNUMBER(U13),U13>=T13,U13<=TODAY(),ISNUMBER(S13),S13>0,S13<=V13),S13,0) -> 0 | X13: =IF(O13="","",IF(COUNTIF(Sum!A:A,O13)=0,"SKU不存在",IF(OR(P13=Q13,AND(P13<>"LA",P13<>"HOU"),AND(Q13<>"LA",Q13<>"HOU")),"仓库错误",IF(AND(ISNUMBER(S13),S13>R13),"收货超过发出",IF(AND(ISNUMBER(U13),OR(NOT(ISNUMBER(T13)),U13<T13)),"收发日期错误","")))))
A14: =Sum!A13 -> CPWJ0011 | B14: =_xlfn.XLOOKUP(A14,Sum_LA!A:A,Sum_LA!V:V) -> 0 | C14: =MAX(0,MIN(_xlfn.XLOOKUP(A14,Sum_LA!A:A,Sum_LA!L:L),_xlfn.XLOOKUP(A14,Sum_LA!A:A,Sum_LA!M:M)-_xlfn.XLOOKUP(A14,Sum_LA!A:A,Sum_LA!O:O)*(_xlfn.XLOOKUP(A14,Sum_LA!A:A,Sum_LA!R:R)+_xlfn.XLOOKUP(A14,Sum_LA!A:A,Sum_LA!S:S)+2)-_xlfn.XLOOKUP(A14,Sum_LA!A:A,Sum_LA!T:T))) -> 496 | D14: =_xlfn.XLOOKUP(A14,Sum_HOU!A:A,Sum_HOU!V:V) -> 784 | E14: =MAX(0,MIN(_xlfn.XLOOKUP(A14,Sum_HOU!A:A,Sum_HOU!L:L),_xlfn.XLOOKUP(A14,Sum_HOU!A:A,Sum_HOU!M:M)-_xlfn.XLOOKUP(A14,Sum_HOU!A:A,Sum_HOU!O:O)*(_xlfn.XLOOKUP(A14,Sum_HOU!A:A,Sum_HOU!R:R)+_xlfn.XLOOKUP(A14,Sum_HOU!A:A,Sum_HOU!S:S)+2)-_xlfn.XLOOKUP(A14,Sum_HOU!A:A,Sum_HOU!T:T))) -> 0 | F14: =_xlfn.XLOOKUP(A14,Sum!A:A,Sum!Y:Y) -> 16 | G14: =_xlfn.XLOOKUP(A14,Sum!A:A,Sum!AA:AA) -> C | H14: =ROUNDDOWN(MIN(D14,C14)/F14,0)*F14 -> 496 | I14: =_xlfn.XLOOKUP(G14,'Case Type'!A:A,'Case Type'!H:H)*(H14/F14) -> 4.8767902 | J14: =ROUNDDOWN(MIN(B14,E14)/F14,0)*F14 -> 0 | K14: =_xlfn.XLOOKUP(G14,'Case Type'!A:A,'Case Type'!H:H)*(J14/F14) -> 0 | V14: =IF(AND(ISNUMBER(T14),T14>0,T14<=TODAY(),ISNUMBER(R14),R14>0,COUNTIF(Sum!A:A,O14)>0,P14<>Q14,OR(P14="LA",P14="HOU"),OR(Q14="LA",Q14="HOU")),R14,0) -> 0 | W14: =IF(AND(V14>0,ISNUMBER(U14),U14>=T14,U14<=TODAY(),ISNUMBER(S14),S14>0,S14<=V14),S14,0) -> 0 | X14: =IF(O14="","",IF(COUNTIF(Sum!A:A,O14)=0,"SKU不存在",IF(OR(P14=Q14,AND(P14<>"LA",P14<>"HOU"),AND(Q14<>"LA",Q14<>"HOU")),"仓库错误",IF(AND(ISNUMBER(S14),S14>R14),"收货超过发出",IF(AND(ISNUMBER(U14),OR(NOT(ISNUMBER(T14)),U14<T14)),"收发日期错误","")))))
A15: =Sum!A14 -> CPWJ0012 | B15: =_xlfn.XLOOKUP(A15,Sum_LA!A:A,Sum_LA!V:V) -> 0 | C15: =MAX(0,MIN(_xlfn.XLOOKUP(A15,Sum_LA!A:A,Sum_LA!L:L),_xlfn.XLOOKUP(A15,Sum_LA!A:A,Sum_LA!M:M)-_xlfn.XLOOKUP(A15,Sum_LA!A:A,Sum_LA!O:O)*(_xlfn.XLOOKUP(A15,Sum_LA!A:A,Sum_LA!R:R)+_xlfn.XLOOKUP(A15,Sum_LA!A:A,Sum_LA!S:S)+2)-_xlfn.XLOOKUP(A15,Sum_LA!A:A,Sum_LA!T:T))) -> 630 | D15: =_xlfn.XLOOKUP(A15,Sum_HOU!A:A,Sum_HOU!V:V) -> 60 | E15: =MAX(0,MIN(_xlfn.XLOOKUP(A15,Sum_HOU!A:A,Sum_HOU!L:L),_xlfn.XLOOKUP(A15,Sum_HOU!A:A,Sum_HOU!M:M)-_xlfn.XLOOKUP(A15,Sum_HOU!A:A,Sum_HOU!O:O)*(_xlfn.XLOOKUP(A15,Sum_HOU!A:A,Sum_HOU!R:R)+_xlfn.XLOOKUP(A15,Sum_HOU!A:A,Sum_HOU!S:S)+2)-_xlfn.XLOOKUP(A15,Sum_HOU!A:A,Sum_HOU!T:T))) -> 0 | F15: =_xlfn.XLOOKUP(A15,Sum!A:A,Sum!Y:Y) -> 30 | G15: =_xlfn.XLOOKUP(A15,Sum!A:A,Sum!AA:AA) -> C | H15: =ROUNDDOWN(MIN(D15,C15)/F15,0)*F15 -> 60 | I15: =_xlfn.XLOOKUP(G15,'Case Type'!A:A,'Case Type'!H:H)*(H15/F15) -> 0.31463163 | J15: =ROUNDDOWN(MIN(B15,E15)/F15,0)*F15 -> 0 | K15: =_xlfn.XLOOKUP(G15,'Case Type'!A:A,'Case Type'!H:H)*(J15/F15) -> 0 | V15: =IF(AND(ISNUMBER(T15),T15>0,T15<=TODAY(),ISNUMBER(R15),R15>0,COUNTIF(Sum!A:A,O15)>0,P15<>Q15,OR(P15="LA",P15="HOU"),OR(Q15="LA",Q15="HOU")),R15,0) -> 0 | W15: =IF(AND(V15>0,ISNUMBER(U15),U15>=T15,U15<=TODAY(),ISNUMBER(S15),S15>0,S15<=V15),S15,0) -> 0 | X15: =IF(O15="","",IF(COUNTIF(Sum!A:A,O15)=0,"SKU不存在",IF(OR(P15=Q15,AND(P15<>"LA",P15<>"HOU"),AND(Q15<>"LA",Q15<>"HOU")),"仓库错误",IF(AND(ISNUMBER(S15),S15>R15),"收货超过发出",IF(AND(ISNUMBER(U15),OR(NOT(ISNUMBER(T15)),U15<T15)),"收发日期错误","")))))
A16: =Sum!A15 -> CPWJ0013 | B16: =_xlfn.XLOOKUP(A16,Sum_LA!A:A,Sum_LA!V:V) -> 0 | C16: =MAX(0,MIN(_xlfn.XLOOKUP(A16,Sum_LA!A:A,Sum_LA!L:L),_xlfn.XLOOKUP(A16,Sum_LA!A:A,Sum_LA!M:M)-_xlfn.XLOOKUP(A16,Sum_LA!A:A,Sum_LA!O:O)*(_xlfn.XLOOKUP(A16,Sum_LA!A:A,Sum_LA!R:R)+_xlfn.XLOOKUP(A16,Sum_LA!A:A,Sum_LA!S:S)+2)-_xlfn.XLOOKUP(A16,Sum_LA!A:A,Sum_LA!T:T))) -> 930 | D16: =_xlfn.XLOOKUP(A16,Sum_HOU!A:A,Sum_HOU!V:V) -> 450 | E16: =MAX(0,MIN(_xlfn.XLOOKUP(A16,Sum_HOU!A:A,Sum_HOU!L:L),_xlfn.XLOOKUP(A16,Sum_HOU!A:A,Sum_HOU!M:M)-_xlfn.XLOOKUP(A16,Sum_HOU!A:A,Sum_HOU!O:O)*(_xlfn.XLOOKUP(A16,Sum_HOU!A:A,Sum_HOU!R:R)+_xlfn.XLOOKUP(A16,Sum_HOU!A:A,Sum_HOU!S:S)+2)-_xlfn.XLOOKUP(A16,Sum_HOU!A:A,Sum_HOU!T:T))) -> 0 | F16: =_xlfn.XLOOKUP(A16,Sum!A:A,Sum!Y:Y) -> 30 | G16: =_xlfn.XLOOKUP(A16,Sum!A:A,Sum!AA:AA) -> C | H16: =ROUNDDOWN(MIN(D16,C16)/F16,0)*F16 -> 450 | I16: =_xlfn.XLOOKUP(G16,'Case Type'!A:A,'Case Type'!H:H)*(H16/F16) -> 2.3597372 | J16: =ROUNDDOWN(MIN(B16,E16)/F16,0)*F16 -> 0 | K16: =_xlfn.XLOOKUP(G16,'Case Type'!A:A,'Case Type'!H:H)*(J16/F16) -> 0 | V16: =IF(AND(ISNUMBER(T16),T16>0,T16<=TODAY(),ISNUMBER(R16),R16>0,COUNTIF(Sum!A:A,O16)>0,P16<>Q16,OR(P16="LA",P16="HOU"),OR(Q16="LA",Q16="HOU")),R16,0) -> 0 | W16: =IF(AND(V16>0,ISNUMBER(U16),U16>=T16,U16<=TODAY(),ISNUMBER(S16),S16>0,S16<=V16),S16,0) -> 0 | X16: =IF(O16="","",IF(COUNTIF(Sum!A:A,O16)=0,"SKU不存在",IF(OR(P16=Q16,AND(P16<>"LA",P16<>"HOU"),AND(Q16<>"LA",Q16<>"HOU")),"仓库错误",IF(AND(ISNUMBER(S16),S16>R16),"收货超过发出",IF(AND(ISNUMBER(U16),OR(NOT(ISNUMBER(T16)),U16<T16)),"收发日期错误","")))))
A17: =Sum!A16 -> CPWJ0014 | B17: =_xlfn.XLOOKUP(A17,Sum_LA!A:A,Sum_LA!V:V) -> 0 | C17: =MAX(0,MIN(_xlfn.XLOOKUP(A17,Sum_LA!A:A,Sum_LA!L:L),_xlfn.XLOOKUP(A17,Sum_LA!A:A,Sum_LA!M:M)-_xlfn.XLOOKUP(A17,Sum_LA!A:A,Sum_LA!O:O)*(_xlfn.XLOOKUP(A17,Sum_LA!A:A,Sum_LA!R:R)+_xlfn.XLOOKUP(A17,Sum_LA!A:A,Sum_LA!S:S)+2)-_xlfn.XLOOKUP(A17,Sum_LA!A:A,Sum_LA!T:T))) -> 450 | D17: =_xlfn.XLOOKUP(A17,Sum_HOU!A:A,Sum_HOU!V:V) -> 30 | E17: =MAX(0,MIN(_xlfn.XLOOKUP(A17,Sum_HOU!A:A,Sum_HOU!L:L),_xlfn.XLOOKUP(A17,Sum_HOU!A:A,Sum_HOU!M:M)-_xlfn.XLOOKUP(A17,Sum_HOU!A:A,Sum_HOU!O:O)*(_xlfn.XLOOKUP(A17,Sum_HOU!A:A,Sum_HOU!R:R)+_xlfn.XLOOKUP(A17,Sum_HOU!A:A,Sum_HOU!S:S)+2)-_xlfn.XLOOKUP(A17,Sum_HOU!A:A,Sum_HOU!T:T))) -> 0 | F17: =_xlfn.XLOOKUP(A17,Sum!A:A,Sum!Y:Y) -> 30 | G17: =_xlfn.XLOOKUP(A17,Sum!A:A,Sum!AA:AA) -> B | H17: =ROUNDDOWN(MIN(D17,C17)/F17,0)*F17 -> 30 | I17: =_xlfn.XLOOKUP(G17,'Case Type'!A:A,'Case Type'!H:H)*(H17/F17) -> 0.073414047 | J17: =ROUNDDOWN(MIN(B17,E17)/F17,0)*F17 -> 0 | K17: =_xlfn.XLOOKUP(G17,'Case Type'!A:A,'Case Type'!H:H)*(J17/F17) -> 0 | V17: =IF(AND(ISNUMBER(T17),T17>0,T17<=TODAY(),ISNUMBER(R17),R17>0,COUNTIF(Sum!A:A,O17)>0,P17<>Q17,OR(P17="LA",P17="HOU"),OR(Q17="LA",Q17="HOU")),R17,0) -> 0 | W17: =IF(AND(V17>0,ISNUMBER(U17),U17>=T17,U17<=TODAY(),ISNUMBER(S17),S17>0,S17<=V17),S17,0) -> 0 | X17: =IF(O17="","",IF(COUNTIF(Sum!A:A,O17)=0,"SKU不存在",IF(OR(P17=Q17,AND(P17<>"LA",P17<>"HOU"),AND(Q17<>"LA",Q17<>"HOU")),"仓库错误",IF(AND(ISNUMBER(S17),S17>R17),"收货超过发出",IF(AND(ISNUMBER(U17),OR(NOT(ISNUMBER(T17)),U17<T17)),"收发日期错误","")))))
A18: =Sum!A17 -> CPWJ0015 | B18: =_xlfn.XLOOKUP(A18,Sum_LA!A:A,Sum_LA!V:V) -> 0 | C18: =MAX(0,MIN(_xlfn.XLOOKUP(A18,Sum_LA!A:A,Sum_LA!L:L),_xlfn.XLOOKUP(A18,Sum_LA!A:A,Sum_LA!M:M)-_xlfn.XLOOKUP(A18,Sum_LA!A:A,Sum_LA!O:O)*(_xlfn.XLOOKUP(A18,Sum_LA!A:A,Sum_LA!R:R)+_xlfn.XLOOKUP(A18,Sum_LA!A:A,Sum_LA!S:S)+2)-_xlfn.XLOOKUP(A18,Sum_LA!A:A,Sum_LA!T:T))) -> 0 | D18: =_xlfn.XLOOKUP(A18,Sum_HOU!A:A,Sum_HOU!V:V) -> 120 | E18: =MAX(0,MIN(_xlfn.XLOOKUP(A18,Sum_HOU!A:A,Sum_HOU!L:L),_xlfn.XLOOKUP(A18,Sum_HOU!A:A,Sum_HOU!M:M)-_xlfn.XLOOKUP(A18,Sum_HOU!A:A,Sum_HOU!O:O)*(_xlfn.XLOOKUP(A18,Sum_HOU!A:A,Sum_HOU!R:R)+_xlfn.XLOOKUP(A18,Sum_HOU!A:A,Sum_HOU!S:S)+2)-_xlfn.XLOOKUP(A18,Sum_HOU!A:A,Sum_HOU!T:T))) -> 0 | F18: =_xlfn.XLOOKUP(A18,Sum!A:A,Sum!Y:Y) -> 30 | G18: =_xlfn.XLOOKUP(A18,Sum!A:A,Sum!AA:AA) -> C | H18: =ROUNDDOWN(MIN(D18,C18)/F18,0)*F18 -> 0 | I18: =_xlfn.XLOOKUP(G18,'Case Type'!A:A,'Case Type'!H:H)*(H18/F18) -> 0 | J18: =ROUNDDOWN(MIN(B18,E18)/F18,0)*F18 -> 0 | K18: =_xlfn.XLOOKUP(G18,'Case Type'!A:A,'Case Type'!H:H)*(J18/F18) -> 0 | V18: =IF(AND(ISNUMBER(T18),T18>0,T18<=TODAY(),ISNUMBER(R18),R18>0,COUNTIF(Sum!A:A,O18)>0,P18<>Q18,OR(P18="LA",P18="HOU"),OR(Q18="LA",Q18="HOU")),R18,0) -> 0 | W18: =IF(AND(V18>0,ISNUMBER(U18),U18>=T18,U18<=TODAY(),ISNUMBER(S18),S18>0,S18<=V18),S18,0) -> 0 | X18: =IF(O18="","",IF(COUNTIF(Sum!A:A,O18)=0,"SKU不存在",IF(OR(P18=Q18,AND(P18<>"LA",P18<>"HOU"),AND(Q18<>"LA",Q18<>"HOU")),"仓库错误",IF(AND(ISNUMBER(S18),S18>R18),"收货超过发出",IF(AND(ISNUMBER(U18),OR(NOT(ISNUMBER(T18)),U18<T18)),"收发日期错误","")))))
A19: =Sum!A18 -> CPWJ0018 | B19: =_xlfn.XLOOKUP(A19,Sum_LA!A:A,Sum_LA!V:V) -> 0 | C19: =MAX(0,MIN(_xlfn.XLOOKUP(A19,Sum_LA!A:A,Sum_LA!L:L),_xlfn.XLOOKUP(A19,Sum_LA!A:A,Sum_LA!M:M)-_xlfn.XLOOKUP(A19,Sum_LA!A:A,Sum_LA!O:O)*(_xlfn.XLOOKUP(A19,Sum_LA!A:A,Sum_LA!R:R)+_xlfn.XLOOKUP(A19,Sum_LA!A:A,Sum_LA!S:S)+2)-_xlfn.XLOOKUP(A19,Sum_LA!A:A,Sum_LA!T:T))) -> 1314.5 | D19: =_xlfn.XLOOKUP(A19,Sum_HOU!A:A,Sum_HOU!V:V) -> 0 | E19: =MAX(0,MIN(_xlfn.XLOOKUP(A19,Sum_HOU!A:A,Sum_HOU!L:L),_xlfn.XLOOKUP(A19,Sum_HOU!A:A,Sum_HOU!M:M)-_xlfn.XLOOKUP(A19,Sum_HOU!A:A,Sum_HOU!O:O)*(_xlfn.XLOOKUP(A19,Sum_HOU!A:A,Sum_HOU!R:R)+_xlfn.XLOOKUP(A19,Sum_HOU!A:A,Sum_HOU!S:S)+2)-_xlfn.XLOOKUP(A19,Sum_HOU!A:A,Sum_HOU!T:T))) -> 0 | F19: =_xlfn.XLOOKUP(A19,Sum!A:A,Sum!Y:Y) -> 48 | G19: =_xlfn.XLOOKUP(A19,Sum!A:A,Sum!AA:AA) -> A | H19: =ROUNDDOWN(MIN(D19,C19)/F19,0)*F19 -> 0 | I19: =_xlfn.XLOOKUP(G19,'Case Type'!A:A,'Case Type'!H:H)*(H19/F19) -> 0 | J19: =ROUNDDOWN(MIN(B19,E19)/F19,0)*F19 -> 0 | K19: =_xlfn.XLOOKUP(G19,'Case Type'!A:A,'Case Type'!H:H)*(J19/F19) -> 0 | V19: =IF(AND(ISNUMBER(T19),T19>0,T19<=TODAY(),ISNUMBER(R19),R19>0,COUNTIF(Sum!A:A,O19)>0,P19<>Q19,OR(P19="LA",P19="HOU"),OR(Q19="LA",Q19="HOU")),R19,0) -> 0 | W19: =IF(AND(V19>0,ISNUMBER(U19),U19>=T19,U19<=TODAY(),ISNUMBER(S19),S19>0,S19<=V19),S19,0) -> 0 | X19: =IF(O19="","",IF(COUNTIF(Sum!A:A,O19)=0,"SKU不存在",IF(OR(P19=Q19,AND(P19<>"LA",P19<>"HOU"),AND(Q19<>"LA",Q19<>"HOU")),"仓库错误",IF(AND(ISNUMBER(S19),S19>R19),"收货超过发出",IF(AND(ISNUMBER(U19),OR(NOT(ISNUMBER(T19)),U19<T19)),"收发日期错误","")))))
A20: =Sum!A19 -> CPWJ162000PK | B20: =_xlfn.XLOOKUP(A20,Sum_LA!A:A,Sum_LA!V:V) -> 0 | C20: =MAX(0,MIN(_xlfn.XLOOKUP(A20,Sum_LA!A:A,Sum_LA!L:L),_xlfn.XLOOKUP(A20,Sum_LA!A:A,Sum_LA!M:M)-_xlfn.XLOOKUP(A20,Sum_LA!A:A,Sum_LA!O:O)*(_xlfn.XLOOKUP(A20,Sum_LA!A:A,Sum_LA!R:R)+_xlfn.XLOOKUP(A20,Sum_LA!A:A,Sum_LA!S:S)+2)-_xlfn.XLOOKUP(A20,Sum_LA!A:A,Sum_LA!T:T))) -> 2313.125 | D20: =_xlfn.XLOOKUP(A20,Sum_HOU!A:A,Sum_HOU!V:V) -> 0 | E20: =MAX(0,MIN(_xlfn.XLOOKUP(A20,Sum_HOU!A:A,Sum_HOU!L:L),_xlfn.XLOOKUP(A20,Sum_HOU!A:A,Sum_HOU!M:M)-_xlfn.XLOOKUP(A20,Sum_HOU!A:A,Sum_HOU!O:O)*(_xlfn.XLOOKUP(A20,Sum_HOU!A:A,Sum_HOU!R:R)+_xlfn.XLOOKUP(A20,Sum_HOU!A:A,Sum_HOU!S:S)+2)-_xlfn.XLOOKUP(A20,Sum_HOU!A:A,Sum_HOU!T:T))) -> 0 | F20: =_xlfn.XLOOKUP(A20,Sum!A:A,Sum!Y:Y) -> 45 | G20: =_xlfn.XLOOKUP(A20,Sum!A:A,Sum!AA:AA) -> B | H20: =ROUNDDOWN(MIN(D20,C20)/F20,0)*F20 -> 0 | I20: =_xlfn.XLOOKUP(G20,'Case Type'!A:A,'Case Type'!H:H)*(H20/F20) -> 0 | J20: =ROUNDDOWN(MIN(B20,E20)/F20,0)*F20 -> 0 | K20: =_xlfn.XLOOKUP(G20,'Case Type'!A:A,'Case Type'!H:H)*(J20/F20) -> 0 | V20: =IF(AND(ISNUMBER(T20),T20>0,T20<=TODAY(),ISNUMBER(R20),R20>0,COUNTIF(Sum!A:A,O20)>0,P20<>Q20,OR(P20="LA",P20="HOU"),OR(Q20="LA",Q20="HOU")),R20,0) -> 0 | W20: =IF(AND(V20>0,ISNUMBER(U20),U20>=T20,U20<=TODAY(),ISNUMBER(S20),S20>0,S20<=V20),S20,0) -> 0 | X20: =IF(O20="","",IF(COUNTIF(Sum!A:A,O20)=0,"SKU不存在",IF(OR(P20=Q20,AND(P20<>"LA",P20<>"HOU"),AND(Q20<>"LA",Q20<>"HOU")),"仓库错误",IF(AND(ISNUMBER(S20),S20>R20),"收货超过发出",IF(AND(ISNUMBER(U20),OR(NOT(ISNUMBER(T20)),U20<T20)),"收发日期错误","")))))
... A39: =Sum!A38 -> SP-4 | B39: =_xlfn.XLOOKUP(A39,Sum_LA!A:A,Sum_LA!V:V) -> 0 | C39: =MAX(0,MIN(_xlfn.XLOOKUP(A39,Sum_LA!A:A,Sum_LA!L:L),_xlfn.XLOOKUP(A39,Sum_LA!A:A,Sum_LA!M:M)-_xlfn.XLOOKUP(A39,Sum_LA!A:A,Sum_LA!O:O)*(_xlfn.XLOOKUP(A39,Sum_LA!A:A,Sum_LA!R:R)+_xlfn.XLOOKUP(A39,Sum_LA!A:A,Sum_LA!S:S)+2)-_xlfn.XLOOKUP(A39,Sum_LA!A:A,Sum_LA!T:T))) -> 435 | D39: =_xlfn.XLOOKUP(A39,Sum_HOU!A:A,Sum_HOU!V:V) -> 0 | E39: =MAX(0,MIN(_xlfn.XLOOKUP(A39,Sum_HOU!A:A,Sum_HOU!L:L),_xlfn.XLOOKUP(A39,Sum_HOU!A:A,Sum_HOU!M:M)-_xlfn.XLOOKUP(A39,Sum_HOU!A:A,Sum_HOU!O:O)*(_xlfn.XLOOKUP(A39,Sum_HOU!A:A,Sum_HOU!R:R)+_xlfn.XLOOKUP(A39,Sum_HOU!A:A,Sum_HOU!S:S)+2)-_xlfn.XLOOKUP(A39,Sum_HOU!A:A,Sum_HOU!T:T))) -> 0 | F39: =_xlfn.XLOOKUP(A39,Sum!A:A,Sum!Y:Y) -> 1 | G39: =_xlfn.XLOOKUP(A39,Sum!A:A,Sum!AA:AA) -> S3 | H39: =ROUNDDOWN(MIN(D39,C39)/F39,0)*F39 -> 0 | I39: =_xlfn.XLOOKUP(G39,'Case Type'!A:A,'Case Type'!H:H)*(H39/F39) -> 0 | J39: =ROUNDDOWN(MIN(B39,E39)/F39,0)*F39 -> 0 | K39: =_xlfn.XLOOKUP(G39,'Case Type'!A:A,'Case Type'!H:H)*(J39/F39) -> 0 | V39: =IF(AND(ISNUMBER(T39),T39>0,T39<=TODAY(),ISNUMBER(R39),R39>0,COUNTIF(Sum!A:A,O39)>0,P39<>Q39,OR(P39="LA",P39="HOU"),OR(Q39="LA",Q39="HOU")),R39,0) -> 0 | W39: =IF(AND(V39>0,ISNUMBER(U39),U39>=T39,U39<=TODAY(),ISNUMBER(S39),S39>0,S39<=V39),S39,0) -> 0 | X39: =IF(O39="","",IF(COUNTIF(Sum!A:A,O39)=0,"SKU不存在",IF(OR(P39=Q39,AND(P39<>"LA",P39<>"HOU"),AND(Q39<>"LA",Q39<>"HOU")),"仓库错误",IF(AND(ISNUMBER(S39),S39>R39),"收货超过发出",IF(AND(ISNUMBER(U39),OR(NOT(ISNUMBER(T39)),U39<T39)),"收发日期错误","")))))
A40: =Sum!A39 -> SP-7 | B40: =_xlfn.XLOOKUP(A40,Sum_LA!A:A,Sum_LA!V:V) -> 0 | C40: =MAX(0,MIN(_xlfn.XLOOKUP(A40,Sum_LA!A:A,Sum_LA!L:L),_xlfn.XLOOKUP(A40,Sum_LA!A:A,Sum_LA!M:M)-_xlfn.XLOOKUP(A40,Sum_LA!A:A,Sum_LA!O:O)*(_xlfn.XLOOKUP(A40,Sum_LA!A:A,Sum_LA!R:R)+_xlfn.XLOOKUP(A40,Sum_LA!A:A,Sum_LA!S:S)+2)-_xlfn.XLOOKUP(A40,Sum_LA!A:A,Sum_LA!T:T))) -> 0 | D40: =_xlfn.XLOOKUP(A40,Sum_HOU!A:A,Sum_HOU!V:V) -> 0 | E40: =MAX(0,MIN(_xlfn.XLOOKUP(A40,Sum_HOU!A:A,Sum_HOU!L:L),_xlfn.XLOOKUP(A40,Sum_HOU!A:A,Sum_HOU!M:M)-_xlfn.XLOOKUP(A40,Sum_HOU!A:A,Sum_HOU!O:O)*(_xlfn.XLOOKUP(A40,Sum_HOU!A:A,Sum_HOU!R:R)+_xlfn.XLOOKUP(A40,Sum_HOU!A:A,Sum_HOU!S:S)+2)-_xlfn.XLOOKUP(A40,Sum_HOU!A:A,Sum_HOU!T:T))) -> 0 | F40: =_xlfn.XLOOKUP(A40,Sum!A:A,Sum!Y:Y) -> 18 | G40: =_xlfn.XLOOKUP(A40,Sum!A:A,Sum!AA:AA) -> C | H40: =ROUNDDOWN(MIN(D40,C40)/F40,0)*F40 -> 0 | I40: =_xlfn.XLOOKUP(G40,'Case Type'!A:A,'Case Type'!H:H)*(H40/F40) -> 0 | J40: =ROUNDDOWN(MIN(B40,E40)/F40,0)*F40 -> 0 | K40: =_xlfn.XLOOKUP(G40,'Case Type'!A:A,'Case Type'!H:H)*(J40/F40) -> 0
A41: =Sum!A40 -> SZP542-GN | B41: =_xlfn.XLOOKUP(A41,Sum_LA!A:A,Sum_LA!V:V) -> 0 | C41: =MAX(0,MIN(_xlfn.XLOOKUP(A41,Sum_LA!A:A,Sum_LA!L:L),_xlfn.XLOOKUP(A41,Sum_LA!A:A,Sum_LA!M:M)-_xlfn.XLOOKUP(A41,Sum_LA!A:A,Sum_LA!O:O)*(_xlfn.XLOOKUP(A41,Sum_LA!A:A,Sum_LA!R:R)+_xlfn.XLOOKUP(A41,Sum_LA!A:A,Sum_LA!S:S)+2)-_xlfn.XLOOKUP(A41,Sum_LA!A:A,Sum_LA!T:T))) -> 234 | D41: =_xlfn.XLOOKUP(A41,Sum_HOU!A:A,Sum_HOU!V:V) -> 0 | E41: =MAX(0,MIN(_xlfn.XLOOKUP(A41,Sum_HOU!A:A,Sum_HOU!L:L),_xlfn.XLOOKUP(A41,Sum_HOU!A:A,Sum_HOU!M:M)-_xlfn.XLOOKUP(A41,Sum_HOU!A:A,Sum_HOU!O:O)*(_xlfn.XLOOKUP(A41,Sum_HOU!A:A,Sum_HOU!R:R)+_xlfn.XLOOKUP(A41,Sum_HOU!A:A,Sum_HOU!S:S)+2)-_xlfn.XLOOKUP(A41,Sum_HOU!A:A,Sum_HOU!T:T))) -> 0 | F41: =_xlfn.XLOOKUP(A41,Sum!A:A,Sum!Y:Y) -> 18 | G41: =_xlfn.XLOOKUP(A41,Sum!A:A,Sum!AA:AA) -> B | H41: =ROUNDDOWN(MIN(D41,C41)/F41,0)*F41 -> 0 | I41: =_xlfn.XLOOKUP(G41,'Case Type'!A:A,'Case Type'!H:H)*(H41/F41) -> 0 | J41: =ROUNDDOWN(MIN(B41,E41)/F41,0)*F41 -> 0 | K41: =_xlfn.XLOOKUP(G41,'Case Type'!A:A,'Case Type'!H:H)*(J41/F41) -> 0
A42: =Sum!A41 -> SZP542-WH | B42: =_xlfn.XLOOKUP(A42,Sum_LA!A:A,Sum_LA!V:V) -> 2394 | C42: =MAX(0,MIN(_xlfn.XLOOKUP(A42,Sum_LA!A:A,Sum_LA!L:L),_xlfn.XLOOKUP(A42,Sum_LA!A:A,Sum_LA!M:M)-_xlfn.XLOOKUP(A42,Sum_LA!A:A,Sum_LA!O:O)*(_xlfn.XLOOKUP(A42,Sum_LA!A:A,Sum_LA!R:R)+_xlfn.XLOOKUP(A42,Sum_LA!A:A,Sum_LA!S:S)+2)-_xlfn.XLOOKUP(A42,Sum_LA!A:A,Sum_LA!T:T))) -> 0 | D42: =_xlfn.XLOOKUP(A42,Sum_HOU!A:A,Sum_HOU!V:V) -> 126 | E42: =MAX(0,MIN(_xlfn.XLOOKUP(A42,Sum_HOU!A:A,Sum_HOU!L:L),_xlfn.XLOOKUP(A42,Sum_HOU!A:A,Sum_HOU!M:M)-_xlfn.XLOOKUP(A42,Sum_HOU!A:A,Sum_HOU!O:O)*(_xlfn.XLOOKUP(A42,Sum_HOU!A:A,Sum_HOU!R:R)+_xlfn.XLOOKUP(A42,Sum_HOU!A:A,Sum_HOU!S:S)+2)-_xlfn.XLOOKUP(A42,Sum_HOU!A:A,Sum_HOU!T:T))) -> 0 | F42: =_xlfn.XLOOKUP(A42,Sum!A:A,Sum!Y:Y) -> 42 | G42: =_xlfn.XLOOKUP(A42,Sum!A:A,Sum!AA:AA) -> C | H42: =ROUNDDOWN(MIN(D42,C42)/F42,0)*F42 -> 0 | I42: =_xlfn.XLOOKUP(G42,'Case Type'!A:A,'Case Type'!H:H)*(H42/F42) -> 0 | J42: =ROUNDDOWN(MIN(B42,E42)/F42,0)*F42 -> 0 | K42: =_xlfn.XLOOKUP(G42,'Case Type'!A:A,'Case Type'!H:H)*(J42/F42) -> 0
A43: =Sum!A42 -> T-1-BL | B43: =_xlfn.XLOOKUP(A43,Sum_LA!A:A,Sum_LA!V:V) -> 0 | C43: =MAX(0,MIN(_xlfn.XLOOKUP(A43,Sum_LA!A:A,Sum_LA!L:L),_xlfn.XLOOKUP(A43,Sum_LA!A:A,Sum_LA!M:M)-_xlfn.XLOOKUP(A43,Sum_LA!A:A,Sum_LA!O:O)*(_xlfn.XLOOKUP(A43,Sum_LA!A:A,Sum_LA!R:R)+_xlfn.XLOOKUP(A43,Sum_LA!A:A,Sum_LA!S:S)+2)-_xlfn.XLOOKUP(A43,Sum_LA!A:A,Sum_LA!T:T))) -> 2557.875 | D43: =_xlfn.XLOOKUP(A43,Sum_HOU!A:A,Sum_HOU!V:V) -> 0 | E43: =MAX(0,MIN(_xlfn.XLOOKUP(A43,Sum_HOU!A:A,Sum_HOU!L:L),_xlfn.XLOOKUP(A43,Sum_HOU!A:A,Sum_HOU!M:M)-_xlfn.XLOOKUP(A43,Sum_HOU!A:A,Sum_HOU!O:O)*(_xlfn.XLOOKUP(A43,Sum_HOU!A:A,Sum_HOU!R:R)+_xlfn.XLOOKUP(A43,Sum_HOU!A:A,Sum_HOU!S:S)+2)-_xlfn.XLOOKUP(A43,Sum_HOU!A:A,Sum_HOU!T:T))) -> 0 | F43: =_xlfn.XLOOKUP(A43,Sum!A:A,Sum!Y:Y) -> 30 | G43: =_xlfn.XLOOKUP(A43,Sum!A:A,Sum!AA:AA) -> A | H43: =ROUNDDOWN(MIN(D43,C43)/F43,0)*F43 -> 0 | I43: =_xlfn.XLOOKUP(G43,'Case Type'!A:A,'Case Type'!H:H)*(H43/F43) -> 0 | J43: =ROUNDDOWN(MIN(B43,E43)/F43,0)*F43 -> 0 | K43: =_xlfn.XLOOKUP(G43,'Case Type'!A:A,'Case Type'!H:H)*(J43/F43) -> 0
A44: =Sum!A43 -> T-1-BL-WH | B44: =_xlfn.XLOOKUP(A44,Sum_LA!A:A,Sum_LA!V:V) -> 0 | C44: =MAX(0,MIN(_xlfn.XLOOKUP(A44,Sum_LA!A:A,Sum_LA!L:L),_xlfn.XLOOKUP(A44,Sum_LA!A:A,Sum_LA!M:M)-_xlfn.XLOOKUP(A44,Sum_LA!A:A,Sum_LA!O:O)*(_xlfn.XLOOKUP(A44,Sum_LA!A:A,Sum_LA!R:R)+_xlfn.XLOOKUP(A44,Sum_LA!A:A,Sum_LA!S:S)+2)-_xlfn.XLOOKUP(A44,Sum_LA!A:A,Sum_LA!T:T))) -> 1380 | D44: =_xlfn.XLOOKUP(A44,Sum_HOU!A:A,Sum_HOU!V:V) -> 150 | E44: =MAX(0,MIN(_xlfn.XLOOKUP(A44,Sum_HOU!A:A,Sum_HOU!L:L),_xlfn.XLOOKUP(A44,Sum_HOU!A:A,Sum_HOU!M:M)-_xlfn.XLOOKUP(A44,Sum_HOU!A:A,Sum_HOU!O:O)*(_xlfn.XLOOKUP(A44,Sum_HOU!A:A,Sum_HOU!R:R)+_xlfn.XLOOKUP(A44,Sum_HOU!A:A,Sum_HOU!S:S)+2)-_xlfn.XLOOKUP(A44,Sum_HOU!A:A,Sum_HOU!T:T))) -> 0 | F44: =_xlfn.XLOOKUP(A44,Sum!A:A,Sum!Y:Y) -> 30 | G44: =_xlfn.XLOOKUP(A44,Sum!A:A,Sum!AA:AA) -> A | H44: =ROUNDDOWN(MIN(D44,C44)/F44,0)*F44 -> 150 | I44: =_xlfn.XLOOKUP(G44,'Case Type'!A:A,'Case Type'!H:H)*(H44/F44) -> 0.55060535 | J44: =ROUNDDOWN(MIN(B44,E44)/F44,0)*F44 -> 0 | K44: =_xlfn.XLOOKUP(G44,'Case Type'!A:A,'Case Type'!H:H)*(J44/F44) -> 0
A45: =Sum!A44 -> T-1-BR-WH | B45: =_xlfn.XLOOKUP(A45,Sum_LA!A:A,Sum_LA!V:V) -> 0 | C45: =MAX(0,MIN(_xlfn.XLOOKUP(A45,Sum_LA!A:A,Sum_LA!L:L),_xlfn.XLOOKUP(A45,Sum_LA!A:A,Sum_LA!M:M)-_xlfn.XLOOKUP(A45,Sum_LA!A:A,Sum_LA!O:O)*(_xlfn.XLOOKUP(A45,Sum_LA!A:A,Sum_LA!R:R)+_xlfn.XLOOKUP(A45,Sum_LA!A:A,Sum_LA!S:S)+2)-_xlfn.XLOOKUP(A45,Sum_LA!A:A,Sum_LA!T:T))) -> 930 | D45: =_xlfn.XLOOKUP(A45,Sum_HOU!A:A,Sum_HOU!V:V) -> 30 | E45: =MAX(0,MIN(_xlfn.XLOOKUP(A45,Sum_HOU!A:A,Sum_HOU!L:L),_xlfn.XLOOKUP(A45,Sum_HOU!A:A,Sum_HOU!M:M)-_xlfn.XLOOKUP(A45,Sum_HOU!A:A,Sum_HOU!O:O)*(_xlfn.XLOOKUP(A45,Sum_HOU!A:A,Sum_HOU!R:R)+_xlfn.XLOOKUP(A45,Sum_HOU!A:A,Sum_HOU!S:S)+2)-_xlfn.XLOOKUP(A45,Sum_HOU!A:A,Sum_HOU!T:T))) -> 0 | F45: =_xlfn.XLOOKUP(A45,Sum!A:A,Sum!Y:Y) -> 30 | G45: =_xlfn.XLOOKUP(A45,Sum!A:A,Sum!AA:AA) -> A | H45: =ROUNDDOWN(MIN(D45,C45)/F45,0)*F45 -> 30 | I45: =_xlfn.XLOOKUP(G45,'Case Type'!A:A,'Case Type'!H:H)*(H45/F45) -> 0.11012107 | J45: =ROUNDDOWN(MIN(B45,E45)/F45,0)*F45 -> 0 | K45: =_xlfn.XLOOKUP(G45,'Case Type'!A:A,'Case Type'!H:H)*(J45/F45) -> 0
A46: =Sum!A45 -> T-1-PK | B46: =_xlfn.XLOOKUP(A46,Sum_LA!A:A,Sum_LA!V:V) -> 0 | C46: =MAX(0,MIN(_xlfn.XLOOKUP(A46,Sum_LA!A:A,Sum_LA!L:L),_xlfn.XLOOKUP(A46,Sum_LA!A:A,Sum_LA!M:M)-_xlfn.XLOOKUP(A46,Sum_LA!A:A,Sum_LA!O:O)*(_xlfn.XLOOKUP(A46,Sum_LA!A:A,Sum_LA!R:R)+_xlfn.XLOOKUP(A46,Sum_LA!A:A,Sum_LA!S:S)+2)-_xlfn.XLOOKUP(A46,Sum_LA!A:A,Sum_LA!T:T))) -> 600 | D46: =_xlfn.XLOOKUP(A46,Sum_HOU!A:A,Sum_HOU!V:V) -> 30 | E46: =MAX(0,MIN(_xlfn.XLOOKUP(A46,Sum_HOU!A:A,Sum_HOU!L:L),_xlfn.XLOOKUP(A46,Sum_HOU!A:A,Sum_HOU!M:M)-_xlfn.XLOOKUP(A46,Sum_HOU!A:A,Sum_HOU!O:O)*(_xlfn.XLOOKUP(A46,Sum_HOU!A:A,Sum_HOU!R:R)+_xlfn.XLOOKUP(A46,Sum_HOU!A:A,Sum_HOU!S:S)+2)-_xlfn.XLOOKUP(A46,Sum_HOU!A:A,Sum_HOU!T:T))) -> 0 | F46: =_xlfn.XLOOKUP(A46,Sum!A:A,Sum!Y:Y) -> 30 | G46: =_xlfn.XLOOKUP(A46,Sum!A:A,Sum!AA:AA) -> A | H46: =ROUNDDOWN(MIN(D46,C46)/F46,0)*F46 -> 30 | I46: =_xlfn.XLOOKUP(G46,'Case Type'!A:A,'Case Type'!H:H)*(H46/F46) -> 0.11012107 | J46: =ROUNDDOWN(MIN(B46,E46)/F46,0)*F46 -> 0 | K46: =_xlfn.XLOOKUP(G46,'Case Type'!A:A,'Case Type'!H:H)*(J46/F46) -> 0
A47: =Sum!A46 -> T-41 | B47: =_xlfn.XLOOKUP(A47,Sum_LA!A:A,Sum_LA!V:V) -> 0 | C47: =MAX(0,MIN(_xlfn.XLOOKUP(A47,Sum_LA!A:A,Sum_LA!L:L),_xlfn.XLOOKUP(A47,Sum_LA!A:A,Sum_LA!M:M)-_xlfn.XLOOKUP(A47,Sum_LA!A:A,Sum_LA!O:O)*(_xlfn.XLOOKUP(A47,Sum_LA!A:A,Sum_LA!R:R)+_xlfn.XLOOKUP(A47,Sum_LA!A:A,Sum_LA!S:S)+2)-_xlfn.XLOOKUP(A47,Sum_LA!A:A,Sum_LA!T:T))) -> 540 | D47: =_xlfn.XLOOKUP(A47,Sum_HOU!A:A,Sum_HOU!V:V) -> 60 | E47: =MAX(0,MIN(_xlfn.XLOOKUP(A47,Sum_HOU!A:A,Sum_HOU!L:L),_xlfn.XLOOKUP(A47,Sum_HOU!A:A,Sum_HOU!M:M)-_xlfn.XLOOKUP(A47,Sum_HOU!A:A,Sum_HOU!O:O)*(_xlfn.XLOOKUP(A47,Sum_HOU!A:A,Sum_HOU!R:R)+_xlfn.XLOOKUP(A47,Sum_HOU!A:A,Sum_HOU!S:S)+2)-_xlfn.XLOOKUP(A47,Sum_HOU!A:A,Sum_HOU!T:T))) -> 0 | F47: =_xlfn.XLOOKUP(A47,Sum!A:A,Sum!Y:Y) -> 60 | G47: =_xlfn.XLOOKUP(A47,Sum!A:A,Sum!AA:AA) -> B | H47: =ROUNDDOWN(MIN(D47,C47)/F47,0)*F47 -> 60 | I47: =_xlfn.XLOOKUP(G47,'Case Type'!A:A,'Case Type'!H:H)*(H47/F47) -> 0.073414047 | J47: =ROUNDDOWN(MIN(B47,E47)/F47,0)*F47 -> 0 | K47: =_xlfn.XLOOKUP(G47,'Case Type'!A:A,'Case Type'!H:H)*(J47/F47) -> 0
A48: =Sum!A47 -> WJ-13 | B48: =_xlfn.XLOOKUP(A48,Sum_LA!A:A,Sum_LA!V:V) -> 0 | C48: =MAX(0,MIN(_xlfn.XLOOKUP(A48,Sum_LA!A:A,Sum_LA!L:L),_xlfn.XLOOKUP(A48,Sum_LA!A:A,Sum_LA!M:M)-_xlfn.XLOOKUP(A48,Sum_LA!A:A,Sum_LA!O:O)*(_xlfn.XLOOKUP(A48,Sum_LA!A:A,Sum_LA!R:R)+_xlfn.XLOOKUP(A48,Sum_LA!A:A,Sum_LA!S:S)+2)-_xlfn.XLOOKUP(A48,Sum_LA!A:A,Sum_LA!T:T))) -> 852 | D48: =_xlfn.XLOOKUP(A48,Sum_HOU!A:A,Sum_HOU!V:V) -> 1422 | E48: =MAX(0,MIN(_xlfn.XLOOKUP(A48,Sum_HOU!A:A,Sum_HOU!L:L),_xlfn.XLOOKUP(A48,Sum_HOU!A:A,Sum_HOU!M:M)-_xlfn.XLOOKUP(A48,Sum_HOU!A:A,Sum_HOU!O:O)*(_xlfn.XLOOKUP(A48,Sum_HOU!A:A,Sum_HOU!R:R)+_xlfn.XLOOKUP(A48,Sum_HOU!A:A,Sum_HOU!S:S)+2)-_xlfn.XLOOKUP(A48,Sum_HOU!A:A,Sum_HOU!T:T))) -> 0 | F48: =_xlfn.XLOOKUP(A48,Sum!A:A,Sum!Y:Y) -> 18 | G48: =_xlfn.XLOOKUP(A48,Sum!A:A,Sum!AA:AA) -> B | H48: =ROUNDDOWN(MIN(D48,C48)/F48,0)*F48 -> 846 | I48: =_xlfn.XLOOKUP(G48,'Case Type'!A:A,'Case Type'!H:H)*(H48/F48) -> 3.4504602 | J48: =ROUNDDOWN(MIN(B48,E48)/F48,0)*F48 -> 0 | K48: =_xlfn.XLOOKUP(G48,'Case Type'!A:A,'Case Type'!H:H)*(J48/F48) -> 0
A49: =Sum!A48 -> WJ-14-B | B49: =_xlfn.XLOOKUP(A49,Sum_LA!A:A,Sum_LA!V:V) -> 0 | C49: =MAX(0,MIN(_xlfn.XLOOKUP(A49,Sum_LA!A:A,Sum_LA!L:L),_xlfn.XLOOKUP(A49,Sum_LA!A:A,Sum_LA!M:M)-_xlfn.XLOOKUP(A49,Sum_LA!A:A,Sum_LA!O:O)*(_xlfn.XLOOKUP(A49,Sum_LA!A:A,Sum_LA!R:R)+_xlfn.XLOOKUP(A49,Sum_LA!A:A,Sum_LA!S:S)+2)-_xlfn.XLOOKUP(A49,Sum_LA!A:A,Sum_LA!T:T))) -> 648 | D49: =_xlfn.XLOOKUP(A49,Sum_HOU!A:A,Sum_HOU!V:V) -> 72 | E49: =MAX(0,MIN(_xlfn.XLOOKUP(A49,Sum_HOU!A:A,Sum_HOU!L:L),_xlfn.XLOOKUP(A49,Sum_HOU!A:A,Sum_HOU!M:M)-_xlfn.XLOOKUP(A49,Sum_HOU!A:A,Sum_HOU!O:O)*(_xlfn.XLOOKUP(A49,Sum_HOU!A:A,Sum_HOU!R:R)+_xlfn.XLOOKUP(A49,Sum_HOU!A:A,Sum_HOU!S:S)+2)-_xlfn.XLOOKUP(A49,Sum_HOU!A:A,Sum_HOU!T:T))) -> 0 | F49: =_xlfn.XLOOKUP(A49,Sum!A:A,Sum!Y:Y) -> 18 | G49: =_xlfn.XLOOKUP(A49,Sum!A:A,Sum!AA:AA) -> C | H49: =ROUNDDOWN(MIN(D49,C49)/F49,0)*F49 -> 72 | I49: =_xlfn.XLOOKUP(G49,'Case Type'!A:A,'Case Type'!H:H)*(H49/F49) -> 0.62926326 | J49: =ROUNDDOWN(MIN(B49,E49)/F49,0)*F49 -> 0 | K49: =_xlfn.XLOOKUP(G49,'Case Type'!A:A,'Case Type'!H:H)*(J49/F49) -> 0
A50: =Sum!A49 -> WJ-39-GN | B50: =_xlfn.XLOOKUP(A50,Sum_LA!A:A,Sum_LA!V:V) -> 0 | C50: =MAX(0,MIN(_xlfn.XLOOKUP(A50,Sum_LA!A:A,Sum_LA!L:L),_xlfn.XLOOKUP(A50,Sum_LA!A:A,Sum_LA!M:M)-_xlfn.XLOOKUP(A50,Sum_LA!A:A,Sum_LA!O:O)*(_xlfn.XLOOKUP(A50,Sum_LA!A:A,Sum_LA!R:R)+_xlfn.XLOOKUP(A50,Sum_LA!A:A,Sum_LA!S:S)+2)-_xlfn.XLOOKUP(A50,Sum_LA!A:A,Sum_LA!T:T))) -> 807 | D50: =_xlfn.XLOOKUP(A50,Sum_HOU!A:A,Sum_HOU!V:V) -> 12 | E50: =MAX(0,MIN(_xlfn.XLOOKUP(A50,Sum_HOU!A:A,Sum_HOU!L:L),_xlfn.XLOOKUP(A50,Sum_HOU!A:A,Sum_HOU!M:M)-_xlfn.XLOOKUP(A50,Sum_HOU!A:A,Sum_HOU!O:O)*(_xlfn.XLOOKUP(A50,Sum_HOU!A:A,Sum_HOU!R:R)+_xlfn.XLOOKUP(A50,Sum_HOU!A:A,Sum_HOU!S:S)+2)-_xlfn.XLOOKUP(A50,Sum_HOU!A:A,Sum_HOU!T:T))) -> 0 | F50: =_xlfn.XLOOKUP(A50,Sum!A:A,Sum!Y:Y) -> 4 | G50: =_xlfn.XLOOKUP(A50,Sum!A:A,Sum!AA:AA) -> D | H50: =ROUNDDOWN(MIN(D50,C50)/F50,0)*F50 -> 12 | I50: =_xlfn.XLOOKUP(G50,'Case Type'!A:A,'Case Type'!H:H)*(H50/F50) -> 0.26430915 | J50: =ROUNDDOWN(MIN(B50,E50)/F50,0)*F50 -> 0 | K50: =_xlfn.XLOOKUP(G50,'Case Type'!A:A,'Case Type'!H:H)*(J50/F50) -> 0
A51: =Sum!A50 -> WJ-39-PK | B51: =_xlfn.XLOOKUP(A51,Sum_LA!A:A,Sum_LA!V:V) -> 0 | C51: =MAX(0,MIN(_xlfn.XLOOKUP(A51,Sum_LA!A:A,Sum_LA!L:L),_xlfn.XLOOKUP(A51,Sum_LA!A:A,Sum_LA!M:M)-_xlfn.XLOOKUP(A51,Sum_LA!A:A,Sum_LA!O:O)*(_xlfn.XLOOKUP(A51,Sum_LA!A:A,Sum_LA!R:R)+_xlfn.XLOOKUP(A51,Sum_LA!A:A,Sum_LA!S:S)+2)-_xlfn.XLOOKUP(A51,Sum_LA!A:A,Sum_LA!T:T))) -> 642 | D51: =_xlfn.XLOOKUP(A51,Sum_HOU!A:A,Sum_HOU!V:V) -> 392 | E51: =MAX(0,MIN(_xlfn.XLOOKUP(A51,Sum_HOU!A:A,Sum_HOU!L:L),_xlfn.XLOOKUP(A51,Sum_HOU!A:A,Sum_HOU!M:M)-_xlfn.XLOOKUP(A51,Sum_HOU!A:A,Sum_HOU!O:O)*(_xlfn.XLOOKUP(A51,Sum_HOU!A:A,Sum_HOU!R:R)+_xlfn.XLOOKUP(A51,Sum_HOU!A:A,Sum_HOU!S:S)+2)-_xlfn.XLOOKUP(A51,Sum_HOU!A:A,Sum_HOU!T:T))) -> 0 | F51: =_xlfn.XLOOKUP(A51,Sum!A:A,Sum!Y:Y) -> 4 | G51: =_xlfn.XLOOKUP(A51,Sum!A:A,Sum!AA:AA) -> D | H51: =ROUNDDOWN(MIN(D51,C51)/F51,0)*F51 -> 392 | I51: =_xlfn.XLOOKUP(G51,'Case Type'!A:A,'Case Type'!H:H)*(H51/F51) -> 8.6340989 | J51: =ROUNDDOWN(MIN(B51,E51)/F51,0)*F51 -> 0 | K51: =_xlfn.XLOOKUP(G51,'Case Type'!A:A,'Case Type'!H:H)*(J51/F51) -> 0
... A63: =Sum!A62 -> ZM1.2-RD-GN | B63: =_xlfn.XLOOKUP(A63,Sum_LA!A:A,Sum_LA!V:V) -> 0 | C63: =MAX(0,MIN(_xlfn.XLOOKUP(A63,Sum_LA!A:A,Sum_LA!L:L),_xlfn.XLOOKUP(A63,Sum_LA!A:A,Sum_LA!M:M)-_xlfn.XLOOKUP(A63,Sum_LA!A:A,Sum_LA!O:O)*(_xlfn.XLOOKUP(A63,Sum_LA!A:A,Sum_LA!R:R)+_xlfn.XLOOKUP(A63,Sum_LA!A:A,Sum_LA!S:S)+2)-_xlfn.XLOOKUP(A63,Sum_LA!A:A,Sum_LA!T:T))) -> 630 | D63: =_xlfn.XLOOKUP(A63,Sum_HOU!A:A,Sum_HOU!V:V) -> 14 | E63: =MAX(0,MIN(_xlfn.XLOOKUP(A63,Sum_HOU!A:A,Sum_HOU!L:L),_xlfn.XLOOKUP(A63,Sum_HOU!A:A,Sum_HOU!M:M)-_xlfn.XLOOKUP(A63,Sum_HOU!A:A,Sum_HOU!O:O)*(_xlfn.XLOOKUP(A63,Sum_HOU!A:A,Sum_HOU!R:R)+_xlfn.XLOOKUP(A63,Sum_HOU!A:A,Sum_HOU!S:S)+2)-_xlfn.XLOOKUP(A63,Sum_HOU!A:A,Sum_HOU!T:T))) -> 0 | F63: =_xlfn.XLOOKUP(A63,Sum!A:A,Sum!Y:Y) -> 14 | G63: =_xlfn.XLOOKUP(A63,Sum!A:A,Sum!AA:AA) -> C | H63: =ROUNDDOWN(MIN(D63,C63)/F63,0)*F63 -> 14 | I63: =_xlfn.XLOOKUP(G63,'Case Type'!A:A,'Case Type'!H:H)*(H63/F63) -> 0.15731581 | J63: =ROUNDDOWN(MIN(B63,E63)/F63,0)*F63 -> 0 | K63: =_xlfn.XLOOKUP(G63,'Case Type'!A:A,'Case Type'!H:H)*(J63/F63) -> 0
A64: =Sum!A63 -> 0

Sheet Purchase
A1: Purchase Date | B1: Product Name | C1: Product Code | D1: UPC | E1: Comment | F1: ORD QTY | G1: Factory Delivery Date | H1: ETD | I1: ETA | J1: AWA | K1: Order Delivery Date | L1: Case Type | M1: Case Pack | N1: Total CTN | O1: Total CBM | P1: BOL | Q1: CTN No. | R1: SEAL No. | S1: Cost | T1: Total value | U1: WH | V1: 备注
A2: 46023 | B2: =_xlfn.XLOOKUP(C2,'Product List'!B:B,'Product List'!I:I) -> MINI/MOE RUFFLE BOWL | C2: WJ-46 | D2: =VLOOKUP(C2,'Product List'!B:C,2,0) -> 850030338969 | E2: Previous | F2: 240 | G2: / | H2: / | I2: 46063 | J2: 46063 | K2: / | L2: {=_xlfn.XLOOKUP(1,('Case Pack'!A:A=C2)*('Case Pack'!F:F<=A2),'Case Pack'!G:G,"未找到箱型")} -> B | M2: {=_xlfn.XLOOKUP(1,('Case Pack'!A:A=C2)*('Case Pack'!F:F<=A2),'Case Pack'!D:D,"未找到箱规")} -> 48 | N2: =F2/M2 -> 5 | O2: =_xlfn.XLOOKUP(L2,'Case Type'!A:A,'Case Type'!H:H)*N2 -> 0.36707023 | P2: / | Q2: / | R2: / | S2: =_xlfn.XLOOKUP(C2,'Product List'!B:B,'Product List'!R:R) -> 1.34 | T2: =S2*F2 -> 321.6 | U2: LA
A3: 46023 | B3: =_xlfn.XLOOKUP(C3,'Product List'!B:B,'Product List'!I:I) -> MINI/MOE WOODLAND POTTY | C3: WJ-9-GN | D3: =VLOOKUP(C3,'Product List'!B:C,2,0) -> 760762457077 | E3: Previous | F3: 756 | G3: / | H3: / | I3: 46063 | J3: 46063 | K3: / | L3: {=_xlfn.XLOOKUP(1,('Case Pack'!A:A=C3)*('Case Pack'!F:F<=A3),'Case Pack'!G:G,"未找到箱规")} -> C | M3: {=_xlfn.XLOOKUP(1,('Case Pack'!A:A=C3)*('Case Pack'!F:F<=A3),'Case Pack'!D:D,"未找到箱规")} -> 36 | N3: =F3/M3 -> 21 | O3: =_xlfn.XLOOKUP(L3,'Case Type'!A:A,'Case Type'!H:H)*N3 -> 3.3036321 | P3: / | Q3: / | R3: / | S3: =_xlfn.XLOOKUP(C3,'Product List'!B:B,'Product List'!R:R) -> 1.19 | T3: =S3*F3 -> 899.64 | U3: LA
A4: 46023 | B4: =_xlfn.XLOOKUP(C4,'Product List'!B:B,'Product List'!I:I) -> MINI/MOE BENDABLE BIRCHWOOD FENCE | C4: R-8 | D4: =VLOOKUP(C4,'Product List'!B:C,2,0) -> 850030338150 | E4: Previous | F4: 1224 | G4: / | H4: / | I4: 46063 | J4: 46063 | K4: / | L4: {=_xlfn.XLOOKUP(1,('Case Pack'!A:A=C4)*('Case Pack'!F:F<=A4),'Case Pack'!G:G,"未找到箱规")} -> F | M4: {=_xlfn.XLOOKUP(1,('Case Pack'!A:A=C4)*('Case Pack'!F:F<=A4),'Case Pack'!D:D,"未找到箱规")} -> 32 | N4: =F4/M4 -> 38.25 | O4: =_xlfn.XLOOKUP(L4,'Case Type'!A:A,'Case Type'!H:H)*N4 -> 1.4040436 | P4: / | Q4: / | R4: / | S4: =_xlfn.XLOOKUP(C4,'Product List'!B:B,'Product List'!R:R) -> 3.4 | T4: =S4*F4 -> 4161.6 | U4: LA
A5: 46023 | B5: =_xlfn.XLOOKUP(C5,'Product List'!B:B,'Product List'!I:I) -> MINI/MOE SILENT CRSTL RUN WHEEL XL 11.5 1EA | C5: WJ-39-PK | D5: =VLOOKUP(C5,'Product List'!B:C,2,0) -> 850030338518 | E5: Previous | F5: 1324 | G5: / | H5: / | I5: 46063 | J5: 46063 | K5: / | L5: {=_xlfn.XLOOKUP(1,('Case Pack'!A:A=C5)*('Case Pack'!F:F<=A5),'Case Pack'!G:G,"未找到箱规")} -> C | M5: {=_xlfn.XLOOKUP(1,('Case Pack'!A:A=C5)*('Case Pack'!F:F<=A5),'Case Pack'!D:D,"未找到箱规")} -> 3 | N5: =F5/M5 -> 441.33333 | O5: =_xlfn.XLOOKUP(L5,'Case Type'!A:A,'Case Type'!H:H)*N5 -> 69.428713 | P5: / | Q5: / | R5: / | S5: =_xlfn.XLOOKUP(C5,'Product List'!B:B,'Product List'!R:R) -> 10.42 | T5: =S5*F5 -> 13796.08 | U5: LA
A6: 46023 | B6: =_xlfn.XLOOKUP(C6,'Product List'!B:B,'Product List'!I:I) -> D. MMO-COTTAGE VIEW CAGE | C6: SP-4 | D6: =VLOOKUP(C6,'Product List'!B:C,2,0) -> 850030338730 | E6: Previous | F6: 761 | G6: / | H6: / | I6: 46063 | J6: 46063 | K6: / | L6: {=_xlfn.XLOOKUP(1,('Case Pack'!A:A=C6)*('Case Pack'!F:F<=A6),'Case Pack'!G:G,"未找到箱规")} -> S3 | M6: {=_xlfn.XLOOKUP(1,('Case Pack'!A:A=C6)*('Case Pack'!F:F<=A6),'Case Pack'!D:D,"未找到箱规")} -> 1 | N6: =F6/M6 -> 761 | O6: =_xlfn.XLOOKUP(L6,'Case Type'!A:A,'Case Type'!H:H)*N6 -> 108.26416 | P6: / | Q6: / | R6: / | S6: =_xlfn.XLOOKUP(C6,'Product List'!B:B,'Product List'!R:R) -> 28.56 | T6: =S6*F6 -> 21734.16 | U6: LA
A7: 46023 | B7: =_xlfn.XLOOKUP(C7,'Product List'!B:B,'Product List'!I:I) -> MINI/MOE TV VIEWING CAGE | C7: HL-4 | D7: =VLOOKUP(C7,'Product List'!B:C,2,0) -> 850030338761 | E7: Previous | F7: 2218 | G7: / | H7: / | I7: 46063 | J7: 46063 | K7: / | L7: {=_xlfn.XLOOKUP(1,('Case Pack'!A:A=C7)*('Case Pack'!F:F<=A7),'Case Pack'!G:G,"未找到箱规")} -> S1 | M7: {=_xlfn.XLOOKUP(1,('Case Pack'!A:A=C7)*('Case Pack'!F:F<=A7),'Case Pack'!D:D,"未找到箱规")} -> 1 | N7: =F7/M7 -> 2218 | O7: =_xlfn.XLOOKUP(L7,'Case Type'!A:A,'Case Type'!H:H)*N7 -> 164.13705 | P7: / | Q7: / | R7: / | S7: =_xlfn.XLOOKUP(C7,'Product List'!B:B,'Product List'!R:R) -> 24.09 | T7: =S7*F7 -> 53431.62 | U7: LA
A8: 46023 | B8: =_xlfn.XLOOKUP(C8,'Product List'!B:B,'Product List'!I:I) -> MINI/MOE TULIP WATER BOTTLE | C8: LT-7-PK | D8: =VLOOKUP(C8,'Product List'!B:C,2,0) -> 850062627567 | E8: Previous | F8: 1260 | G8: / | H8: / | I8: 46063 | J8: 46063 | K8: / | L8: {=_xlfn.XLOOKUP(1,('Case Pack'!A:A=C8)*('Case Pack'!F:F<=A8),'Case Pack'!G:G,"未找到箱规")} -> C | M8: {=_xlfn.XLOOKUP(1,('Case Pack'!A:A=C8)*('Case Pack'!F:F<=A8),'Case Pack'!D:D,"未找到箱规")} -> 60 | N8: =F8/M8 -> 21 | O8: =_xlfn.XLOOKUP(L8,'Case Type'!A:A,'Case Type'!H:H)*N8 -> 3.3036321 | P8: / | Q8: / | R8: / | S8: =_xlfn.XLOOKUP(C8,'Product List'!B:B,'Product List'!R:R) -> 0.73 | T8: =S8*F8 -> 919.8 | U8: LA
A9: 46023 | B9: =_xlfn.XLOOKUP(C9,'Product List'!B:B,'Product List'!I:I) -> MINI/MOE SILENT CRSTL RUN WHEEL LG 8.5-Green | C9: BOBO22-GN | D9: =VLOOKUP(C9,'Product List'!B:C,2,0) -> 698746777135 | E9: Previous | F9: 1820 | G9: / | H9: / | I9: 46063 | J9: 46063 | K9: / | L9: {=_xlfn.XLOOKUP(1,('Case Pack'!A:A=C9)*('Case Pack'!F:F<=A9),'Case Pack'!G:G,"未找到箱规")} -> C | M9: {=_xlfn.XLOOKUP(1,('Case Pack'!A:A=C9)*('Case Pack'!F:F<=A9),'Case Pack'!D:D,"未找到箱规")} -> 8 | N9: =F9/M9 -> 227.5 | O9: =_xlfn.XLOOKUP(L9,'Case Type'!A:A,'Case Type'!H:H)*N9 -> 35.789348 | P9: / | Q9: / | R9: / | S9: =_xlfn.XLOOKUP(C9,'Product List'!B:B,'Product List'!R:R) -> 6.27 | T9: =S9*F9 -> 11411.4 | U9: LA
A10: 46023 | B10: =_xlfn.XLOOKUP(C10,'Product List'!B:B,'Product List'!I:I) -> MMO-COTTON NESTING BALLS | C10: ZM005-BL | D10: =VLOOKUP(C10,'Product List'!B:C,2,0) -> 850030338198 | E10: Previous | F10: 1240 | G10: / | H10: / | I10: 46063 | J10: 46063 | K10: / | L10: {=_xlfn.XLOOKUP(1,('Case Pack'!A:A=C10)*('Case Pack'!F:F<=A10),'Case Pack'!G:G,"未找到箱规")} -> A | M10: {=_xlfn.XLOOKUP(1,('Case Pack'!A:A=C10)*('Case Pack'!F:F<=A10),'Case Pack'!D:D,"未找到箱规")} -> 32 | N10: =F10/M10 -> 38.75 | O10: =_xlfn.XLOOKUP(L10,'Case Type'!A:A,'Case Type'!H:H)*N10 -> 4.2671915 | P10: / | Q10: / | R10: / | S10: =_xlfn.XLOOKUP(C10,'Product List'!B:B,'Product List'!R:R) -> 1.64 | T10: =S10*F10 -> 2033.6 | U10: LA
A11: 46023 | B11: =_xlfn.XLOOKUP(C11,'Product List'!B:B,'Product List'!I:I) -> MMO-BUBBLE WATER BOTTLE | C11: SZP542-WH | D11: =VLOOKUP(C11,'Product List'!B:C,2,0) -> 760762456971 | E11: Previous | F11: 1116 | G11: / | H11: / | I11: 46063 | J11: 46063 | K11: / | L11: {=_xlfn.XLOOKUP(1,('Case Pack'!A:A=C11)*('Case Pack'!F:F<=A11),'Case Pack'!G:G,"未找到箱规")} -> C | M11: {=_xlfn.XLOOKUP(1,('Case Pack'!A:A=C11)*('Case Pack'!F:F<=A11),'Case Pack'!D:D,"未找到箱规")} -> 42 | N11: =F11/M11 -> 26.571429 | O11: =_xlfn.XLOOKUP(L11,'Case Type'!A:A,'Case Type'!H:H)*N11 -> 4.1801059 | P11: / | Q11: / | R11: / | S11: =_xlfn.XLOOKUP(C11,'Product List'!B:B,'Product List'!R:R) -> 3.1 | T11: =S11*F11 -> 3459.6 | U11: LA
A12: 46023 | B12: =_xlfn.XLOOKUP(C12,'Product List'!B:B,'Product List'!I:I) -> MMO-CLOUD WATER BOTTLE | C12: WJ-4 | D12: =VLOOKUP(C12,'Product List'!B:C,2,0) -> 850030338112 | E12: Previous | F12: 1440 | G12: / | H12: / | I12: 46063 | J12: 46063 | K12: / | L12: {=_xlfn.XLOOKUP(1,('Case Pack'!A:A=C12)*('Case Pack'!F:F<=A12),'Case Pack'!G:G,"未找到箱规")} -> A | M12: {=_xlfn.XLOOKUP(1,('Case Pack'!A:A=C12)*('Case Pack'!F:F<=A12),'Case Pack'!D:D,"未找到箱规")} -> 50 | N12: =F12/M12 -> 28.8 | O12: =_xlfn.XLOOKUP(L12,'Case Type'!A:A,'Case Type'!H:H)*N12 -> 3.1714868 | P12: / | Q12: / | R12: / | S12: =_xlfn.XLOOKUP(C12,'Product List'!B:B,'Product List'!R:R) -> 0.62 | T12: =S12*F12 -> 892.8 | U12: LA
A13: 46023 | B13: =_xlfn.XLOOKUP(C13,'Product List'!B:B,'Product List'!I:I) -> MMO-PAPER PEBBLES | C13: ZM003-BL-WH | D13: =VLOOKUP(C13,'Product List'!B:C,2,0) -> 850067049258 | E13: Previous | F13: 1100 | G13: / | H13: / | I13: 46063 | J13: 46063 | K13: / | L13: {=_xlfn.XLOOKUP(1,('Case Pack'!A:A=C13)*('Case Pack'!F:F<=A13),'Case Pack'!G:G,"未找到箱规")} -> B | M13: {=_xlfn.XLOOKUP(1,('Case Pack'!A:A=C13)*('Case Pack'!F:F<=A13),'Case Pack'!D:D,"未找到箱规")} -> 12 | N13: =F13/M13 -> 91.666667 | O13: =_xlfn.XLOOKUP(L13,'Case Type'!A:A,'Case Type'!H:H)*N13 -> 6.7296209 | P13: / | Q13: / | R13: / | S13: =_xlfn.XLOOKUP(C13,'Product List'!B:B,'Product List'!R:R) -> 2.84 | T13: =S13*F13 -> 3124 | U13: LA
A14: 46023 | B14: =_xlfn.XLOOKUP(C14,'Product List'!B:B,'Product List'!I:I) -> MMO-PAPER TWIST BLU/WHT | C14: T-1-BL | D14: =VLOOKUP(C14,'Product List'!B:C,2,0) -> 850030338075 | E14: Previous | F14: 1242 | G14: / | H14: / | I14: 46063 | J14: 46063 | K14: / | L14: {=_xlfn.XLOOKUP(1,('Case Pack'!A:A=C14)*('Case Pack'!F:F<=A14),'Case Pack'!G:G,"未找到箱规")} -> A | M14: {=_xlfn.XLOOKUP(1,('Case Pack'!A:A=C14)*('Case Pack'!F:F<=A14),'Case Pack'!D:D,"未找到箱规")} -> 30 | N14: =F14/M14 -> 41.4 | O14: =_xlfn.XLOOKUP(L14,'Case Type'!A:A,'Case Type'!H:H)*N14 -> 4.5590123 | P14: / | Q14: / | R14: / | S14: =_xlfn.XLOOKUP(C14,'Product List'!B:B,'Product List'!R:R) -> 1.98 | T14: =S14*F14 -> 2459.16 | U14: LA
... A43: 46081 | B43: =_xlfn.XLOOKUP(C43,'Product List'!B:B,'Product List'!I:I) -> MMO-WAVE BRIDGE | C43: R-72 | D43: =VLOOKUP(C43,'Product List'!B:C,2,0) -> 850030338440 | E43: Pre-build for Petco | F43: 429 | G43: / | H43: / | I43: 46160 | J43: 46159 | K43: / | L43: {=_xlfn.XLOOKUP(1,('Case Pack'!A:A=C43)*('Case Pack'!F:F<=A43),'Case Pack'!G:G,"未找到箱规")} -> C | M43: {=_xlfn.XLOOKUP(1,('Case Pack'!A:A=C43)*('Case Pack'!F:F<=A43),'Case Pack'!D:D,"未找到箱规")} -> 33 | N43: =F43/M43 -> 13 | O43: =_xlfn.XLOOKUP(L43,'Case Type'!A:A,'Case Type'!H:H)*N43 -> 2.0451056 | P43: / | Q43: / | R43: / | S43: =_xlfn.XLOOKUP(C43,'Product List'!B:B,'Product List'!R:R) -> 2.79 | T43: =S43*F43 -> 1196.91 | U43: LA
A44: 46081 | B44: =_xlfn.XLOOKUP(C44,'Product List'!B:B,'Product List'!I:I) -> MINI/MOE BENDABLE BIRCHWOOD FENCE | C44: R-8 | D44: =VLOOKUP(C44,'Product List'!B:C,2,0) -> 850030338150 | E44: Pre-build for Petco | F44: 672 | G44: 46162 | H44: 46163 | I44: 46188 | J44: 46191 | K44: / | L44: {=_xlfn.XLOOKUP(1,('Case Pack'!A:A=C44)*('Case Pack'!F:F<=A44),'Case Pack'!G:G,"未找到箱规")} -> F | M44: {=_xlfn.XLOOKUP(1,('Case Pack'!A:A=C44)*('Case Pack'!F:F<=A44),'Case Pack'!D:D,"未找到箱规")} -> 32 | N44: =F44/M44 -> 21 | O44: =_xlfn.XLOOKUP(L44,'Case Type'!A:A,'Case Type'!H:H)*N44 -> 0.77084749 | P44: COSU6501144420 | Q44: CSNU7581329 | R44: CU384480 | S44: =_xlfn.XLOOKUP(C44,'Product List'!B:B,'Product List'!R:R) -> 3.4 | T44: =S44*F44 -> 2284.8 | U44: LA
A45: 46081 | B45: =_xlfn.XLOOKUP(C45,'Product List'!B:B,'Product List'!I:I) -> MMO-STARFISH CASTLE | C45: R-71 | D45: =VLOOKUP(C45,'Product List'!B:C,2,0) -> 850030338433 | E45: Pre-build for Petco | F45: 1840 | G45: 46162 | H45: 46163 | I45: 46188 | J45: 46191 | K45: / | L45: {=_xlfn.XLOOKUP(1,('Case Pack'!A:A=C45)*('Case Pack'!F:F<=A45),'Case Pack'!G:G,"未找到箱规")} -> C | M45: {=_xlfn.XLOOKUP(1,('Case Pack'!A:A=C45)*('Case Pack'!F:F<=A45),'Case Pack'!D:D,"未找到箱规")} -> 20 | N45: =F45/M45 -> 92 | O45: =_xlfn.XLOOKUP(L45,'Case Type'!A:A,'Case Type'!H:H)*N45 -> 14.473055 | P45: COSU6501144420 | Q45: CSNU7581329 | R45: CU384480 | S45: =_xlfn.XLOOKUP(C45,'Product List'!B:B,'Product List'!R:R) -> 2.81 | T45: =S45*F45 -> 5170.4 | U45: LA
A46: 46081 | B46: =_xlfn.XLOOKUP(C46,'Product List'!B:B,'Product List'!I:I) -> MINI/MOE RUFFLE BOWL | C46: WJ-46 | D46: =VLOOKUP(C46,'Product List'!B:C,2,0) -> 850030338969 | E46: Pre-build for Petco | F46: 2976 | G46: 46162 | H46: 46163 | I46: 46188 | J46: 46191 | K46: / | L46: {=_xlfn.XLOOKUP(1,('Case Pack'!A:A=C46)*('Case Pack'!F:F<=A46),'Case Pack'!G:G,"未找到箱规")} -> B | M46: {=_xlfn.XLOOKUP(1,('Case Pack'!A:A=C46)*('Case Pack'!F:F<=A46),'Case Pack'!D:D,"未找到箱规")} -> 48 | N46: =F46/M46 -> 62 | O46: =_xlfn.XLOOKUP(L46,'Case Type'!A:A,'Case Type'!H:H)*N46 -> 4.5516709 | P46: COSU6501144420 | Q46: CSNU7581329 | R46: CU384480 | S46: =_xlfn.XLOOKUP(C46,'Product List'!B:B,'Product List'!R:R) -> 1.34 | T46: =S46*F46 -> 3987.84 | U46: LA
A47: 46081 | B47: =_xlfn.XLOOKUP(C47,'Product List'!B:B,'Product List'!I:I) -> MMO-PAPER PEBBLES | C47: ZM003-BL-WH | D47: =VLOOKUP(C47,'Product List'!B:C,2,0) -> 850067049258 | E47: Pre-build for Petco | F47: 1740 | G47: 46162 | H47: 46163 | I47: 46188 | J47: 46191 | K47: / | L47: {=_xlfn.XLOOKUP(1,('Case Pack'!A:A=C47)*('Case Pack'!F:F<=A47),'Case Pack'!G:G,"未找到箱规")} -> B | M47: {=_xlfn.XLOOKUP(1,('Case Pack'!A:A=C47)*('Case Pack'!F:F<=A47),'Case Pack'!D:D,"未找到箱规")} -> 12 | N47: =F47/M47 -> 145 | O47: =_xlfn.XLOOKUP(L47,'Case Type'!A:A,'Case Type'!H:H)*N47 -> 10.645037 | P47: COSU6501144420 | Q47: CSNU7581329 | R47: CU384480 | S47: =_xlfn.XLOOKUP(C47,'Product List'!B:B,'Product List'!R:R) -> 2.84 | T47: =S47*F47 -> 4941.6 | U47: LA
A48: 46081 | B48: =_xlfn.XLOOKUP(C48,'Product List'!B:B,'Product List'!I:I) -> MMO-PAPER TWIST BLU/WHT | C48: T-1-BL | D48: =VLOOKUP(C48,'Product List'!B:C,2,0) -> 850030338075 | E48: Pre-build for Petco | F48: 1920 | G48: 46162 | H48: 46163 | I48: 46188 | J48: 46191 | K48: / | L48: {=_xlfn.XLOOKUP(1,('Case Pack'!A:A=C48)*('Case Pack'!F:F<=A48),'Case Pack'!G:G,"未找到箱规")} -> A | M48: {=_xlfn.XLOOKUP(1,('Case Pack'!A:A=C48)*('Case Pack'!F:F<=A48),'Case Pack'!D:D,"未找到箱规")} -> 30 | N48: =F48/M48 -> 64 | O48: =_xlfn.XLOOKUP(L48,'Case Type'!A:A,'Case Type'!H:H)*N48 -> 7.0477485 | P48: COSU6501144420 | Q48: CSNU7581329 | R48: CU384480 | S48: =_xlfn.XLOOKUP(C48,'Product List'!B:B,'Product List'!R:R) -> 1.98 | T48: =S48*F48 -> 3801.6 | U48: LA
A49: 46081 | B49: =_xlfn.XLOOKUP(C49,'Product List'!B:B,'Product List'!I:I) -> MMO-COTTON NESTING BALLS | C49: ZM005-BL | D49: =VLOOKUP(C49,'Product List'!B:C,2,0) -> 850030338198 | E49: Pre-build for Petco | F49: 2368 | G49: 46162 | H49: 46163 | I49: 46188 | J49: 46191 | K49: / | L49: {=_xlfn.XLOOKUP(1,('Case Pack'!A:A=C49)*('Case Pack'!F:F<=A49),'Case Pack'!G:G,"未找到箱规")} -> A | M49: {=_xlfn.XLOOKUP(1,('Case Pack'!A:A=C49)*('Case Pack'!F:F<=A49),'Case Pack'!D:D,"未找到箱规")} -> 32 | N49: =F49/M49 -> 74 | O49: =_xlfn.XLOOKUP(L49,'Case Type'!A:A,'Case Type'!H:H)*N49 -> 8.1489592 | P49: COSU6501144420 | Q49: CSNU7581329 | R49: CU384480 | S49: =_xlfn.XLOOKUP(C49,'Product List'!B:B,'Product List'!R:R) -> 1.64 | T49: =S49*F49 -> 3883.52 | U49: LA
A50: 46081 | B50: =_xlfn.XLOOKUP(C50,'Product List'!B:B,'Product List'!I:I) -> MMO-WAVE BRIDGE | C50: R-72 | D50: =VLOOKUP(C50,'Product List'!B:C,2,0) -> 850030338440 | E50: Pre-build for Petco | F50: 2079 | G50: 46157 | H50: 46160 | I50: 46203 | J50: 46183 | K50: / | L50: {=_xlfn.XLOOKUP(1,('Case Pack'!A:A=C50)*('Case Pack'!F:F<=A50),'Case Pack'!G:G,"未找到箱规")} -> C | M50: {=_xlfn.XLOOKUP(1,('Case Pack'!A:A=C50)*('Case Pack'!F:F<=A50),'Case Pack'!D:D,"未找到箱规")} -> 33 | N50: =F50/M50 -> 63 | O50: =_xlfn.XLOOKUP(L50,'Case Type'!A:A,'Case Type'!H:H)*N50 -> 9.9108963 | P50: COSU6500494050 | Q50: HOUU9018554 | R50: CW892817 | S50: =_xlfn.XLOOKUP(C50,'Product List'!B:B,'Product List'!R:R) -> 2.79 | T50: =S50*F50 -> 5800.41 | U50: LA
A51: 46079 | B51: =_xlfn.XLOOKUP(C51,'Product List'!B:B,'Product List'!I:I) -> MINI/MOE TV VIEWING CAGE | C51: HL-4 | D51: =VLOOKUP(C51,'Product List'!B:C,2,0) -> 850030338761 | E51: Pre-build for PSP | F51: 1108 | G51: / | H51: / | I51: 46160 | J51: 46154 | K51: / | L51: {=_xlfn.XLOOKUP(1,('Case Pack'!A:A=C51)*('Case Pack'!F:F<=A51),'Case Pack'!G:G,"未找到箱规")} -> S1 | M51: {=_xlfn.XLOOKUP(1,('Case Pack'!A:A=C51)*('Case Pack'!F:F<=A51),'Case Pack'!D:D,"未找到箱规")} -> 1 | N51: =F51/M51 -> 1108 | O51: =_xlfn.XLOOKUP(L51,'Case Type'!A:A,'Case Type'!H:H)*N51 -> 81.99452 | P51: / | Q51: / | R51: / | S51: =_xlfn.XLOOKUP(C51,'Product List'!B:B,'Product List'!R:R) -> 24.09 | T51: =S51*F51 -> 26691.72 | U51: LA
A52: 46079 | B52: =_xlfn.XLOOKUP(C52,'Product List'!B:B,'Product List'!I:I) -> MINI/MOE SILENT CRSTL RUN WHEEL XL 11.5 1EA | C52: WJ-39-PK | D52: =VLOOKUP(C52,'Product List'!B:C,2,0) -> 850030338518 | E52: Pre-build for PSP | F52: 1260 | G52: / | H52: / | I52: 46160 | J52: 46167 | K52: / | L52: {=_xlfn.XLOOKUP(1,('Case Pack'!A:A=C52)*('Case Pack'!F:F<=A52),'Case Pack'!G:G,"未找到箱规")} -> C | M52: {=_xlfn.XLOOKUP(1,('Case Pack'!A:A=C52)*('Case Pack'!F:F<=A52),'Case Pack'!D:D,"未找到箱规")} -> 3 | N52: =F52/M52 -> 420 | O52: =_xlfn.XLOOKUP(L52,'Case Type'!A:A,'Case Type'!H:H)*N52 -> 66.072642 | P52: / | Q52: / | R52: / | S52: =_xlfn.XLOOKUP(C52,'Product List'!B:B,'Product List'!R:R) -> 10.42 | T52: =S52*F52 -> 13129.2 | U52: LA
A53: 46079 | B53: =_xlfn.XLOOKUP(C53,'Product List'!B:B,'Product List'!I:I) -> D. MMO-COTTAGE VIEW CAGE | C53: SP-4 | D53: =VLOOKUP(C53,'Product List'!B:C,2,0) -> 850030338730 | E53: Pre-build for PSP | F53: 734 | G53: / | H53: / | I53: 46160 | J53: 46154 | K53: / | L53: {=_xlfn.XLOOKUP(1,('Case Pack'!A:A=C53)*('Case Pack'!F:F<=A53),'Case Pack'!G:G,"未找到箱规")} -> S3 | M53: {=_xlfn.XLOOKUP(1,('Case Pack'!A:A=C53)*('Case Pack'!F:F<=A53),'Case Pack'!D:D,"未找到箱规")} -> 1 | N53: =F53/M53 -> 734 | O53: =_xlfn.XLOOKUP(L53,'Case Type'!A:A,'Case Type'!H:H)*N53 -> 104.42299 | P53: / | Q53: / | R53: / | S53: =_xlfn.XLOOKUP(C53,'Product List'!B:B,'Product List'!R:R) -> 28.56 | T53: =S53*F53 -> 20963.04 | U53: LA
A54: 46079 | B54: =_xlfn.XLOOKUP(C54,'Product List'!B:B,'Product List'!I:I) -> MINI/MOE SILENT CRSTL RUN WHEEL LG 8.5-Green | C54: BOBO22-GN | D54: =VLOOKUP(C54,'Product List'!B:C,2,0) -> 698746777135 | E54: Pre-build for PSP | F54: 696 | G54: / | H54: / | I54: 46160 | J54: 46154 | K54: / | L54: {=_xlfn.XLOOKUP(1,('Case Pack'!A:A=C54)*('Case Pack'!F:F<=A54),'Case Pack'!G:G,"未找到箱规")} -> C | M54: {=_xlfn.XLOOKUP(1,('Case Pack'!A:A=C54)*('Case Pack'!F:F<=A54),'Case Pack'!D:D,"未找到箱规")} -> 8 | N54: =F54/M54 -> 87 | O54: =_xlfn.XLOOKUP(L54,'Case Type'!A:A,'Case Type'!H:H)*N54 -> 13.686476 | P54: / | Q54: / | R54: / | S54: =_xlfn.XLOOKUP(C54,'Product List'!B:B,'Product List'!R:R) -> 6.27 | T54: =S54*F54 -> 4363.92 | U54: LA
A55: 46079 | B55: =_xlfn.XLOOKUP(C55,'Product List'!B:B,'Product List'!I:I) -> MINI/MOE WOODLAND POTTY | C55: WJ-9-GN | D55: =VLOOKUP(C55,'Product List'!B:C,2,0) -> 760762457077 | E55: Pre-build for PSP | F55: 792 | G55: / | H55: / | I55: 46160 | J55: 46154 | K55: / | L55: {=_xlfn.XLOOKUP(1,('Case Pack'!A:A=C55)*('Case Pack'!F:F<=A55),'Case Pack'!G:G,"未找到箱规")} -> C | M55: {=_xlfn.XLOOKUP(1,('Case Pack'!A:A=C55)*('Case Pack'!F:F<=A55),'Case Pack'!D:D,"未找到箱规")} -> 36 | N55: =F55/M55 -> 22 | O55: =_xlfn.XLOOKUP(L55,'Case Type'!A:A,'Case Type'!H:H)*N55 -> 3.4609479 | P55: / | Q55: / | R55: / | S55: =_xlfn.XLOOKUP(C55,'Product List'!B:B,'Product List'!R:R) -> 1.19 | T55: =S55*F55 -> 942.48 | U55: LA
A56: 46079 | B56: =_xlfn.XLOOKUP(C56,'Product List'!B:B,'Product List'!I:I) -> MINI/MOE TULIP WATER BOTTLE | C56: LT-7-PK | D56: =VLOOKUP(C56,'Product List'!B:C,2,0) -> 850062627567 | E56: Pre-build for PSP | F56: 1140 | G56: / | H56: / | I56: 46160 | J56: 46154 | K56: / | L56: {=_xlfn.XLOOKUP(1,('Case Pack'!A:A=C56)*('Case Pack'!F:F<=A56),'Case Pack'!G:G,"未找到箱规")} -> C | M56: {=_xlfn.XLOOKUP(1,('Case Pack'!A:A=C56)*('Case Pack'!F:F<=A56),'Case Pack'!D:D,"未找到箱规")} -> 60 | N56: =F56/M56 -> 19 | O56: =_xlfn.XLOOKUP(L56,'Case Type'!A:A,'Case Type'!H:H)*N56 -> 2.9890005 | P56: / | Q56: / | R56: / | S56: =_xlfn.XLOOKUP(C56,'Product List'!B:B,'Product List'!R:R) -> 0.73 | T56: =S56*F56 -> 832.2 | U56: LA
A57: 46079 | B57: =_xlfn.XLOOKUP(C57,'Product List'!B:B,'Product List'!I:I) -> MINI/MOE GARDEN TEAPOT | C57: CPWJ0015 | D57: =VLOOKUP(C57,'Product List'!B:C,2,0) -> 760762457015 | E57: Pre-build for PSP | F57: 210 | G57: / | H57: / | I57: 46160 | J57: 46154 | K57: / | L57: {=_xlfn.XLOOKUP(1,('Case Pack'!A:A=C57)*('Case Pack'!F:F<=A57),'Case Pack'!G:G,"未找到箱规")} -> C | M57: {=_xlfn.XLOOKUP(1,('Case Pack'!A:A=C57)*('Case Pack'!F:F<=A57),'Case Pack'!D:D,"未找到箱规")} -> 30 | N57: =F57/M57 -> 7 | O57: =_xlfn.XLOOKUP(L57,'Case Type'!A:A,'Case Type'!H:H)*N57 -> 1.1012107 | P57: / | Q57: / | R57: / | S57: =_xlfn.XLOOKUP(C57,'Product List'!B:B,'Product List'!R:R) -> 2.25 | T57: =S57*F57 -> 472.5 | U57: LA
A58: 46079 | B58: =_xlfn.XLOOKUP(C58,'Product List'!B:B,'Product List'!I:I) -> MINI/MOE MUSHROOM CABIN | C58: CPWJ0011 | D58: =VLOOKUP(C58,'Product List'!B:C,2,0) -> 760762457008 | E58: Pre-build for PSP | F58: 528 | G58: / | H58: / | I58: 46148 | J58: 46149 | K58: / | L58: {=_xlfn.XLOOKUP(1,('Case Pack'!A:A=C58)*('Case Pack'!F:F<=A58),'Case Pack'!G:G,"未找到箱规")} -> C | M58: {=_xlfn.XLOOKUP(1,('Case Pack'!A:A=C58)*('Case Pack'!F:F<=A58),'Case Pack'!D:D,"未找到箱规")} -> 16 | N58: =F58/M58 -> 33 | O58: =_xlfn.XLOOKUP(L58,'Case Type'!A:A,'Case Type'!H:H)*N58 -> 5.1914219 | P58: / | Q58: / | R58: / | S58: =_xlfn.XLOOKUP(C58,'Product List'!B:B,'Product List'!R:R) -> 3.2 | T58: =S58*F58 -> 1689.6 | U58: LA
A59: 46079 | B59: =_xlfn.XLOOKUP(C59,'Product List'!B:B,'Product List'!I:I) -> MINI/MOE TREEHOUSE CABIN | C59: CPWJ0013 | D59: =VLOOKUP(C59,'Product List'!B:C,2,0) -> 760762457022 | E59: Pre-build for PSP | F59: 570 | G59: / | H59: / | I59: 46148 | J59: 46149 | K59: / | L59: {=_xlfn.XLOOKUP(1,('Case Pack'!A:A=C59)*('Case Pack'!F:F<=A59),'Case Pack'!G:G,"未找到箱规")} -> C | M59: {=_xlfn.XLOOKUP(1,('Case Pack'!A:A=C59)*('Case Pack'!F:F<=A59),'Case Pack'!D:D,"未找到箱规")} -> 30 | N59: =F59/M59 -> 19 | O59: =_xlfn.XLOOKUP(L59,'Case Type'!A:A,'Case Type'!H:H)*N59 -> 2.9890005 | P59: / | Q59: / | R59: / | S59: =_xlfn.XLOOKUP(C59,'Product List'!B:B,'Product List'!R:R) -> 2.07 | T59: =S59*F59 -> 1179.9 | U59: LA
A60: 46079 | B60: =_xlfn.XLOOKUP(C60,'Product List'!B:B,'Product List'!I:I) -> MINI/MOE CAMPING TENT HIDE | C60: WJ-13 | D60: =VLOOKUP(C60,'Product List'!B:C,2,0) -> 850030338082 | E60: Pre-build for PSP | F60: 576 | G60: / | H60: / | I60: 46148 | J60: 46149 | K60: / | L60: {=_xlfn.XLOOKUP(1,('Case Pack'!A:A=C60)*('Case Pack'!F:F<=A60),'Case Pack'!G:G,"未找到箱规")} -> B | M60: {=_xlfn.XLOOKUP(1,('Case Pack'!A:A=C60)*('Case Pack'!F:F<=A60),'Case Pack'!D:D,"未找到箱规")} -> 12 | N60: =F60/M60 -> 48 | O60: =_xlfn.XLOOKUP(L60,'Case Type'!A:A,'Case Type'!H:H)*N60 -> 3.5238742 | P60: / | Q60: / | R60: / | S60: =_xlfn.XLOOKUP(C60,'Product List'!B:B,'Product List'!R:R) -> 1.96 | T60: =S60*F60 -> 1128.96 | U60: LA
A61: 46079 | B61: =_xlfn.XLOOKUP(C61,'Product List'!B:B,'Product List'!I:I) -> MINI/MOE MUSHROOM CABIN | C61: CPWJ0011 | D61: =VLOOKUP(C61,'Product List'!B:C,2,0) -> 760762457008 | E61: Pre-build for PSP | F61: 816 | G61: 46157 | H61: 46160 | I61: 46180 | J61: 46183 | K61: / | L61: {=_xlfn.XLOOKUP(1,('Case Pack'!A:A=C61)*('Case Pack'!F:F<=A61),'Case Pack'!G:G,"未找到箱规")} -> C | M61: {=_xlfn.XLOOKUP(1,('Case Pack'!A:A=C61)*('Case Pack'!F:F<=A61),'Case Pack'!D:D,"未找到箱规")} -> 16 | N61: =F61/M61 -> 51 | O61: =_xlfn.XLOOKUP(L61,'Case Type'!A:A,'Case Type'!H:H)*N61 -> 8.0231065 | P61: COSU6500494050 | Q61: HOUU9018554 | R61: CW892817 | S61: =_xlfn.XLOOKUP(C61,'Product List'!B:B,'Product List'!R:R) -> 3.2 | T61: =S61*F61 -> 2611.2 | U61: LA
A62: 46079 | B62: =_xlfn.XLOOKUP(C62,'Product List'!B:B,'Product List'!I:I) -> MINI/MOE GARDEN TEAPOT | C62: CPWJ0015 | D62: =VLOOKUP(C62,'Product List'!B:C,2,0) -> 760762457015 | E62: Pre-build for PSP | F62: 1230 | G62: 46157 | H62: 46160 | I62: 46180 | J62: 46183 | K62: / | L62: {=_xlfn.XLOOKUP(1,('Case Pack'!A:A=C62)*('Case Pack'!F:F<=A62),'Case Pack'!G:G,"未找到箱规")} -> C | M62: {=_xlfn.XLOOKUP(1,('Case Pack'!A:A=C62)*('Case Pack'!F:F<=A62),'Case Pack'!D:D,"未找到箱规")} -> 30 | N62: =F62/M62 -> 41 | O62: =_xlfn.XLOOKUP(L62,'Case Type'!A:A,'Case Type'!H:H)*N62 -> 6.4499484 | P62: COSU6500494050 | Q62: HOUU9018554 | R62: CW892817 | S62: =_xlfn.XLOOKUP(C62,'Product List'!B:B,'Product List'!R:R) -> 2.25 | T62: =S62*F62 -> 2767.5 | U62: LA
A63: 46079 | B63: =_xlfn.XLOOKUP(C63,'Product List'!B:B,'Product List'!I:I) -> MINI/MOE TREEHOUSE CABIN | C63: CPWJ0013 | D63: =VLOOKUP(C63,'Product List'!B:C,2,0) -> 760762457022 | E63: Pre-build for PSP | F63: 780 | G63: 46157 | H63: 46160 | I63: 46180 | J63: 46183 | K63: / | L63: {=_xlfn.XLOOKUP(1,('Case Pack'!A:A=C63)*('Case Pack'!F:F<=A63),'Case Pack'!G:G,"未找到箱规")} -> C | M63: {=_xlfn.XLOOKUP(1,('Case Pack'!A:A=C63)*('Case Pack'!F:F<=A63),'Case Pack'!D:D,"未找到箱规")} -> 30 | N63: =F63/M63 -> 26 | O63: =_xlfn.XLOOKUP(L63,'Case Type'!A:A,'Case Type'!H:H)*N63 -> 4.0902112 | P63: COSU6500494050 | Q63: HOUU9018554 | R63: CW892817 | S63: =_xlfn.XLOOKUP(C63,'Product List'!B:B,'Product List'!R:R) -> 2.07 | T63: =S63*F63 -> 1614.6 | U63: LA
A64: 46079 | B64: =_xlfn.XLOOKUP(C64,'Product List'!B:B,'Product List'!I:I) -> MINI/MOE IVY BURROWING BOX | C64: CPWJ87000 | D64: =VLOOKUP(C64,'Product List'!B:C,2,0) -> 850030338051 | E64: Pre-build for PSP | F64: 1388 | G64: 46157 | H64: 46160 | I64: 46180 | J64: 46183 | K64: / | L64: {=_xlfn.XLOOKUP(1,('Case Pack'!A:A=C64)*('Case Pack'!F:F<=A64),'Case Pack'!G:G,"未找到箱规")} -> D | M64: {=_xlfn.XLOOKUP(1,('Case Pack'!A:A=C64)*('Case Pack'!F:F<=A64),'Case Pack'!D:D,"未找到箱规")} -> 4 | N64: =F64/M64 -> 347 | O64: =_xlfn.XLOOKUP(L64,'Case Type'!A:A,'Case Type'!H:H)*N64 -> 30.571758 | P64: COSU6500494050 | Q64: HOUU9018554 | R64: CW892817 | S64: =_xlfn.XLOOKUP(C64,'Product List'!B:B,'Product List'!R:R) -> 7.16 | T64: =S64*F64 -> 9938.08 | U64: LA
A65: 46079 | B65: =_xlfn.XLOOKUP(C65,'Product List'!B:B,'Product List'!I:I) -> MINI/MOE CAMPING TENT HIDE | C65: WJ-13 | D65: =VLOOKUP(C65,'Product List'!B:C,2,0) -> 850030338082 | E65: Pre-build for PSP | F65: 912 | G65: 46187 | H65: =IF(P65="","",_xlfn.XLOOKUP(P65,'Shipment Control'!A:A,'Shipment Control'!I:I)) -> 46192 | I65: =IF(P65="",G65+30,_xlfn.XLOOKUP(P65,'Shipment Control'!A:A,'Shipment Control'!J:J)) -> 46218 | J65: 46224 | K65: / | L65: {=_xlfn.XLOOKUP(1,('Case Pack'!A:A=C65)*('Case Pack'!F:F<=A65),'Case Pack'!G:G,"未找到箱规")} -> B | M65: {=_xlfn.XLOOKUP(1,('Case Pack'!A:A=C65)*('Case Pack'!F:F<=A65),'Case Pack'!D:D,"未找到箱规")} -> 12 | N65: =F65/M65 -> 76 | O65: =_xlfn.XLOOKUP(L65,'Case Type'!A:A,'Case Type'!H:H)*N65 -> 5.5794676 | P65: EGLV140601443027 | Q65: EMCU8565150 | R65: EMCFHW4275 | S65: =_xlfn.XLOOKUP(C65,'Product List'!B:B,'Product List'!R:R) -> 1.96 | T65: =S65*F65 -> 1787.52 | U65: LA
A66: 46079 | B66: =_xlfn.XLOOKUP(C66,'Product List'!B:B,'Product List'!I:I) -> MINI/MOE CAMPING TENT HIDE | C66: WJ-13 | D66: =VLOOKUP(C66,'Product List'!B:C,2,0) -> 850030338082 | E66: Pre-build for PSP | F66: 780 | G66: 46157 | H66: 46160 | I66: 46180 | J66: 46183 | K66: / | L66: {=_xlfn.XLOOKUP(1,('Case Pack'!A:A=C66)*('Case Pack'!F:F<=A66),'Case Pack'!G:G,"未找到箱规")} -> B | M66: {=_xlfn.XLOOKUP(1,('Case Pack'!A:A=C66)*('Case Pack'!F:F<=A66),'Case Pack'!D:D,"未找到箱规")} -> 12 | N66: =F66/M66 -> 65 | O66: =_xlfn.XLOOKUP(L66,'Case Type'!A:A,'Case Type'!H:H)*N66 -> 4.771913 | P66: COSU6500494050 | Q66: HOUU9018554 | R66: CW892817 | S66: =_xlfn.XLOOKUP(C66,'Product List'!B:B,'Product List'!R:R) -> 1.96 | T66: =S66*F66 -> 1528.8 | U66: LA
